Workbook

Sheet Lisez-moi
B2: Publications intermédiaires - CGF Gestion
B3: Fichier de suivi à charger dans l'application « Fiche de valeur BRVM », au même titre que le classeur des états financiers et la base de données SMF.
B5: Objet | C5: Suivre, titre par titre, les indicateurs publiés en cours d'exercice : T1 (1er trimestre), S1 (1er semestre) et T3 (3e trimestre). L'application en tire la dynamique de l'exercice en cours : croissance cumulée face à la même période de l'an dernier, tendance d'une publication à l'autre, 12 mois glissants. Cette dynamique s'ajoute aux états financiers complets du dernier exercice clos.
B6: Comment renseigner | C6: 1. Choisissez la feuille « Entreprises » ou « Banques » selon le type du titre (feuille « Titres »). 2. Trouvez la ligne du titre, de l'exercice et de la période, ou ajoutez une ligne sous les dernières. 3. Saisissez les montants de la publication en millions de FCFA, cumulés depuis le 1er janvier. 4. Une publication donne N et N-1 : renseignez aussi la ligne de l'exercice précédent (même période). Les colonnes « Var. ... vs même période N-1 » (à droite, calculées) comparent chaque ligne à la même période de l'exercice précédent. 5. Indiquez le statut, la date de publication et la source (lien richbourse ou brvm.org). 6. Contrôlez la colonne « Contrôle de cohérence » et suivez l'avancement dans « Suivi ».
B7: Cumul et périodes | C7: Toutes les valeurs sont cumulées depuis le 1er janvier : T1 = 3 mois, S1 = 6 mois, T3 = 9 mois. Si une société publie un trimestre isolé, additionnez les trimestres. Les encours bancaires (crédits, dépôts) sont ceux de la fin de période.
B8: Unité et signes | C8: Millions de FCFA. Les charges se saisissent en négatif (frais de gestion, coût du risque). Les autres soldes sont repris tels que publiés. Si le document est en milliers ou en milliards, convertissez en millions.
B9: Retraitements | C9: Si le comparatif N-1 d'une publication diffère du chiffre publié l'an dernier (retraitement), retenez le chiffre de la publication la plus récente et indiquez-le dans la source.
B10: Statuts | C10: Publié : chiffres figurant dans le document publié. Provisoire : communiqué ou chiffres non encore certifiés. À vérifier : valeur à contrôler.
B11: Règles de priorité | C11: Le fichier prime sur la lecture automatique de richbourse.com, qui comble seulement les périodes ou indicateurs absents. Un document PDF chargé dans l'application prime sur la lecture automatique.
B12: 12 mois glissants | C12: 12 mois glissants = exercice N-1 + cumul N - cumul N-1 de la même période. Ils neutralisent la saisonnalité et alimentent le PER glissant, la croissance et la tendance. Ils exigent le dernier exercice clos dans les états financiers ou la base SMF.
B13: Où trouver les chiffres | C13: brvm.org (avis et communiqués), richbourse.com (rubrique Etats financiers : rapports d'activités T1, S1, T3), sites des sociétés.
B14: Code couleur | C14: Texte bleu : saisie. Texte noir : formule, ne pas modifier. Fond gris : colonne calculée.
B16: Société de gestion collective au capital de 500 000 000 FCFA - N° agrément CREPMF SG-003/2001

Sheet Entreprises
A1: Publications intermédiaires (T1, S1, T3) - entreprises
A2: Une ligne par titre, exercice et période. Montants cumulés depuis le 1er janvier (T1 = 3 mois, S1 = 6 mois, T3 = 9 mois), en millions de FCFA, tels que publiés. Charges en négatif. Une publication donne l'exercice N et le comparatif N-1 : renseignez les deux lignes. Texte bleu : saisie. Voir « Lisez-moi ».
A4: Ticker | B4: Société | C4: Exercice | D4: Période | E4: Statut | F4: Date de publication | G4: Source (lien ou référence) | H4: Chiffre d'affaires | I4: Valeur ajoutée | J4: EBE (excédent brut d'exploitation) | K4: Résultat d'exploitation | L4: Résultat des activités ordinaires (RAO) | M4: Résultat net | N4: Complétude | O4: Contrôle de cohérence | P4: Var. chiffre d'affaires vs même période N-1 | Q4: Var. valeur ajoutée vs même période N-1 | R4: Var. ebe vs même période N-1 | S4: Var. résultat d'exploitation vs même période N-1 | T4: Var. résultat des activités ordinaires vs même période N-1 | U4: Var. résultat net vs même période N-1
A5: NTLC | B5: =IF(A5="","",IFERROR(VLOOKUP(A5,Titres!$A$2:$B$400,2,FALSE),"Ticker inconnu")) | C5: 2021 | D5: T1 | N5: =IF(A5="","",COUNT(H5:M5)/6) | O5: =IF(COUNT(H5:M5)=0,"",IF(LEN(IF(COUNT(I5,J5)=2,IF(J5>I5+1,"EBE > VA ",""),"")&IF(COUNT(H5,M5)=2,IF(ABS(M5)>ABS(H5),"RN > CA ",""),"")&IF(COUNT(H5,K5)=2,IF(ABS(K5)>ABS(H5),"RE > CA ",""),""))=0,"OK",IF(COUNT(I5,J5)=2,IF(J5>I5+1,"EBE > VA ",""),"")&IF(COUNT(H5,M5)=2,IF(ABS(M5)>ABS(H5),"RN > CA ",""),"")&IF(COUNT(H5,K5)=2,IF(ABS(K5)>ABS(H5),"RE > CA ",""),""))) | P5: =IF(OR($A5="",H5="",$C5=""),"",IF(COUNTIFS($A$5:$A$639,$A5,$C$5:$C$639,$C5-1,$D$5:$D$639,$D5,H$5:H$639,"<>")=0,"",IF(OR(SUMIFS(H$5:H$639,$A$5:$A$639,$A5,$C$5:$C$639,$C5-1,$D$5:$D$639,$D5)=0,H5*SUMIFS(H$5:H$639,$A$5:$A$639,$A5,$C$5:$C$639,$C5-1,$D$5:$D$639,$D5)<0),"n.s.",ABS(H5)/ABS(SUMIFS(H$5:H$639,$A$5:$A$639,$A5,$C$5:$C$639,$C5-1,$D$5:$D$639,$D5))-1))) | Q5: =IF(OR($A5="",I5="",$C5=""),"",IF(COUNTIFS($A$5:$A$639,$A5,$C$5:$C$639,$C5-1,$D$5:$D$639,$D5,I$5:I$639,"<>")=0,"",IF(OR(SUMIFS(I$5:I$639,$A$5:$A$639,$A5,$C$5:$C$639,$C5-1,$D$5:$D$639,$D5)=0,I5*SUMIFS(I$5:I$639,$A$5:$A$639,$A5,$C$5:$C$639,$C5-1,$D$5:$D$639,$D5)<0),"n.s.",ABS(I5)/ABS(SUMIFS(I$5:I$639,$A$5:$A$639,$A5,$C$5:$C$639,$C5-1,$D$5:$D$639,$D5))-1))) | R5: =IF(OR($A5="",J5="",$C5=""),"",IF(COUNTIFS($A$5:$A$639,$A5,$C$5:$C$639,$C5-1,$D$5:$D$639,$D5,J$5:J$639,"<>")=0,"",IF(OR(SUMIFS(J$5:J$639,$A$5:$A$639,$A5,$C$5:$C$639,$C5-1,$D$5:$D$639,$D5)=0,J5*SUMIFS(J$5:J$639,$A$5:$A$639,$A5,$C$5:$C$639,$C5-1,$D$5:$D$639,$D5)<0),"n.s.",ABS(J5)/ABS(SUMIFS(J$5:J$639,$A$5:$A$639,$A5,$C$5:$C$639,$C5-1,$D$5:$D$639,$D5))-1))) | S5: =IF(OR($A5="",K5="",$C5=""),"",IF(COUNTIFS($A$5:$A$639,$A5,$C$5:$C$639,$C5-1,$D$5:$D$639,$D5,K$5:K$639,"<>")=0,"",IF(OR(SUMIFS(K$5:K$639,$A$5:$A$639,$A5,$C$5:$C$639,$C5-1,$D$5:$D$639,$D5)=0,K5*SUMIFS(K$5:K$639,$A$5:$A$639,$A5,$C$5:$C$639,$C5-1,$D$5:$D$639,$D5)<0),"n.s.",ABS(K5)/ABS(SUMIFS(K$5:K$639,$A$5:$A$639,$A5,$C$5:$C$639,$C5-1,$D$5:$D$639,$D5))-1))) | T5: =IF(OR($A5="",L5="",$C5=""),"",IF(COUNTIFS($A$5:$A$639,$A5,$C$5:$C$639,$C5-1,$D$5:$D$639,$D5,L$5:L$639,"<>")=0,"",IF(OR(SUMIFS(L$5:L$639,$A$5:$A$639,$A5,$C$5:$C$639,$C5-1,$D$5:$D$639,$D5)=0,L5*SUMIFS(L$5:L$639,$A$5:$A$639,$A5,$C$5:$C$639,$C5-1,$D$5:$D$639,$D5)<0),"n.s.",ABS(L5)/ABS(SUMIFS(L$5:L$639,$A$5:$A$639,$A5,$C$5:$C$639,$C5-1,$D$5:$D$639,$D5))-1))) | U5: =IF(OR($A5="",M5="",$C5=""),"",IF(COUNTIFS($A$5:$A$639,$A5,$C$5:$C$639,$C5-1,$D$5:$D$639,$D5,M$5:M$639,"<>")=0,"",IF(OR(SUMIFS(M$5:M$639,$A$5:$A$639,$A5,$C$5:$C$639,$C5-1,$D$5:$D$639,$D5)=0,M5*SUMIFS(M$5:M$639,$A$5:$A$639,$A5,$C$5:$C$639,$C5-1,$D$5:$D$639,$D5)<0),"n.s.",ABS(M5)/ABS(SUMIFS(M$5:M$639,$A$5:$A$639,$A5,$C$5:$C$639,$C5-1,$D$5:$D$639,$D5))-1)))
A6: NTLC | B6: =IF(A6="","",IFERROR(VLOOKUP(A6,Titres!$A$2:$B$400,2,FALSE),"Ticker inconnu")) | C6: 2021 | D6: S1 | N6: =IF(A6="","",COUNT(H6:M6)/6) | O6: =IF(COUNT(H6:M6)=0,"",IF(LEN(IF(COUNT(I6,J6)=2,IF(J6>I6+1,"EBE > VA ",""),"")&IF(COUNT(H6,M6)=2,IF(ABS(M6)>ABS(H6),"RN > CA ",""),"")&IF(COUNT(H6,K6)=2,IF(ABS(K6)>ABS(H6),"RE > CA ",""),""))=0,"OK",IF(COUNT(I6,J6)=2,IF(J6>I6+1,"EBE > VA ",""),"")&IF(COUNT(H6,M6)=2,IF(ABS(M6)>ABS(H6),"RN > CA ",""),"")&IF(COUNT(H6,K6)=2,IF(ABS(K6)>ABS(H6),"RE > CA ",""),""))) | P6: =IF(OR($A6="",H6="",$C6=""),"",IF(COUNTIFS($A$5:$A$639,$A6,$C$5:$C$639,$C6-1,$D$5:$D$639,$D6,H$5:H$639,"<>")=0,"",IF(OR(SUMIFS(H$5:H$639,$A$5:$A$639,$A6,$C$5:$C$639,$C6-1,$D$5:$D$639,$D6)=0,H6*SUMIFS(H$5:H$639,$A$5:$A$639,$A6,$C$5:$C$639,$C6-1,$D$5:$D$639,$D6)<0),"n.s.",ABS(H6)/ABS(SUMIFS(H$5:H$639,$A$5:$A$639,$A6,$C$5:$C$639,$C6-1,$D$5:$D$639,$D6))-1))) | Q6: =IF(OR($A6="",I6="",$C6=""),"",IF(COUNTIFS($A$5:$A$639,$A6,$C$5:$C$639,$C6-1,$D$5:$D$639,$D6,I$5:I$639,"<>")=0,"",IF(OR(SUMIFS(I$5:I$639,$A$5:$A$639,$A6,$C$5:$C$639,$C6-1,$D$5:$D$639,$D6)=0,I6*SUMIFS(I$5:I$639,$A$5:$A$639,$A6,$C$5:$C$639,$C6-1,$D$5:$D$639,$D6)<0),"n.s.",ABS(I6)/ABS(SUMIFS(I$5:I$639,$A$5:$A$639,$A6,$C$5:$C$639,$C6-1,$D$5:$D$639,$D6))-1))) | R6: =IF(OR($A6="",J6="",$C6=""),"",IF(COUNTIFS($A$5:$A$639,$A6,$C$5:$C$639,$C6-1,$D$5:$D$639,$D6,J$5:J$639,"<>")=0,"",IF(OR(SUMIFS(J$5:J$639,$A$5:$A$639,$A6,$C$5:$C$639,$C6-1,$D$5:$D$639,$D6)=0,J6*SUMIFS(J$5:J$639,$A$5:$A$639,$A6,$C$5:$C$639,$C6-1,$D$5:$D$639,$D6)<0),"n.s.",ABS(J6)/ABS(SUMIFS(J$5:J$639,$A$5:$A$639,$A6,$C$5:$C$639,$C6-1,$D$5:$D$639,$D6))-1))) | S6: =IF(OR($A6="",K6="",$C6=""),"",IF(COUNTIFS($A$5:$A$639,$A6,$C$5:$C$639,$C6-1,$D$5:$D$639,$D6,K$5:K$639,"<>")=0,"",IF(OR(SUMIFS(K$5:K$639,$A$5:$A$639,$A6,$C$5:$C$639,$C6-1,$D$5:$D$639,$D6)=0,K6*SUMIFS(K$5:K$639,$A$5:$A$639,$A6,$C$5:$C$639,$C6-1,$D$5:$D$639,$D6)<0),"n.s.",ABS(K6)/ABS(SUMIFS(K$5:K$639,$A$5:$A$639,$A6,$C$5:$C$639,$C6-1,$D$5:$D$639,$D6))-1))) | T6: =IF(OR($A6="",L6="",$C6=""),"",IF(COUNTIFS($A$5:$A$639,$A6,$C$5:$C$639,$C6-1,$D$5:$D$639,$D6,L$5:L$639,"<>")=0,"",IF(OR(SUMIFS(L$5:L$639,$A$5:$A$639,$A6,$C$5:$C$639,$C6-1,$D$5:$D$639,$D6)=0,L6*SUMIFS(L$5:L$639,$A$5:$A$639,$A6,$C$5:$C$639,$C6-1,$D$5:$D$639,$D6)<0),"n.s.",ABS(L6)/ABS(SUMIFS(L$5:L$639,$A$5:$A$639,$A6,$C$5:$C$639,$C6-1,$D$5:$D$639,$D6))-1))) | U6: =IF(OR($A6="",M6="",$C6=""),"",IF(COUNTIFS($A$5:$A$639,$A6,$C$5:$C$639,$C6-1,$D$5:$D$639,$D6,M$5:M$639,"<>")=0,"",IF(OR(SUMIFS(M$5:M$639,$A$5:$A$639,$A6,$C$5:$C$639,$C6-1,$D$5:$D$639,$D6)=0,M6*SUMIFS(M$5:M$639,$A$5:$A$639,$A6,$C$5:$C$639,$C6-1,$D$5:$D$639,$D6)<0),"n.s.",ABS(M6)/ABS(SUMIFS(M$5:M$639,$A$5:$A$639,$A6,$C$5:$C$639,$C6-1,$D$5:$D$639,$D6))-1)))
A7: NTLC | B7: =IF(A7="","",IFERROR(VLOOKUP(A7,Titres!$A$2:$B$400,2,FALSE),"Ticker inconnu")) | C7: 2021 | D7: T3 | N7: =IF(A7="","",COUNT(H7:M7)/6) | O7: =IF(COUNT(H7:M7)=0,"",IF(LEN(IF(COUNT(I7,J7)=2,IF(J7>I7+1,"EBE > VA ",""),"")&IF(COUNT(H7,M7)=2,IF(ABS(M7)>ABS(H7),"RN > CA ",""),"")&IF(COUNT(H7,K7)=2,IF(ABS(K7)>ABS(H7),"RE > CA ",""),""))=0,"OK",IF(COUNT(I7,J7)=2,IF(J7>I7+1,"EBE > VA ",""),"")&IF(COUNT(H7,M7)=2,IF(ABS(M7)>ABS(H7),"RN > CA ",""),"")&IF(COUNT(H7,K7)=2,IF(ABS(K7)>ABS(H7),"RE > CA ",""),""))) | P7: =IF(OR($A7="",H7="",$C7=""),"",IF(COUNTIFS($A$5:$A$639,$A7,$C$5:$C$639,$C7-1,$D$5:$D$639,$D7,H$5:H$639,"<>")=0,"",IF(OR(SUMIFS(H$5:H$639,$A$5:$A$639,$A7,$C$5:$C$639,$C7-1,$D$5:$D$639,$D7)=0,H7*SUMIFS(H$5:H$639,$A$5:$A$639,$A7,$C$5:$C$639,$C7-1,$D$5:$D$639,$D7)<0),"n.s.",ABS(H7)/ABS(SUMIFS(H$5:H$639,$A$5:$A$639,$A7,$C$5:$C$639,$C7-1,$D$5:$D$639,$D7))-1))) | Q7: =IF(OR($A7="",I7="",$C7=""),"",IF(COUNTIFS($A$5:$A$639,$A7,$C$5:$C$639,$C7-1,$D$5:$D$639,$D7,I$5:I$639,"<>")=0,"",IF(OR(SUMIFS(I$5:I$639,$A$5:$A$639,$A7,$C$5:$C$639,$C7-1,$D$5:$D$639,$D7)=0,I7*SUMIFS(I$5:I$639,$A$5:$A$639,$A7,$C$5:$C$639,$C7-1,$D$5:$D$639,$D7)<0),"n.s.",ABS(I7)/ABS(SUMIFS(I$5:I$639,$A$5:$A$639,$A7,$C$5:$C$639,$C7-1,$D$5:$D$639,$D7))-1))) | R7: =IF(OR($A7="",J7="",$C7=""),"",IF(COUNTIFS($A$5:$A$639,$A7,$C$5:$C$639,$C7-1,$D$5:$D$639,$D7,J$5:J$639,"<>")=0,"",IF(OR(SUMIFS(J$5:J$639,$A$5:$A$639,$A7,$C$5:$C$639,$C7-1,$D$5:$D$639,$D7)=0,J7*SUMIFS(J$5:J$639,$A$5:$A$639,$A7,$C$5:$C$639,$C7-1,$D$5:$D$639,$D7)<0),"n.s.",ABS(J7)/ABS(SUMIFS(J$5:J$639,$A$5:$A$639,$A7,$C$5:$C$639,$C7-1,$D$5:$D$639,$D7))-1))) | S7: =IF(OR($A7="",K7="",$C7=""),"",IF(COUNTIFS($A$5:$A$639,$A7,$C$5:$C$639,$C7-1,$D$5:$D$639,$D7,K$5:K$639,"<>")=0,"",IF(OR(SUMIFS(K$5:K$639,$A$5:$A$639,$A7,$C$5:$C$639,$C7-1,$D$5:$D$639,$D7)=0,K7*SUMIFS(K$5:K$639,$A$5:$A$639,$A7,$C$5:$C$639,$C7-1,$D$5:$D$639,$D7)<0),"n.s.",ABS(K7)/ABS(SUMIFS(K$5:K$639,$A$5:$A$639,$A7,$C$5:$C$639,$C7-1,$D$5:$D$639,$D7))-1))) | T7: =IF(OR($A7="",L7="",$C7=""),"",IF(COUNTIFS($A$5:$A$639,$A7,$C$5:$C$639,$C7-1,$D$5:$D$639,$D7,L$5:L$639,"<>")=0,"",IF(OR(SUMIFS(L$5:L$639,$A$5:$A$639,$A7,$C$5:$C$639,$C7-1,$D$5:$D$639,$D7)=0,L7*SUMIFS(L$5:L$639,$A$5:$A$639,$A7,$C$5:$C$639,$C7-1,$D$5:$D$639,$D7)<0),"n.s.",ABS(L7)/ABS(SUMIFS(L$5:L$639,$A$5:$A$639,$A7,$C$5:$C$639,$C7-1,$D$5:$D$639,$D7))-1))) | U7: =IF(OR($A7="",M7="",$C7=""),"",IF(COUNTIFS($A$5:$A$639,$A7,$C$5:$C$639,$C7-1,$D$5:$D$639,$D7,M$5:M$639,"<>")=0,"",IF(OR(SUMIFS(M$5:M$639,$A$5:$A$639,$A7,$C$5:$C$639,$C7-1,$D$5:$D$639,$D7)=0,M7*SUMIFS(M$5:M$639,$A$5:$A$639,$A7,$C$5:$C$639,$C7-1,$D$5:$D$639,$D7)<0),"n.s.",ABS(M7)/ABS(SUMIFS(M$5:M$639,$A$5:$A$639,$A7,$C$5:$C$639,$C7-1,$D$5:$D$639,$D7))-1)))
A8: NTLC | B8: =IF(A8="","",IFERROR(VLOOKUP(A8,Titres!$A$2:$B$400,2,FALSE),"Ticker inconnu")) | C8: 2022 | D8: T1 | N8: =IF(A8="","",COUNT(H8:M8)/6) | O8: =IF(COUNT(H8:M8)=0,"",IF(LEN(IF(COUNT(I8,J8)=2,IF(J8>I8+1,"EBE > VA ",""),"")&IF(COUNT(H8,M8)=2,IF(ABS(M8)>ABS(H8),"RN > CA ",""),"")&IF(COUNT(H8,K8)=2,IF(ABS(K8)>ABS(H8),"RE > CA ",""),""))=0,"OK",IF(COUNT(I8,J8)=2,IF(J8>I8+1,"EBE > VA ",""),"")&IF(COUNT(H8,M8)=2,IF(ABS(M8)>ABS(H8),"RN > CA ",""),"")&IF(COUNT(H8,K8)=2,IF(ABS(K8)>ABS(H8),"RE > CA ",""),""))) | P8: =IF(OR($A8="",H8="",$C8=""),"",IF(COUNTIFS($A$5:$A$639,$A8,$C$5:$C$639,$C8-1,$D$5:$D$639,$D8,H$5:H$639,"<>")=0,"",IF(OR(SUMIFS(H$5:H$639,$A$5:$A$639,$A8,$C$5:$C$639,$C8-1,$D$5:$D$639,$D8)=0,H8*SUMIFS(H$5:H$639,$A$5:$A$639,$A8,$C$5:$C$639,$C8-1,$D$5:$D$639,$D8)<0),"n.s.",ABS(H8)/ABS(SUMIFS(H$5:H$639,$A$5:$A$639,$A8,$C$5:$C$639,$C8-1,$D$5:$D$639,$D8))-1))) | Q8: =IF(OR($A8="",I8="",$C8=""),"",IF(COUNTIFS($A$5:$A$639,$A8,$C$5:$C$639,$C8-1,$D$5:$D$639,$D8,I$5:I$639,"<>")=0,"",IF(OR(SUMIFS(I$5:I$639,$A$5:$A$639,$A8,$C$5:$C$639,$C8-1,$D$5:$D$639,$D8)=0,I8*SUMIFS(I$5:I$639,$A$5:$A$639,$A8,$C$5:$C$639,$C8-1,$D$5:$D$639,$D8)<0),"n.s.",ABS(I8)/ABS(SUMIFS(I$5:I$639,$A$5:$A$639,$A8,$C$5:$C$639,$C8-1,$D$5:$D$639,$D8))-1))) | R8: =IF(OR($A8="",J8="",$C8=""),"",IF(COUNTIFS($A$5:$A$639,$A8,$C$5:$C$639,$C8-1,$D$5:$D$639,$D8,J$5:J$639,"<>")=0,"",IF(OR(SUMIFS(J$5:J$639,$A$5:$A$639,$A8,$C$5:$C$639,$C8-1,$D$5:$D$639,$D8)=0,J8*SUMIFS(J$5:J$639,$A$5:$A$639,$A8,$C$5:$C$639,$C8-1,$D$5:$D$639,$D8)<0),"n.s.",ABS(J8)/ABS(SUMIFS(J$5:J$639,$A$5:$A$639,$A8,$C$5:$C$639,$C8-1,$D$5:$D$639,$D8))-1))) | S8: =IF(OR($A8="",K8="",$C8=""),"",IF(COUNTIFS($A$5:$A$639,$A8,$C$5:$C$639,$C8-1,$D$5:$D$639,$D8,K$5:K$639,"<>")=0,"",IF(OR(SUMIFS(K$5:K$639,$A$5:$A$639,$A8,$C$5:$C$639,$C8-1,$D$5:$D$639,$D8)=0,K8*SUMIFS(K$5:K$639,$A$5:$A$639,$A8,$C$5:$C$639,$C8-1,$D$5:$D$639,$D8)<0),"n.s.",ABS(K8)/ABS(SUMIFS(K$5:K$639,$A$5:$A$639,$A8,$C$5:$C$639,$C8-1,$D$5:$D$639,$D8))-1))) | T8: =IF(OR($A8="",L8="",$C8=""),"",IF(COUNTIFS($A$5:$A$639,$A8,$C$5:$C$639,$C8-1,$D$5:$D$639,$D8,L$5:L$639,"<>")=0,"",IF(OR(SUMIFS(L$5:L$639,$A$5:$A$639,$A8,$C$5:$C$639,$C8-1,$D$5:$D$639,$D8)=0,L8*SUMIFS(L$5:L$639,$A$5:$A$639,$A8,$C$5:$C$639,$C8-1,$D$5:$D$639,$D8)<0),"n.s.",ABS(L8)/ABS(SUMIFS(L$5:L$639,$A$5:$A$639,$A8,$C$5:$C$639,$C8-1,$D$5:$D$639,$D8))-1))) | U8: =IF(OR($A8="",M8="",$C8=""),"",IF(COUNTIFS($A$5:$A$639,$A8,$C$5:$C$639,$C8-1,$D$5:$D$639,$D8,M$5:M$639,"<>")=0,"",IF(OR(SUMIFS(M$5:M$639,$A$5:$A$639,$A8,$C$5:$C$639,$C8-1,$D$5:$D$639,$D8)=0,M8*SUMIFS(M$5:M$639,$A$5:$A$639,$A8,$C$5:$C$639,$C8-1,$D$5:$D$639,$D8)<0),"n.s.",ABS(M8)/ABS(SUMIFS(M$5:M$639,$A$5:$A$639,$A8,$C$5:$C$639,$C8-1,$D$5:$D$639,$D8))-1)))
A9: NTLC | B9: =IF(A9="","",IFERROR(VLOOKUP(A9,Titres!$A$2:$B$400,2,FALSE),"Ticker inconnu")) | C9: 2022 | D9: S1 | N9: =IF(A9="","",COUNT(H9:M9)/6) | O9: =IF(COUNT(H9:M9)=0,"",IF(LEN(IF(COUNT(I9,J9)=2,IF(J9>I9+1,"EBE > VA ",""),"")&IF(COUNT(H9,M9)=2,IF(ABS(M9)>ABS(H9),"RN > CA ",""),"")&IF(COUNT(H9,K9)=2,IF(ABS(K9)>ABS(H9),"RE > CA ",""),""))=0,"OK",IF(COUNT(I9,J9)=2,IF(J9>I9+1,"EBE > VA ",""),"")&IF(COUNT(H9,M9)=2,IF(ABS(M9)>ABS(H9),"RN > CA ",""),"")&IF(COUNT(H9,K9)=2,IF(ABS(K9)>ABS(H9),"RE > CA ",""),""))) | P9: =IF(OR($A9="",H9="",$C9=""),"",IF(COUNTIFS($A$5:$A$639,$A9,$C$5:$C$639,$C9-1,$D$5:$D$639,$D9,H$5:H$639,"<>")=0,"",IF(OR(SUMIFS(H$5:H$639,$A$5:$A$639,$A9,$C$5:$C$639,$C9-1,$D$5:$D$639,$D9)=0,H9*SUMIFS(H$5:H$639,$A$5:$A$639,$A9,$C$5:$C$639,$C9-1,$D$5:$D$639,$D9)<0),"n.s.",ABS(H9)/ABS(SUMIFS(H$5:H$639,$A$5:$A$639,$A9,$C$5:$C$639,$C9-1,$D$5:$D$639,$D9))-1))) | Q9: =IF(OR($A9="",I9="",$C9=""),"",IF(COUNTIFS($A$5:$A$639,$A9,$C$5:$C$639,$C9-1,$D$5:$D$639,$D9,I$5:I$639,"<>")=0,"",IF(OR(SUMIFS(I$5:I$639,$A$5:$A$639,$A9,$C$5:$C$639,$C9-1,$D$5:$D$639,$D9)=0,I9*SUMIFS(I$5:I$639,$A$5:$A$639,$A9,$C$5:$C$639,$C9-1,$D$5:$D$639,$D9)<0),"n.s.",ABS(I9)/ABS(SUMIFS(I$5:I$639,$A$5:$A$639,$A9,$C$5:$C$639,$C9-1,$D$5:$D$639,$D9))-1))) | R9: =IF(OR($A9="",J9="",$C9=""),"",IF(COUNTIFS($A$5:$A$639,$A9,$C$5:$C$639,$C9-1,$D$5:$D$639,$D9,J$5:J$639,"<>")=0,"",IF(OR(SUMIFS(J$5:J$639,$A$5:$A$639,$A9,$C$5:$C$639,$C9-1,$D$5:$D$639,$D9)=0,J9*SUMIFS(J$5:J$639,$A$5:$A$639,$A9,$C$5:$C$639,$C9-1,$D$5:$D$639,$D9)<0),"n.s.",ABS(J9)/ABS(SUMIFS(J$5:J$639,$A$5:$A$639,$A9,$C$5:$C$639,$C9-1,$D$5:$D$639,$D9))-1))) | S9: =IF(OR($A9="",K9="",$C9=""),"",IF(COUNTIFS($A$5:$A$639,$A9,$C$5:$C$639,$C9-1,$D$5:$D$639,$D9,K$5:K$639,"<>")=0,"",IF(OR(SUMIFS(K$5:K$639,$A$5:$A$639,$A9,$C$5:$C$639,$C9-1,$D$5:$D$639,$D9)=0,K9*SUMIFS(K$5:K$639,$A$5:$A$639,$A9,$C$5:$C$639,$C9-1,$D$5:$D$639,$D9)<0),"n.s.",ABS(K9)/ABS(SUMIFS(K$5:K$639,$A$5:$A$639,$A9,$C$5:$C$639,$C9-1,$D$5:$D$639,$D9))-1))) | T9: =IF(OR($A9="",L9="",$C9=""),"",IF(COUNTIFS($A$5:$A$639,$A9,$C$5:$C$639,$C9-1,$D$5:$D$639,$D9,L$5:L$639,"<>")=0,"",IF(OR(SUMIFS(L$5:L$639,$A$5:$A$639,$A9,$C$5:$C$639,$C9-1,$D$5:$D$639,$D9)=0,L9*SUMIFS(L$5:L$639,$A$5:$A$639,$A9,$C$5:$C$639,$C9-1,$D$5:$D$639,$D9)<0),"n.s.",ABS(L9)/ABS(SUMIFS(L$5:L$639,$A$5:$A$639,$A9,$C$5:$C$639,$C9-1,$D$5:$D$639,$D9))-1))) | U9: =IF(OR($A9="",M9="",$C9=""),"",IF(COUNTIFS($A$5:$A$639,$A9,$C$5:$C$639,$C9-1,$D$5:$D$639,$D9,M$5:M$639,"<>")=0,"",IF(OR(SUMIFS(M$5:M$639,$A$5:$A$639,$A9,$C$5:$C$639,$C9-1,$D$5:$D$639,$D9)=0,M9*SUMIFS(M$5:M$639,$A$5:$A$639,$A9,$C$5:$C$639,$C9-1,$D$5:$D$639,$D9)<0),"n.s.",ABS(M9)/ABS(SUMIFS(M$5:M$639,$A$5:$A$639,$A9,$C$5:$C$639,$C9-1,$D$5:$D$639,$D9))-1)))
A10: NTLC | B10: =IF(A10="","",IFERROR(VLOOKUP(A10,Titres!$A$2:$B$400,2,FALSE),"Ticker inconnu")) | C10: 2022 | D10: T3 | N10: =IF(A10="","",COUNT(H10:M10)/6) | O10: =IF(COUNT(H10:M10)=0,"",IF(LEN(IF(COUNT(I10,J10)=2,IF(J10>I10+1,"EBE > VA ",""),"")&IF(COUNT(H10,M10)=2,IF(ABS(M10)>ABS(H10),"RN > CA ",""),"")&IF(COUNT(H10,K10)=2,IF(ABS(K10)>ABS(H10),"RE > CA ",""),""))=0,"OK",IF(COUNT(I10,J10)=2,IF(J10>I10+1,"EBE > VA ",""),"")&IF(COUNT(H10,M10)=2,IF(ABS(M10)>ABS(H10),"RN > CA ",""),"")&IF(COUNT(H10,K10)=2,IF(ABS(K10)>ABS(H10),"RE > CA ",""),""))) | P10: =IF(OR($A10="",H10="",$C10=""),"",IF(COUNTIFS($A$5:$A$639,$A10,$C$5:$C$639,$C10-1,$D$5:$D$639,$D10,H$5:H$639,"<>")=0,"",IF(OR(SUMIFS(H$5:H$639,$A$5:$A$639,$A10,$C$5:$C$639,$C10-1,$D$5:$D$639,$D10)=0,H10*SUMIFS(H$5:H$639,$A$5:$A$639,$A10,$C$5:$C$639,$C10-1,$D$5:$D$639,$D10)<0),"n.s.",ABS(H10)/ABS(SUMIFS(H$5:H$639,$A$5:$A$639,$A10,$C$5:$C$639,$C10-1,$D$5:$D$639,$D10))-1))) | Q10: =IF(OR($A10="",I10="",$C10=""),"",IF(COUNTIFS($A$5:$A$639,$A10,$C$5:$C$639,$C10-1,$D$5:$D$639,$D10,I$5:I$639,"<>")=0,"",IF(OR(SUMIFS(I$5:I$639,$A$5:$A$639,$A10,$C$5:$C$639,$C10-1,$D$5:$D$639,$D10)=0,I10*SUMIFS(I$5:I$639,$A$5:$A$639,$A10,$C$5:$C$639,$C10-1,$D$5:$D$639,$D10)<0),"n.s.",ABS(I10)/ABS(SUMIFS(I$5:I$639,$A$5:$A$639,$A10,$C$5:$C$639,$C10-1,$D$5:$D$639,$D10))-1))) | R10: =IF(OR($A10="",J10="",$C10=""),"",IF(COUNTIFS($A$5:$A$639,$A10,$C$5:$C$639,$C10-1,$D$5:$D$639,$D10,J$5:J$639,"<>")=0,"",IF(OR(SUMIFS(J$5:J$639,$A$5:$A$639,$A10,$C$5:$C$639,$C10-1,$D$5:$D$639,$D10)=0,J10*SUMIFS(J$5:J$639,$A$5:$A$639,$A10,$C$5:$C$639,$C10-1,$D$5:$D$639,$D10)<0),"n.s.",ABS(J10)/ABS(SUMIFS(J$5:J$639,$A$5:$A$639,$A10,$C$5:$C$639,$C10-1,$D$5:$D$639,$D10))-1))) | S10: =IF(OR($A10="",K10="",$C10=""),"",IF(COUNTIFS($A$5:$A$639,$A10,$C$5:$C$639,$C10-1,$D$5:$D$639,$D10,K$5:K$639,"<>")=0,"",IF(OR(SUMIFS(K$5:K$639,$A$5:$A$639,$A10,$C$5:$C$639,$C10-1,$D$5:$D$639,$D10)=0,K10*SUMIFS(K$5:K$639,$A$5:$A$639,$A10,$C$5:$C$639,$C10-1,$D$5:$D$639,$D10)<0),"n.s.",ABS(K10)/ABS(SUMIFS(K$5:K$639,$A$5:$A$639,$A10,$C$5:$C$639,$C10-1,$D$5:$D$639,$D10))-1))) | T10: =IF(OR($A10="",L10="",$C10=""),"",IF(COUNTIFS($A$5:$A$639,$A10,$C$5:$C$639,$C10-1,$D$5:$D$639,$D10,L$5:L$639,"<>")=0,"",IF(OR(SUMIFS(L$5:L$639,$A$5:$A$639,$A10,$C$5:$C$639,$C10-1,$D$5:$D$639,$D10)=0,L10*SUMIFS(L$5:L$639,$A$5:$A$639,$A10,$C$5:$C$639,$C10-1,$D$5:$D$639,$D10)<0),"n.s.",ABS(L10)/ABS(SUMIFS(L$5:L$639,$A$5:$A$639,$A10,$C$5:$C$639,$C10-1,$D$5:$D$639,$D10))-1))) | U10: =IF(OR($A10="",M10="",$C10=""),"",IF(COUNTIFS($A$5:$A$639,$A10,$C$5:$C$639,$C10-1,$D$5:$D$639,$D10,M$5:M$639,"<>")=0,"",IF(OR(SUMIFS(M$5:M$639,$A$5:$A$639,$A10,$C$5:$C$639,$C10-1,$D$5:$D$639,$D10)=0,M10*SUMIFS(M$5:M$639,$A$5:$A$639,$A10,$C$5:$C$639,$C10-1,$D$5:$D$639,$D10)<0),"n.s.",ABS(M10)/ABS(SUMIFS(M$5:M$639,$A$5:$A$639,$A10,$C$5:$C$639,$C10-1,$D$5:$D$639,$D10))-1)))
A11: NTLC | B11: =IF(A11="","",IFERROR(VLOOKUP(A11,Titres!$A$2:$B$400,2,FALSE),"Ticker inconnu")) | C11: 2023 | D11: T1 | N11: =IF(A11="","",COUNT(H11:M11)/6) | O11: =IF(COUNT(H11:M11)=0,"",IF(LEN(IF(COUNT(I11,J11)=2,IF(J11>I11+1,"EBE > VA ",""),"")&IF(COUNT(H11,M11)=2,IF(ABS(M11)>ABS(H11),"RN > CA ",""),"")&IF(COUNT(H11,K11)=2,IF(ABS(K11)>ABS(H11),"RE > CA ",""),""))=0,"OK",IF(COUNT(I11,J11)=2,IF(J11>I11+1,"EBE > VA ",""),"")&IF(COUNT(H11,M11)=2,IF(ABS(M11)>ABS(H11),"RN > CA ",""),"")&IF(COUNT(H11,K11)=2,IF(ABS(K11)>ABS(H11),"RE > CA ",""),""))) | P11: =IF(OR($A11="",H11="",$C11=""),"",IF(COUNTIFS($A$5:$A$639,$A11,$C$5:$C$639,$C11-1,$D$5:$D$639,$D11,H$5:H$639,"<>")=0,"",IF(OR(SUMIFS(H$5:H$639,$A$5:$A$639,$A11,$C$5:$C$639,$C11-1,$D$5:$D$639,$D11)=0,H11*SUMIFS(H$5:H$639,$A$5:$A$639,$A11,$C$5:$C$639,$C11-1,$D$5:$D$639,$D11)<0),"n.s.",ABS(H11)/ABS(SUMIFS(H$5:H$639,$A$5:$A$639,$A11,$C$5:$C$639,$C11-1,$D$5:$D$639,$D11))-1))) | Q11: =IF(OR($A11="",I11="",$C11=""),"",IF(COUNTIFS($A$5:$A$639,$A11,$C$5:$C$639,$C11-1,$D$5:$D$639,$D11,I$5:I$639,"<>")=0,"",IF(OR(SUMIFS(I$5:I$639,$A$5:$A$639,$A11,$C$5:$C$639,$C11-1,$D$5:$D$639,$D11)=0,I11*SUMIFS(I$5:I$639,$A$5:$A$639,$A11,$C$5:$C$639,$C11-1,$D$5:$D$639,$D11)<0),"n.s.",ABS(I11)/ABS(SUMIFS(I$5:I$639,$A$5:$A$639,$A11,$C$5:$C$639,$C11-1,$D$5:$D$639,$D11))-1))) | R11: =IF(OR($A11="",J11="",$C11=""),"",IF(COUNTIFS($A$5:$A$639,$A11,$C$5:$C$639,$C11-1,$D$5:$D$639,$D11,J$5:J$639,"<>")=0,"",IF(OR(SUMIFS(J$5:J$639,$A$5:$A$639,$A11,$C$5:$C$639,$C11-1,$D$5:$D$639,$D11)=0,J11*SUMIFS(J$5:J$639,$A$5:$A$639,$A11,$C$5:$C$639,$C11-1,$D$5:$D$639,$D11)<0),"n.s.",ABS(J11)/ABS(SUMIFS(J$5:J$639,$A$5:$A$639,$A11,$C$5:$C$639,$C11-1,$D$5:$D$639,$D11))-1))) | S11: =IF(OR($A11="",K11="",$C11=""),"",IF(COUNTIFS($A$5:$A$639,$A11,$C$5:$C$639,$C11-1,$D$5:$D$639,$D11,K$5:K$639,"<>")=0,"",IF(OR(SUMIFS(K$5:K$639,$A$5:$A$639,$A11,$C$5:$C$639,$C11-1,$D$5:$D$639,$D11)=0,K11*SUMIFS(K$5:K$639,$A$5:$A$639,$A11,$C$5:$C$639,$C11-1,$D$5:$D$639,$D11)<0),"n.s.",ABS(K11)/ABS(SUMIFS(K$5:K$639,$A$5:$A$639,$A11,$C$5:$C$639,$C11-1,$D$5:$D$639,$D11))-1))) | T11: =IF(OR($A11="",L11="",$C11=""),"",IF(COUNTIFS($A$5:$A$639,$A11,$C$5:$C$639,$C11-1,$D$5:$D$639,$D11,L$5:L$639,"<>")=0,"",IF(OR(SUMIFS(L$5:L$639,$A$5:$A$639,$A11,$C$5:$C$639,$C11-1,$D$5:$D$639,$D11)=0,L11*SUMIFS(L$5:L$639,$A$5:$A$639,$A11,$C$5:$C$639,$C11-1,$D$5:$D$639,$D11)<0),"n.s.",ABS(L11)/ABS(SUMIFS(L$5:L$639,$A$5:$A$639,$A11,$C$5:$C$639,$C11-1,$D$5:$D$639,$D11))-1))) | U11: =IF(OR($A11="",M11="",$C11=""),"",IF(COUNTIFS($A$5:$A$639,$A11,$C$5:$C$639,$C11-1,$D$5:$D$639,$D11,M$5:M$639,"<>")=0,"",IF(OR(SUMIFS(M$5:M$639,$A$5:$A$639,$A11,$C$5:$C$639,$C11-1,$D$5:$D$639,$D11)=0,M11*SUMIFS(M$5:M$639,$A$5:$A$639,$A11,$C$5:$C$639,$C11-1,$D$5:$D$639,$D11)<0),"n.s.",ABS(M11)/ABS(SUMIFS(M$5:M$639,$A$5:$A$639,$A11,$C$5:$C$639,$C11-1,$D$5:$D$639,$D11))-1)))
A12: NTLC | B12: =IF(A12="","",IFERROR(VLOOKUP(A12,Titres!$A$2:$B$400,2,FALSE),"Ticker inconnu")) | C12: 2023 | D12: S1 | N12: =IF(A12="","",COUNT(H12:M12)/6) | O12: =IF(COUNT(H12:M12)=0,"",IF(LEN(IF(COUNT(I12,J12)=2,IF(J12>I12+1,"EBE > VA ",""),"")&IF(COUNT(H12,M12)=2,IF(ABS(M12)>ABS(H12),"RN > CA ",""),"")&IF(COUNT(H12,K12)=2,IF(ABS(K12)>ABS(H12),"RE > CA ",""),""))=0,"OK",IF(COUNT(I12,J12)=2,IF(J12>I12+1,"EBE > VA ",""),"")&IF(COUNT(H12,M12)=2,IF(ABS(M12)>ABS(H12),"RN > CA ",""),"")&IF(COUNT(H12,K12)=2,IF(ABS(K12)>ABS(H12),"RE > CA ",""),""))) | P12: =IF(OR($A12="",H12="",$C12=""),"",IF(COUNTIFS($A$5:$A$639,$A12,$C$5:$C$639,$C12-1,$D$5:$D$639,$D12,H$5:H$639,"<>")=0,"",IF(OR(SUMIFS(H$5:H$639,$A$5:$A$639,$A12,$C$5:$C$639,$C12-1,$D$5:$D$639,$D12)=0,H12*SUMIFS(H$5:H$639,$A$5:$A$639,$A12,$C$5:$C$639,$C12-1,$D$5:$D$639,$D12)<0),"n.s.",ABS(H12)/ABS(SUMIFS(H$5:H$639,$A$5:$A$639,$A12,$C$5:$C$639,$C12-1,$D$5:$D$639,$D12))-1))) | Q12: =IF(OR($A12="",I12="",$C12=""),"",IF(COUNTIFS($A$5:$A$639,$A12,$C$5:$C$639,$C12-1,$D$5:$D$639,$D12,I$5:I$639,"<>")=0,"",IF(OR(SUMIFS(I$5:I$639,$A$5:$A$639,$A12,$C$5:$C$639,$C12-1,$D$5:$D$639,$D12)=0,I12*SUMIFS(I$5:I$639,$A$5:$A$639,$A12,$C$5:$C$639,$C12-1,$D$5:$D$639,$D12)<0),"n.s.",ABS(I12)/ABS(SUMIFS(I$5:I$639,$A$5:$A$639,$A12,$C$5:$C$639,$C12-1,$D$5:$D$639,$D12))-1))) | R12: =IF(OR($A12="",J12="",$C12=""),"",IF(COUNTIFS($A$5:$A$639,$A12,$C$5:$C$639,$C12-1,$D$5:$D$639,$D12,J$5:J$639,"<>")=0,"",IF(OR(SUMIFS(J$5:J$639,$A$5:$A$639,$A12,$C$5:$C$639,$C12-1,$D$5:$D$639,$D12)=0,J12*SUMIFS(J$5:J$639,$A$5:$A$639,$A12,$C$5:$C$639,$C12-1,$D$5:$D$639,$D12)<0),"n.s.",ABS(J12)/ABS(SUMIFS(J$5:J$639,$A$5:$A$639,$A12,$C$5:$C$639,$C12-1,$D$5:$D$639,$D12))-1))) | S12: =IF(OR($A12="",K12="",$C12=""),"",IF(COUNTIFS($A$5:$A$639,$A12,$C$5:$C$639,$C12-1,$D$5:$D$639,$D12,K$5:K$639,"<>")=0,"",IF(OR(SUMIFS(K$5:K$639,$A$5:$A$639,$A12,$C$5:$C$639,$C12-1,$D$5:$D$639,$D12)=0,K12*SUMIFS(K$5:K$639,$A$5:$A$639,$A12,$C$5:$C$639,$C12-1,$D$5:$D$639,$D12)<0),"n.s.",ABS(K12)/ABS(SUMIFS(K$5:K$639,$A$5:$A$639,$A12,$C$5:$C$639,$C12-1,$D$5:$D$639,$D12))-1))) | T12: =IF(OR($A12="",L12="",$C12=""),"",IF(COUNTIFS($A$5:$A$639,$A12,$C$5:$C$639,$C12-1,$D$5:$D$639,$D12,L$5:L$639,"<>")=0,"",IF(OR(SUMIFS(L$5:L$639,$A$5:$A$639,$A12,$C$5:$C$639,$C12-1,$D$5:$D$639,$D12)=0,L12*SUMIFS(L$5:L$639,$A$5:$A$639,$A12,$C$5:$C$639,$C12-1,$D$5:$D$639,$D12)<0),"n.s.",ABS(L12)/ABS(SUMIFS(L$5:L$639,$A$5:$A$639,$A12,$C$5:$C$639,$C12-1,$D$5:$D$639,$D12))-1))) | U12: =IF(OR($A12="",M12="",$C12=""),"",IF(COUNTIFS($A$5:$A$639,$A12,$C$5:$C$639,$C12-1,$D$5:$D$639,$D12,M$5:M$639,"<>")=0,"",IF(OR(SUMIFS(M$5:M$639,$A$5:$A$639,$A12,$C$5:$C$639,$C12-1,$D$5:$D$639,$D12)=0,M12*SUMIFS(M$5:M$639,$A$5:$A$639,$A12,$C$5:$C$639,$C12-1,$D$5:$D$639,$D12)<0),"n.s.",ABS(M12)/ABS(SUMIFS(M$5:M$639,$A$5:$A$639,$A12,$C$5:$C$639,$C12-1,$D$5:$D$639,$D12))-1)))
A13: NTLC | B13: =IF(A13="","",IFERROR(VLOOKUP(A13,Titres!$A$2:$B$400,2,FALSE),"Ticker inconnu")) | C13: 2023 | D13: T3 | N13: =IF(A13="","",COUNT(H13:M13)/6) | O13: =IF(COUNT(H13:M13)=0,"",IF(LEN(IF(COUNT(I13,J13)=2,IF(J13>I13+1,"EBE > VA ",""),"")&IF(COUNT(H13,M13)=2,IF(ABS(M13)>ABS(H13),"RN > CA ",""),"")&IF(COUNT(H13,K13)=2,IF(ABS(K13)>ABS(H13),"RE > CA ",""),""))=0,"OK",IF(COUNT(I13,J13)=2,IF(J13>I13+1,"EBE > VA ",""),"")&IF(COUNT(H13,M13)=2,IF(ABS(M13)>ABS(H13),"RN > CA ",""),"")&IF(COUNT(H13,K13)=2,IF(ABS(K13)>ABS(H13),"RE > CA ",""),""))) | P13: =IF(OR($A13="",H13="",$C13=""),"",IF(COUNTIFS($A$5:$A$639,$A13,$C$5:$C$639,$C13-1,$D$5:$D$639,$D13,H$5:H$639,"<>")=0,"",IF(OR(SUMIFS(H$5:H$639,$A$5:$A$639,$A13,$C$5:$C$639,$C13-1,$D$5:$D$639,$D13)=0,H13*SUMIFS(H$5:H$639,$A$5:$A$639,$A13,$C$5:$C$639,$C13-1,$D$5:$D$639,$D13)<0),"n.s.",ABS(H13)/ABS(SUMIFS(H$5:H$639,$A$5:$A$639,$A13,$C$5:$C$639,$C13-1,$D$5:$D$639,$D13))-1))) | Q13: =IF(OR($A13="",I13="",$C13=""),"",IF(COUNTIFS($A$5:$A$639,$A13,$C$5:$C$639,$C13-1,$D$5:$D$639,$D13,I$5:I$639,"<>")=0,"",IF(OR(SUMIFS(I$5:I$639,$A$5:$A$639,$A13,$C$5:$C$639,$C13-1,$D$5:$D$639,$D13)=0,I13*SUMIFS(I$5:I$639,$A$5:$A$639,$A13,$C$5:$C$639,$C13-1,$D$5:$D$639,$D13)<0),"n.s.",ABS(I13)/ABS(SUMIFS(I$5:I$639,$A$5:$A$639,$A13,$C$5:$C$639,$C13-1,$D$5:$D$639,$D13))-1))) | R13: =IF(OR($A13="",J13="",$C13=""),"",IF(COUNTIFS($A$5:$A$639,$A13,$C$5:$C$639,$C13-1,$D$5:$D$639,$D13,J$5:J$639,"<>")=0,"",IF(OR(SUMIFS(J$5:J$639,$A$5:$A$639,$A13,$C$5:$C$639,$C13-1,$D$5:$D$639,$D13)=0,J13*SUMIFS(J$5:J$639,$A$5:$A$639,$A13,$C$5:$C$639,$C13-1,$D$5:$D$639,$D13)<0),"n.s.",ABS(J13)/ABS(SUMIFS(J$5:J$639,$A$5:$A$639,$A13,$C$5:$C$639,$C13-1,$D$5:$D$639,$D13))-1))) | S13: =IF(OR($A13="",K13="",$C13=""),"",IF(COUNTIFS($A$5:$A$639,$A13,$C$5:$C$639,$C13-1,$D$5:$D$639,$D13,K$5:K$639,"<>")=0,"",IF(OR(SUMIFS(K$5:K$639,$A$5:$A$639,$A13,$C$5:$C$639,$C13-1,$D$5:$D$639,$D13)=0,K13*SUMIFS(K$5:K$639,$A$5:$A$639,$A13,$C$5:$C$639,$C13-1,$D$5:$D$639,$D13)<0),"n.s.",ABS(K13)/ABS(SUMIFS(K$5:K$639,$A$5:$A$639,$A13,$C$5:$C$639,$C13-1,$D$5:$D$639,$D13))-1))) | T13: =IF(OR($A13="",L13="",$C13=""),"",IF(COUNTIFS($A$5:$A$639,$A13,$C$5:$C$639,$C13-1,$D$5:$D$639,$D13,L$5:L$639,"<>")=0,"",IF(OR(SUMIFS(L$5:L$639,$A$5:$A$639,$A13,$C$5:$C$639,$C13-1,$D$5:$D$639,$D13)=0,L13*SUMIFS(L$5:L$639,$A$5:$A$639,$A13,$C$5:$C$639,$C13-1,$D$5:$D$639,$D13)<0),"n.s.",ABS(L13)/ABS(SUMIFS(L$5:L$639,$A$5:$A$639,$A13,$C$5:$C$639,$C13-1,$D$5:$D$639,$D13))-1))) | U13: =IF(OR($A13="",M13="",$C13=""),"",IF(COUNTIFS($A$5:$A$639,$A13,$C$5:$C$639,$C13-1,$D$5:$D$639,$D13,M$5:M$639,"<>")=0,"",IF(OR(SUMIFS(M$5:M$639,$A$5:$A$639,$A13,$C$5:$C$639,$C13-1,$D$5:$D$639,$D13)=0,M13*SUMIFS(M$5:M$639,$A$5:$A$639,$A13,$C$5:$C$639,$C13-1,$D$5:$D$639,$D13)<0),"n.s.",ABS(M13)/ABS(SUMIFS(M$5:M$639,$A$5:$A$639,$A13,$C$5:$C$639,$C13-1,$D$5:$D$639,$D13))-1)))
A14: NTLC | B14: =IF(A14="","",IFERROR(VLOOKUP(A14,Titres!$A$2:$B$400,2,FALSE),"Ticker inconnu")) | C14: 2024 | D14: T1 | N14: =IF(A14="","",COUNT(H14:M14)/6) | O14: =IF(COUNT(H14:M14)=0,"",IF(LEN(IF(COUNT(I14,J14)=2,IF(J14>I14+1,"EBE > VA ",""),"")&IF(COUNT(H14,M14)=2,IF(ABS(M14)>ABS(H14),"RN > CA ",""),"")&IF(COUNT(H14,K14)=2,IF(ABS(K14)>ABS(H14),"RE > CA ",""),""))=0,"OK",IF(COUNT(I14,J14)=2,IF(J14>I14+1,"EBE > VA ",""),"")&IF(COUNT(H14,M14)=2,IF(ABS(M14)>ABS(H14),"RN > CA ",""),"")&IF(COUNT(H14,K14)=2,IF(ABS(K14)>ABS(H14),"RE > CA ",""),""))) | P14: =IF(OR($A14="",H14="",$C14=""),"",IF(COUNTIFS($A$5:$A$639,$A14,$C$5:$C$639,$C14-1,$D$5:$D$639,$D14,H$5:H$639,"<>")=0,"",IF(OR(SUMIFS(H$5:H$639,$A$5:$A$639,$A14,$C$5:$C$639,$C14-1,$D$5:$D$639,$D14)=0,H14*SUMIFS(H$5:H$639,$A$5:$A$639,$A14,$C$5:$C$639,$C14-1,$D$5:$D$639,$D14)<0),"n.s.",ABS(H14)/ABS(SUMIFS(H$5:H$639,$A$5:$A$639,$A14,$C$5:$C$639,$C14-1,$D$5:$D$639,$D14))-1))) | Q14: =IF(OR($A14="",I14="",$C14=""),"",IF(COUNTIFS($A$5:$A$639,$A14,$C$5:$C$639,$C14-1,$D$5:$D$639,$D14,I$5:I$639,"<>")=0,"",IF(OR(SUMIFS(I$5:I$639,$A$5:$A$639,$A14,$C$5:$C$639,$C14-1,$D$5:$D$639,$D14)=0,I14*SUMIFS(I$5:I$639,$A$5:$A$639,$A14,$C$5:$C$639,$C14-1,$D$5:$D$639,$D14)<0),"n.s.",ABS(I14)/ABS(SUMIFS(I$5:I$639,$A$5:$A$639,$A14,$C$5:$C$639,$C14-1,$D$5:$D$639,$D14))-1))) | R14: =IF(OR($A14="",J14="",$C14=""),"",IF(COUNTIFS($A$5:$A$639,$A14,$C$5:$C$639,$C14-1,$D$5:$D$639,$D14,J$5:J$639,"<>")=0,"",IF(OR(SUMIFS(J$5:J$639,$A$5:$A$639,$A14,$C$5:$C$639,$C14-1,$D$5:$D$639,$D14)=0,J14*SUMIFS(J$5:J$639,$A$5:$A$639,$A14,$C$5:$C$639,$C14-1,$D$5:$D$639,$D14)<0),"n.s.",ABS(J14)/ABS(SUMIFS(J$5:J$639,$A$5:$A$639,$A14,$C$5:$C$639,$C14-1,$D$5:$D$639,$D14))-1))) | S14: =IF(OR($A14="",K14="",$C14=""),"",IF(COUNTIFS($A$5:$A$639,$A14,$C$5:$C$639,$C14-1,$D$5:$D$639,$D14,K$5:K$639,"<>")=0,"",IF(OR(SUMIFS(K$5:K$639,$A$5:$A$639,$A14,$C$5:$C$639,$C14-1,$D$5:$D$639,$D14)=0,K14*SUMIFS(K$5:K$639,$A$5:$A$639,$A14,$C$5:$C$639,$C14-1,$D$5:$D$639,$D14)<0),"n.s.",ABS(K14)/ABS(SUMIFS(K$5:K$639,$A$5:$A$639,$A14,$C$5:$C$639,$C14-1,$D$5:$D$639,$D14))-1))) | T14: =IF(OR($A14="",L14="",$C14=""),"",IF(COUNTIFS($A$5:$A$639,$A14,$C$5:$C$639,$C14-1,$D$5:$D$639,$D14,L$5:L$639,"<>")=0,"",IF(OR(SUMIFS(L$5:L$639,$A$5:$A$639,$A14,$C$5:$C$639,$C14-1,$D$5:$D$639,$D14)=0,L14*SUMIFS(L$5:L$639,$A$5:$A$639,$A14,$C$5:$C$639,$C14-1,$D$5:$D$639,$D14)<0),"n.s.",ABS(L14)/ABS(SUMIFS(L$5:L$639,$A$5:$A$639,$A14,$C$5:$C$639,$C14-1,$D$5:$D$639,$D14))-1))) | U14: =IF(OR($A14="",M14="",$C14=""),"",IF(COUNTIFS($A$5:$A$639,$A14,$C$5:$C$639,$C14-1,$D$5:$D$639,$D14,M$5:M$639,"<>")=0,"",IF(OR(SUMIFS(M$5:M$639,$A$5:$A$639,$A14,$C$5:$C$639,$C14-1,$D$5:$D$639,$D14)=0,M14*SUMIFS(M$5:M$639,$A$5:$A$639,$A14,$C$5:$C$639,$C14-1,$D$5:$D$639,$D14)<0),"n.s.",ABS(M14)/ABS(SUMIFS(M$5:M$639,$A$5:$A$639,$A14,$C$5:$C$639,$C14-1,$D$5:$D$639,$D14))-1)))
A15: NTLC | B15: =IF(A15="","",IFERROR(VLOOKUP(A15,Titres!$A$2:$B$400,2,FALSE),"Ticker inconnu")) | C15: 2024 | D15: S1 | N15: =IF(A15="","",COUNT(H15:M15)/6) | O15: =IF(COUNT(H15:M15)=0,"",IF(LEN(IF(COUNT(I15,J15)=2,IF(J15>I15+1,"EBE > VA ",""),"")&IF(COUNT(H15,M15)=2,IF(ABS(M15)>ABS(H15),"RN > CA ",""),"")&IF(COUNT(H15,K15)=2,IF(ABS(K15)>ABS(H15),"RE > CA ",""),""))=0,"OK",IF(COUNT(I15,J15)=2,IF(J15>I15+1,"EBE > VA ",""),"")&IF(COUNT(H15,M15)=2,IF(ABS(M15)>ABS(H15),"RN > CA ",""),"")&IF(COUNT(H15,K15)=2,IF(ABS(K15)>ABS(H15),"RE > CA ",""),""))) | P15: =IF(OR($A15="",H15="",$C15=""),"",IF(COUNTIFS($A$5:$A$639,$A15,$C$5:$C$639,$C15-1,$D$5:$D$639,$D15,H$5:H$639,"<>")=0,"",IF(OR(SUMIFS(H$5:H$639,$A$5:$A$639,$A15,$C$5:$C$639,$C15-1,$D$5:$D$639,$D15)=0,H15*SUMIFS(H$5:H$639,$A$5:$A$639,$A15,$C$5:$C$639,$C15-1,$D$5:$D$639,$D15)<0),"n.s.",ABS(H15)/ABS(SUMIFS(H$5:H$639,$A$5:$A$639,$A15,$C$5:$C$639,$C15-1,$D$5:$D$639,$D15))-1))) | Q15: =IF(OR($A15="",I15="",$C15=""),"",IF(COUNTIFS($A$5:$A$639,$A15,$C$5:$C$639,$C15-1,$D$5:$D$639,$D15,I$5:I$639,"<>")=0,"",IF(OR(SUMIFS(I$5:I$639,$A$5:$A$639,$A15,$C$5:$C$639,$C15-1,$D$5:$D$639,$D15)=0,I15*SUMIFS(I$5:I$639,$A$5:$A$639,$A15,$C$5:$C$639,$C15-1,$D$5:$D$639,$D15)<0),"n.s.",ABS(I15)/ABS(SUMIFS(I$5:I$639,$A$5:$A$639,$A15,$C$5:$C$639,$C15-1,$D$5:$D$639,$D15))-1))) | R15: =IF(OR($A15="",J15="",$C15=""),"",IF(COUNTIFS($A$5:$A$639,$A15,$C$5:$C$639,$C15-1,$D$5:$D$639,$D15,J$5:J$639,"<>")=0,"",IF(OR(SUMIFS(J$5:J$639,$A$5:$A$639,$A15,$C$5:$C$639,$C15-1,$D$5:$D$639,$D15)=0,J15*SUMIFS(J$5:J$639,$A$5:$A$639,$A15,$C$5:$C$639,$C15-1,$D$5:$D$639,$D15)<0),"n.s.",ABS(J15)/ABS(SUMIFS(J$5:J$639,$A$5:$A$639,$A15,$C$5:$C$639,$C15-1,$D$5:$D$639,$D15))-1))) | S15: =IF(OR($A15="",K15="",$C15=""),"",IF(COUNTIFS($A$5:$A$639,$A15,$C$5:$C$639,$C15-1,$D$5:$D$639,$D15,K$5:K$639,"<>")=0,"",IF(OR(SUMIFS(K$5:K$639,$A$5:$A$639,$A15,$C$5:$C$639,$C15-1,$D$5:$D$639,$D15)=0,K15*SUMIFS(K$5:K$639,$A$5:$A$639,$A15,$C$5:$C$639,$C15-1,$D$5:$D$639,$D15)<0),"n.s.",ABS(K15)/ABS(SUMIFS(K$5:K$639,$A$5:$A$639,$A15,$C$5:$C$639,$C15-1,$D$5:$D$639,$D15))-1))) | T15: =IF(OR($A15="",L15="",$C15=""),"",IF(COUNTIFS($A$5:$A$639,$A15,$C$5:$C$639,$C15-1,$D$5:$D$639,$D15,L$5:L$639,"<>")=0,"",IF(OR(SUMIFS(L$5:L$639,$A$5:$A$639,$A15,$C$5:$C$639,$C15-1,$D$5:$D$639,$D15)=0,L15*SUMIFS(L$5:L$639,$A$5:$A$639,$A15,$C$5:$C$639,$C15-1,$D$5:$D$639,$D15)<0),"n.s.",ABS(L15)/ABS(SUMIFS(L$5:L$639,$A$5:$A$639,$A15,$C$5:$C$639,$C15-1,$D$5:$D$639,$D15))-1))) | U15: =IF(OR($A15="",M15="",$C15=""),"",IF(COUNTIFS($A$5:$A$639,$A15,$C$5:$C$639,$C15-1,$D$5:$D$639,$D15,M$5:M$639,"<>")=0,"",IF(OR(SUMIFS(M$5:M$639,$A$5:$A$639,$A15,$C$5:$C$639,$C15-1,$D$5:$D$639,$D15)=0,M15*SUMIFS(M$5:M$639,$A$5:$A$639,$A15,$C$5:$C$639,$C15-1,$D$5:$D$639,$D15)<0),"n.s.",ABS(M15)/ABS(SUMIFS(M$5:M$639,$A$5:$A$639,$A15,$C$5:$C$639,$C15-1,$D$5:$D$639,$D15))-1)))
A16: NTLC | B16: =IF(A16="","",IFERROR(VLOOKUP(A16,Titres!$A$2:$B$400,2,FALSE),"Ticker inconnu")) | C16: 2024 | D16: T3 | N16: =IF(A16="","",COUNT(H16:M16)/6) | O16: =IF(COUNT(H16:M16)=0,"",IF(LEN(IF(COUNT(I16,J16)=2,IF(J16>I16+1,"EBE > VA ",""),"")&IF(COUNT(H16,M16)=2,IF(ABS(M16)>ABS(H16),"RN > CA ",""),"")&IF(COUNT(H16,K16)=2,IF(ABS(K16)>ABS(H16),"RE > CA ",""),""))=0,"OK",IF(COUNT(I16,J16)=2,IF(J16>I16+1,"EBE > VA ",""),"")&IF(COUNT(H16,M16)=2,IF(ABS(M16)>ABS(H16),"RN > CA ",""),"")&IF(COUNT(H16,K16)=2,IF(ABS(K16)>ABS(H16),"RE > CA ",""),""))) | P16: =IF(OR($A16="",H16="",$C16=""),"",IF(COUNTIFS($A$5:$A$639,$A16,$C$5:$C$639,$C16-1,$D$5:$D$639,$D16,H$5:H$639,"<>")=0,"",IF(OR(SUMIFS(H$5:H$639,$A$5:$A$639,$A16,$C$5:$C$639,$C16-1,$D$5:$D$639,$D16)=0,H16*SUMIFS(H$5:H$639,$A$5:$A$639,$A16,$C$5:$C$639,$C16-1,$D$5:$D$639,$D16)<0),"n.s.",ABS(H16)/ABS(SUMIFS(H$5:H$639,$A$5:$A$639,$A16,$C$5:$C$639,$C16-1,$D$5:$D$639,$D16))-1))) | Q16: =IF(OR($A16="",I16="",$C16=""),"",IF(COUNTIFS($A$5:$A$639,$A16,$C$5:$C$639,$C16-1,$D$5:$D$639,$D16,I$5:I$639,"<>")=0,"",IF(OR(SUMIFS(I$5:I$639,$A$5:$A$639,$A16,$C$5:$C$639,$C16-1,$D$5:$D$639,$D16)=0,I16*SUMIFS(I$5:I$639,$A$5:$A$639,$A16,$C$5:$C$639,$C16-1,$D$5:$D$639,$D16)<0),"n.s.",ABS(I16)/ABS(SUMIFS(I$5:I$639,$A$5:$A$639,$A16,$C$5:$C$639,$C16-1,$D$5:$D$639,$D16))-1))) | R16: =IF(OR($A16="",J16="",$C16=""),"",IF(COUNTIFS($A$5:$A$639,$A16,$C$5:$C$639,$C16-1,$D$5:$D$639,$D16,J$5:J$639,"<>")=0,"",IF(OR(SUMIFS(J$5:J$639,$A$5:$A$639,$A16,$C$5:$C$639,$C16-1,$D$5:$D$639,$D16)=0,J16*SUMIFS(J$5:J$639,$A$5:$A$639,$A16,$C$5:$C$639,$C16-1,$D$5:$D$639,$D16)<0),"n.s.",ABS(J16)/ABS(SUMIFS(J$5:J$639,$A$5:$A$639,$A16,$C$5:$C$639,$C16-1,$D$5:$D$639,$D16))-1))) | S16: =IF(OR($A16="",K16="",$C16=""),"",IF(COUNTIFS($A$5:$A$639,$A16,$C$5:$C$639,$C16-1,$D$5:$D$639,$D16,K$5:K$639,"<>")=0,"",IF(OR(SUMIFS(K$5:K$639,$A$5:$A$639,$A16,$C$5:$C$639,$C16-1,$D$5:$D$639,$D16)=0,K16*SUMIFS(K$5:K$639,$A$5:$A$639,$A16,$C$5:$C$639,$C16-1,$D$5:$D$639,$D16)<0),"n.s.",ABS(K16)/ABS(SUMIFS(K$5:K$639,$A$5:$A$639,$A16,$C$5:$C$639,$C16-1,$D$5:$D$639,$D16))-1))) | T16: =IF(OR($A16="",L16="",$C16=""),"",IF(COUNTIFS($A$5:$A$639,$A16,$C$5:$C$639,$C16-1,$D$5:$D$639,$D16,L$5:L$639,"<>")=0,"",IF(OR(SUMIFS(L$5:L$639,$A$5:$A$639,$A16,$C$5:$C$639,$C16-1,$D$5:$D$639,$D16)=0,L16*SUMIFS(L$5:L$639,$A$5:$A$639,$A16,$C$5:$C$639,$C16-1,$D$5:$D$639,$D16)<0),"n.s.",ABS(L16)/ABS(SUMIFS(L$5:L$639,$A$5:$A$639,$A16,$C$5:$C$639,$C16-1,$D$5:$D$639,$D16))-1))) | U16: =IF(OR($A16="",M16="",$C16=""),"",IF(COUNTIFS($A$5:$A$639,$A16,$C$5:$C$639,$C16-1,$D$5:$D$639,$D16,M$5:M$639,"<>")=0,"",IF(OR(SUMIFS(M$5:M$639,$A$5:$A$639,$A16,$C$5:$C$639,$C16-1,$D$5:$D$639,$D16)=0,M16*SUMIFS(M$5:M$639,$A$5:$A$639,$A16,$C$5:$C$639,$C16-1,$D$5:$D$639,$D16)<0),"n.s.",ABS(M16)/ABS(SUMIFS(M$5:M$639,$A$5:$A$639,$A16,$C$5:$C$639,$C16-1,$D$5:$D$639,$D16))-1)))
A17: NTLC | B17: =IF(A17="","",IFERROR(VLOOKUP(A17,Titres!$A$2:$B$400,2,FALSE),"Ticker inconnu")) | C17: 2025 | D17: T1 | E17: Publié | F17: 46142 | G17: https://www.richbourse.com/common/actualite/afficher-fichier/30-04-2026-nestle-ci-rapport-dactivites-1er-trimestre-2026 (comparatif N-1) | H17: 54079.13 | L17: 9487.853 | M17: 5479.04 | N17: =IF(A17="","",COUNT(H17:M17)/6) | O17: =IF(COUNT(H17:M17)=0,"",IF(LEN(IF(COUNT(I17,J17)=2,IF(J17>I17+1,"EBE > VA ",""),"")&IF(COUNT(H17,M17)=2,IF(ABS(M17)>ABS(H17),"RN > CA ",""),"")&IF(COUNT(H17,K17)=2,IF(ABS(K17)>ABS(H17),"RE > CA ",""),""))=0,"OK",IF(COUNT(I17,J17)=2,IF(J17>I17+1,"EBE > VA ",""),"")&IF(COUNT(H17,M17)=2,IF(ABS(M17)>ABS(H17),"RN > CA ",""),"")&IF(COUNT(H17,K17)=2,IF(ABS(K17)>ABS(H17),"RE > CA ",""),""))) | P17: =IF(OR($A17="",H17="",$C17=""),"",IF(COUNTIFS($A$5:$A$639,$A17,$C$5:$C$639,$C17-1,$D$5:$D$639,$D17,H$5:H$639,"<>")=0,"",IF(OR(SUMIFS(H$5:H$639,$A$5:$A$639,$A17,$C$5:$C$639,$C17-1,$D$5:$D$639,$D17)=0,H17*SUMIFS(H$5:H$639,$A$5:$A$639,$A17,$C$5:$C$639,$C17-1,$D$5:$D$639,$D17)<0),"n.s.",ABS(H17)/ABS(SUMIFS(H$5:H$639,$A$5:$A$639,$A17,$C$5:$C$639,$C17-1,$D$5:$D$639,$D17))-1))) | Q17: =IF(OR($A17="",I17="",$C17=""),"",IF(COUNTIFS($A$5:$A$639,$A17,$C$5:$C$639,$C17-1,$D$5:$D$639,$D17,I$5:I$639,"<>")=0,"",IF(OR(SUMIFS(I$5:I$639,$A$5:$A$639,$A17,$C$5:$C$639,$C17-1,$D$5:$D$639,$D17)=0,I17*SUMIFS(I$5:I$639,$A$5:$A$639,$A17,$C$5:$C$639,$C17-1,$D$5:$D$639,$D17)<0),"n.s.",ABS(I17)/ABS(SUMIFS(I$5:I$639,$A$5:$A$639,$A17,$C$5:$C$639,$C17-1,$D$5:$D$639,$D17))-1))) | R17: =IF(OR($A17="",J17="",$C17=""),"",IF(COUNTIFS($A$5:$A$639,$A17,$C$5:$C$639,$C17-1,$D$5:$D$639,$D17,J$5:J$639,"<>")=0,"",IF(OR(SUMIFS(J$5:J$639,$A$5:$A$639,$A17,$C$5:$C$639,$C17-1,$D$5:$D$639,$D17)=0,J17*SUMIFS(J$5:J$639,$A$5:$A$639,$A17,$C$5:$C$639,$C17-1,$D$5:$D$639,$D17)<0),"n.s.",ABS(J17)/ABS(SUMIFS(J$5:J$639,$A$5:$A$639,$A17,$C$5:$C$639,$C17-1,$D$5:$D$639,$D17))-1))) | S17: =IF(OR($A17="",K17="",$C17=""),"",IF(COUNTIFS($A$5:$A$639,$A17,$C$5:$C$639,$C17-1,$D$5:$D$639,$D17,K$5:K$639,"<>")=0,"",IF(OR(SUMIFS(K$5:K$639,$A$5:$A$639,$A17,$C$5:$C$639,$C17-1,$D$5:$D$639,$D17)=0,K17*SUMIFS(K$5:K$639,$A$5:$A$639,$A17,$C$5:$C$639,$C17-1,$D$5:$D$639,$D17)<0),"n.s.",ABS(K17)/ABS(SUMIFS(K$5:K$639,$A$5:$A$639,$A17,$C$5:$C$639,$C17-1,$D$5:$D$639,$D17))-1))) | T17: =IF(OR($A17="",L17="",$C17=""),"",IF(COUNTIFS($A$5:$A$639,$A17,$C$5:$C$639,$C17-1,$D$5:$D$639,$D17,L$5:L$639,"<>")=0,"",IF(OR(SUMIFS(L$5:L$639,$A$5:$A$639,$A17,$C$5:$C$639,$C17-1,$D$5:$D$639,$D17)=0,L17*SUMIFS(L$5:L$639,$A$5:$A$639,$A17,$C$5:$C$639,$C17-1,$D$5:$D$639,$D17)<0),"n.s.",ABS(L17)/ABS(SUMIFS(L$5:L$639,$A$5:$A$639,$A17,$C$5:$C$639,$C17-1,$D$5:$D$639,$D17))-1))) | U17: =IF(OR($A17="",M17="",$C17=""),"",IF(COUNTIFS($A$5:$A$639,$A17,$C$5:$C$639,$C17-1,$D$5:$D$639,$D17,M$5:M$639,"<>")=0,"",IF(OR(SUMIFS(M$5:M$639,$A$5:$A$639,$A17,$C$5:$C$639,$C17-1,$D$5:$D$639,$D17)=0,M17*SUMIFS(M$5:M$639,$A$5:$A$639,$A17,$C$5:$C$639,$C17-1,$D$5:$D$639,$D17)<0),"n.s.",ABS(M17)/ABS(SUMIFS(M$5:M$639,$A$5:$A$639,$A17,$C$5:$C$639,$C17-1,$D$5:$D$639,$D17))-1)))
A18: NTLC | B18: =IF(A18="","",IFERROR(VLOOKUP(A18,Titres!$A$2:$B$400,2,FALSE),"Ticker inconnu")) | C18: 2025 | D18: S1 | N18: =IF(A18="","",COUNT(H18:M18)/6) | O18: =IF(COUNT(H18:M18)=0,"",IF(LEN(IF(COUNT(I18,J18)=2,IF(J18>I18+1,"EBE > VA ",""),"")&IF(COUNT(H18,M18)=2,IF(ABS(M18)>ABS(H18),"RN > CA ",""),"")&IF(COUNT(H18,K18)=2,IF(ABS(K18)>ABS(H18),"RE > CA ",""),""))=0,"OK",IF(COUNT(I18,J18)=2,IF(J18>I18+1,"EBE > VA ",""),"")&IF(COUNT(H18,M18)=2,IF(ABS(M18)>ABS(H18),"RN > CA ",""),"")&IF(COUNT(H18,K18)=2,IF(ABS(K18)>ABS(H18),"RE > CA ",""),""))) | P18: =IF(OR($A18="",H18="",$C18=""),"",IF(COUNTIFS($A$5:$A$639,$A18,$C$5:$C$639,$C18-1,$D$5:$D$639,$D18,H$5:H$639,"<>")=0,"",IF(OR(SUMIFS(H$5:H$639,$A$5:$A$639,$A18,$C$5:$C$639,$C18-1,$D$5:$D$639,$D18)=0,H18*SUMIFS(H$5:H$639,$A$5:$A$639,$A18,$C$5:$C$639,$C18-1,$D$5:$D$639,$D18)<0),"n.s.",ABS(H18)/ABS(SUMIFS(H$5:H$639,$A$5:$A$639,$A18,$C$5:$C$639,$C18-1,$D$5:$D$639,$D18))-1))) | Q18: =IF(OR($A18="",I18="",$C18=""),"",IF(COUNTIFS($A$5:$A$639,$A18,$C$5:$C$639,$C18-1,$D$5:$D$639,$D18,I$5:I$639,"<>")=0,"",IF(OR(SUMIFS(I$5:I$639,$A$5:$A$639,$A18,$C$5:$C$639,$C18-1,$D$5:$D$639,$D18)=0,I18*SUMIFS(I$5:I$639,$A$5:$A$639,$A18,$C$5:$C$639,$C18-1,$D$5:$D$639,$D18)<0),"n.s.",ABS(I18)/ABS(SUMIFS(I$5:I$639,$A$5:$A$639,$A18,$C$5:$C$639,$C18-1,$D$5:$D$639,$D18))-1))) | R18: =IF(OR($A18="",J18="",$C18=""),"",IF(COUNTIFS($A$5:$A$639,$A18,$C$5:$C$639,$C18-1,$D$5:$D$639,$D18,J$5:J$639,"<>")=0,"",IF(OR(SUMIFS(J$5:J$639,$A$5:$A$639,$A18,$C$5:$C$639,$C18-1,$D$5:$D$639,$D18)=0,J18*SUMIFS(J$5:J$639,$A$5:$A$639,$A18,$C$5:$C$639,$C18-1,$D$5:$D$639,$D18)<0),"n.s.",ABS(J18)/ABS(SUMIFS(J$5:J$639,$A$5:$A$639,$A18,$C$5:$C$639,$C18-1,$D$5:$D$639,$D18))-1))) | S18: =IF(OR($A18="",K18="",$C18=""),"",IF(COUNTIFS($A$5:$A$639,$A18,$C$5:$C$639,$C18-1,$D$5:$D$639,$D18,K$5:K$639,"<>")=0,"",IF(OR(SUMIFS(K$5:K$639,$A$5:$A$639,$A18,$C$5:$C$639,$C18-1,$D$5:$D$639,$D18)=0,K18*SUMIFS(K$5:K$639,$A$5:$A$639,$A18,$C$5:$C$639,$C18-1,$D$5:$D$639,$D18)<0),"n.s.",ABS(K18)/ABS(SUMIFS(K$5:K$639,$A$5:$A$639,$A18,$C$5:$C$639,$C18-1,$D$5:$D$639,$D18))-1))) | T18: =IF(OR($A18="",L18="",$C18=""),"",IF(COUNTIFS($A$5:$A$639,$A18,$C$5:$C$639,$C18-1,$D$5:$D$639,$D18,L$5:L$639,"<>")=0,"",IF(OR(SUMIFS(L$5:L$639,$A$5:$A$639,$A18,$C$5:$C$639,$C18-1,$D$5:$D$639,$D18)=0,L18*SUMIFS(L$5:L$639,$A$5:$A$639,$A18,$C$5:$C$639,$C18-1,$D$5:$D$639,$D18)<0),"n.s.",ABS(L18)/ABS(SUMIFS(L$5:L$639,$A$5:$A$639,$A18,$C$5:$C$639,$C18-1,$D$5:$D$639,$D18))-1))) | U18: =IF(OR($A18="",M18="",$C18=""),"",IF(COUNTIFS($A$5:$A$639,$A18,$C$5:$C$639,$C18-1,$D$5:$D$639,$D18,M$5:M$639,"<>")=0,"",IF(OR(SUMIFS(M$5:M$639,$A$5:$A$639,$A18,$C$5:$C$639,$C18-1,$D$5:$D$639,$D18)=0,M18*SUMIFS(M$5:M$639,$A$5:$A$639,$A18,$C$5:$C$639,$C18-1,$D$5:$D$639,$D18)<0),"n.s.",ABS(M18)/ABS(SUMIFS(M$5:M$639,$A$5:$A$639,$A18,$C$5:$C$639,$C18-1,$D$5:$D$639,$D18))-1)))
A19: NTLC | B19: =IF(A19="","",IFERROR(VLOOKUP(A19,Titres!$A$2:$B$400,2,FALSE),"Ticker inconnu")) | C19: 2025 | D19: T3 | N19: =IF(A19="","",COUNT(H19:M19)/6) | O19: =IF(COUNT(H19:M19)=0,"",IF(LEN(IF(COUNT(I19,J19)=2,IF(J19>I19+1,"EBE > VA ",""),"")&IF(COUNT(H19,M19)=2,IF(ABS(M19)>ABS(H19),"RN > CA ",""),"")&IF(COUNT(H19,K19)=2,IF(ABS(K19)>ABS(H19),"RE > CA ",""),""))=0,"OK",IF(COUNT(I19,J19)=2,IF(J19>I19+1,"EBE > VA ",""),"")&IF(COUNT(H19,M19)=2,IF(ABS(M19)>ABS(H19),"RN > CA ",""),"")&IF(COUNT(H19,K19)=2,IF(ABS(K19)>ABS(H19),"RE > CA ",""),""))) | P19: =IF(OR($A19="",H19="",$C19=""),"",IF(COUNTIFS($A$5:$A$639,$A19,$C$5:$C$639,$C19-1,$D$5:$D$639,$D19,H$5:H$639,"<>")=0,"",IF(OR(SUMIFS(H$5:H$639,$A$5:$A$639,$A19,$C$5:$C$639,$C19-1,$D$5:$D$639,$D19)=0,H19*SUMIFS(H$5:H$639,$A$5:$A$639,$A19,$C$5:$C$639,$C19-1,$D$5:$D$639,$D19)<0),"n.s.",ABS(H19)/ABS(SUMIFS(H$5:H$639,$A$5:$A$639,$A19,$C$5:$C$639,$C19-1,$D$5:$D$639,$D19))-1))) | Q19: =IF(OR($A19="",I19="",$C19=""),"",IF(COUNTIFS($A$5:$A$639,$A19,$C$5:$C$639,$C19-1,$D$5:$D$639,$D19,I$5:I$639,"<>")=0,"",IF(OR(SUMIFS(I$5:I$639,$A$5:$A$639,$A19,$C$5:$C$639,$C19-1,$D$5:$D$639,$D19)=0,I19*SUMIFS(I$5:I$639,$A$5:$A$639,$A19,$C$5:$C$639,$C19-1,$D$5:$D$639,$D19)<0),"n.s.",ABS(I19)/ABS(SUMIFS(I$5:I$639,$A$5:$A$639,$A19,$C$5:$C$639,$C19-1,$D$5:$D$639,$D19))-1))) | R19: =IF(OR($A19="",J19="",$C19=""),"",IF(COUNTIFS($A$5:$A$639,$A19,$C$5:$C$639,$C19-1,$D$5:$D$639,$D19,J$5:J$639,"<>")=0,"",IF(OR(SUMIFS(J$5:J$639,$A$5:$A$639,$A19,$C$5:$C$639,$C19-1,$D$5:$D$639,$D19)=0,J19*SUMIFS(J$5:J$639,$A$5:$A$639,$A19,$C$5:$C$639,$C19-1,$D$5:$D$639,$D19)<0),"n.s.",ABS(J19)/ABS(SUMIFS(J$5:J$639,$A$5:$A$639,$A19,$C$5:$C$639,$C19-1,$D$5:$D$639,$D19))-1))) | S19: =IF(OR($A19="",K19="",$C19=""),"",IF(COUNTIFS($A$5:$A$639,$A19,$C$5:$C$639,$C19-1,$D$5:$D$639,$D19,K$5:K$639,"<>")=0,"",IF(OR(SUMIFS(K$5:K$639,$A$5:$A$639,$A19,$C$5:$C$639,$C19-1,$D$5:$D$639,$D19)=0,K19*SUMIFS(K$5:K$639,$A$5:$A$639,$A19,$C$5:$C$639,$C19-1,$D$5:$D$639,$D19)<0),"n.s.",ABS(K19)/ABS(SUMIFS(K$5:K$639,$A$5:$A$639,$A19,$C$5:$C$639,$C19-1,$D$5:$D$639,$D19))-1))) | T19: =IF(OR($A19="",L19="",$C19=""),"",IF(COUNTIFS($A$5:$A$639,$A19,$C$5:$C$639,$C19-1,$D$5:$D$639,$D19,L$5:L$639,"<>")=0,"",IF(OR(SUMIFS(L$5:L$639,$A$5:$A$639,$A19,$C$5:$C$639,$C19-1,$D$5:$D$639,$D19)=0,L19*SUMIFS(L$5:L$639,$A$5:$A$639,$A19,$C$5:$C$639,$C19-1,$D$5:$D$639,$D19)<0),"n.s.",ABS(L19)/ABS(SUMIFS(L$5:L$639,$A$5:$A$639,$A19,$C$5:$C$639,$C19-1,$D$5:$D$639,$D19))-1))) | U19: =IF(OR($A19="",M19="",$C19=""),"",IF(COUNTIFS($A$5:$A$639,$A19,$C$5:$C$639,$C19-1,$D$5:$D$639,$D19,M$5:M$639,"<>")=0,"",IF(OR(SUMIFS(M$5:M$639,$A$5:$A$639,$A19,$C$5:$C$639,$C19-1,$D$5:$D$639,$D19)=0,M19*SUMIFS(M$5:M$639,$A$5:$A$639,$A19,$C$5:$C$639,$C19-1,$D$5:$D$639,$D19)<0),"n.s.",ABS(M19)/ABS(SUMIFS(M$5:M$639,$A$5:$A$639,$A19,$C$5:$C$639,$C19-1,$D$5:$D$639,$D19))-1)))
A20: NTLC | B20: =IF(A20="","",IFERROR(VLOOKUP(A20,Titres!$A$2:$B$400,2,FALSE),"Ticker inconnu")) | C20: 2026 | D20: T1 | E20: Publié | F20: 46142 | G20: https://www.richbourse.com/common/actualite/afficher-fichier/30-04-2026-nestle-ci-rapport-dactivites-1er-trimestre-2026 | H20: 70821.658 | L20: 10874.637 | M20: 7525.623 | N20: =IF(A20="","",COUNT(H20:M20)/6) | O20: =IF(COUNT(H20:M20)=0,"",IF(LEN(IF(COUNT(I20,J20)=2,IF(J20>I20+1,"EBE > VA ",""),"")&IF(COUNT(H20,M20)=2,IF(ABS(M20)>ABS(H20),"RN > CA ",""),"")&IF(COUNT(H20,K20)=2,IF(ABS(K20)>ABS(H20),"RE > CA ",""),""))=0,"OK",IF(COUNT(I20,J20)=2,IF(J20>I20+1,"EBE > VA ",""),"")&IF(COUNT(H20,M20)=2,IF(ABS(M20)>ABS(H20),"RN > CA ",""),"")&IF(COUNT(H20,K20)=2,IF(ABS(K20)>ABS(H20),"RE > CA ",""),""))) | P20: =IF(OR($A20="",H20="",$C20=""),"",IF(COUNTIFS($A$5:$A$639,$A20,$C$5:$C$639,$C20-1,$D$5:$D$639,$D20,H$5:H$639,"<>")=0,"",IF(OR(SUMIFS(H$5:H$639,$A$5:$A$639,$A20,$C$5:$C$639,$C20-1,$D$5:$D$639,$D20)=0,H20*SUMIFS(H$5:H$639,$A$5:$A$639,$A20,$C$5:$C$639,$C20-1,$D$5:$D$639,$D20)<0),"n.s.",ABS(H20)/ABS(SUMIFS(H$5:H$639,$A$5:$A$639,$A20,$C$5:$C$639,$C20-1,$D$5:$D$639,$D20))-1))) | Q20: =IF(OR($A20="",I20="",$C20=""),"",IF(COUNTIFS($A$5:$A$639,$A20,$C$5:$C$639,$C20-1,$D$5:$D$639,$D20,I$5:I$639,"<>")=0,"",IF(OR(SUMIFS(I$5:I$639,$A$5:$A$639,$A20,$C$5:$C$639,$C20-1,$D$5:$D$639,$D20)=0,I20*SUMIFS(I$5:I$639,$A$5:$A$639,$A20,$C$5:$C$639,$C20-1,$D$5:$D$639,$D20)<0),"n.s.",ABS(I20)/ABS(SUMIFS(I$5:I$639,$A$5:$A$639,$A20,$C$5:$C$639,$C20-1,$D$5:$D$639,$D20))-1))) | R20: =IF(OR($A20="",J20="",$C20=""),"",IF(COUNTIFS($A$5:$A$639,$A20,$C$5:$C$639,$C20-1,$D$5:$D$639,$D20,J$5:J$639,"<>")=0,"",IF(OR(SUMIFS(J$5:J$639,$A$5:$A$639,$A20,$C$5:$C$639,$C20-1,$D$5:$D$639,$D20)=0,J20*SUMIFS(J$5:J$639,$A$5:$A$639,$A20,$C$5:$C$639,$C20-1,$D$5:$D$639,$D20)<0),"n.s.",ABS(J20)/ABS(SUMIFS(J$5:J$639,$A$5:$A$639,$A20,$C$5:$C$639,$C20-1,$D$5:$D$639,$D20))-1))) | S20: =IF(OR($A20="",K20="",$C20=""),"",IF(COUNTIFS($A$5:$A$639,$A20,$C$5:$C$639,$C20-1,$D$5:$D$639,$D20,K$5:K$639,"<>")=0,"",IF(OR(SUMIFS(K$5:K$639,$A$5:$A$639,$A20,$C$5:$C$639,$C20-1,$D$5:$D$639,$D20)=0,K20*SUMIFS(K$5:K$639,$A$5:$A$639,$A20,$C$5:$C$639,$C20-1,$D$5:$D$639,$D20)<0),"n.s.",ABS(K20)/ABS(SUMIFS(K$5:K$639,$A$5:$A$639,$A20,$C$5:$C$639,$C20-1,$D$5:$D$639,$D20))-1))) | T20: =IF(OR($A20="",L20="",$C20=""),"",IF(COUNTIFS($A$5:$A$639,$A20,$C$5:$C$639,$C20-1,$D$5:$D$639,$D20,L$5:L$639,"<>")=0,"",IF(OR(SUMIFS(L$5:L$639,$A$5:$A$639,$A20,$C$5:$C$639,$C20-1,$D$5:$D$639,$D20)=0,L20*SUMIFS(L$5:L$639,$A$5:$A$639,$A20,$C$5:$C$639,$C20-1,$D$5:$D$639,$D20)<0),"n.s.",ABS(L20)/ABS(SUMIFS(L$5:L$639,$A$5:$A$639,$A20,$C$5:$C$639,$C20-1,$D$5:$D$639,$D20))-1))) | U20: =IF(OR($A20="",M20="",$C20=""),"",IF(COUNTIFS($A$5:$A$639,$A20,$C$5:$C$639,$C20-1,$D$5:$D$639,$D20,M$5:M$639,"<>")=0,"",IF(OR(SUMIFS(M$5:M$639,$A$5:$A$639,$A20,$C$5:$C$639,$C20-1,$D$5:$D$639,$D20)=0,M20*SUMIFS(M$5:M$639,$A$5:$A$639,$A20,$C$5:$C$639,$C20-1,$D$5:$D$639,$D20)<0),"n.s.",ABS(M20)/ABS(SUMIFS(M$5:M$639,$A$5:$A$639,$A20,$C$5:$C$639,$C20-1,$D$5:$D$639,$D20))-1)))
A21: NTLC | B21: =IF(A21="","",IFERROR(VLOOKUP(A21,Titres!$A$2:$B$400,2,FALSE),"Ticker inconnu")) | C21: 2026 | D21: S1 | N21: =IF(A21="","",COUNT(H21:M21)/6) | O21: =IF(COUNT(H21:M21)=0,"",IF(LEN(IF(COUNT(I21,J21)=2,IF(J21>I21+1,"EBE > VA ",""),"")&IF(COUNT(H21,M21)=2,IF(ABS(M21)>ABS(H21),"RN > CA ",""),"")&IF(COUNT(H21,K21)=2,IF(ABS(K21)>ABS(H21),"RE > CA ",""),""))=0,"OK",IF(COUNT(I21,J21)=2,IF(J21>I21+1,"EBE > VA ",""),"")&IF(COUNT(H21,M21)=2,IF(ABS(M21)>ABS(H21),"RN > CA ",""),"")&IF(COUNT(H21,K21)=2,IF(ABS(K21)>ABS(H21),"RE > CA ",""),""))) | P21: =IF(OR($A21="",H21="",$C21=""),"",IF(COUNTIFS($A$5:$A$639,$A21,$C$5:$C$639,$C21-1,$D$5:$D$639,$D21,H$5:H$639,"<>")=0,"",IF(OR(SUMIFS(H$5:H$639,$A$5:$A$639,$A21,$C$5:$C$639,$C21-1,$D$5:$D$639,$D21)=0,H21*SUMIFS(H$5:H$639,$A$5:$A$639,$A21,$C$5:$C$639,$C21-1,$D$5:$D$639,$D21)<0),"n.s.",ABS(H21)/ABS(SUMIFS(H$5:H$639,$A$5:$A$639,$A21,$C$5:$C$639,$C21-1,$D$5:$D$639,$D21))-1))) | Q21: =IF(OR($A21="",I21="",$C21=""),"",IF(COUNTIFS($A$5:$A$639,$A21,$C$5:$C$639,$C21-1,$D$5:$D$639,$D21,I$5:I$639,"<>")=0,"",IF(OR(SUMIFS(I$5:I$639,$A$5:$A$639,$A21,$C$5:$C$639,$C21-1,$D$5:$D$639,$D21)=0,I21*SUMIFS(I$5:I$639,$A$5:$A$639,$A21,$C$5:$C$639,$C21-1,$D$5:$D$639,$D21)<0),"n.s.",ABS(I21)/ABS(SUMIFS(I$5:I$639,$A$5:$A$639,$A21,$C$5:$C$639,$C21-1,$D$5:$D$639,$D21))-1))) | R21: =IF(OR($A21="",J21="",$C21=""),"",IF(COUNTIFS($A$5:$A$639,$A21,$C$5:$C$639,$C21-1,$D$5:$D$639,$D21,J$5:J$639,"<>")=0,"",IF(OR(SUMIFS(J$5:J$639,$A$5:$A$639,$A21,$C$5:$C$639,$C21-1,$D$5:$D$639,$D21)=0,J21*SUMIFS(J$5:J$639,$A$5:$A$639,$A21,$C$5:$C$639,$C21-1,$D$5:$D$639,$D21)<0),"n.s.",ABS(J21)/ABS(SUMIFS(J$5:J$639,$A$5:$A$639,$A21,$C$5:$C$639,$C21-1,$D$5:$D$639,$D21))-1))) | S21: =IF(OR($A21="",K21="",$C21=""),"",IF(COUNTIFS($A$5:$A$639,$A21,$C$5:$C$639,$C21-1,$D$5:$D$639,$D21,K$5:K$639,"<>")=0,"",IF(OR(SUMIFS(K$5:K$639,$A$5:$A$639,$A21,$C$5:$C$639,$C21-1,$D$5:$D$639,$D21)=0,K21*SUMIFS(K$5:K$639,$A$5:$A$639,$A21,$C$5:$C$639,$C21-1,$D$5:$D$639,$D21)<0),"n.s.",ABS(K21)/ABS(SUMIFS(K$5:K$639,$A$5:$A$639,$A21,$C$5:$C$639,$C21-1,$D$5:$D$639,$D21))-1))) | T21: =IF(OR($A21="",L21="",$C21=""),"",IF(COUNTIFS($A$5:$A$639,$A21,$C$5:$C$639,$C21-1,$D$5:$D$639,$D21,L$5:L$639,"<>")=0,"",IF(OR(SUMIFS(L$5:L$639,$A$5:$A$639,$A21,$C$5:$C$639,$C21-1,$D$5:$D$639,$D21)=0,L21*SUMIFS(L$5:L$639,$A$5:$A$639,$A21,$C$5:$C$639,$C21-1,$D$5:$D$639,$D21)<0),"n.s.",ABS(L21)/ABS(SUMIFS(L$5:L$639,$A$5:$A$639,$A21,$C$5:$C$639,$C21-1,$D$5:$D$639,$D21))-1))) | U21: =IF(OR($A21="",M21="",$C21=""),"",IF(COUNTIFS($A$5:$A$639,$A21,$C$5:$C$639,$C21-1,$D$5:$D$639,$D21,M$5:M$639,"<>")=0,"",IF(OR(SUMIFS(M$5:M$639,$A$5:$A$639,$A21,$C$5:$C$639,$C21-1,$D$5:$D$639,$D21)=0,M21*SUMIFS(M$5:M$639,$A$5:$A$639,$A21,$C$5:$C$639,$C21-1,$D$5:$D$639,$D21)<0),"n.s.",ABS(M21)/ABS(SUMIFS(M$5:M$639,$A$5:$A$639,$A21,$C$5:$C$639,$C21-1,$D$5:$D$639,$D21))-1)))
A22: NTLC | B22: =IF(A22="","",IFERROR(VLOOKUP(A22,Titres!$A$2:$B$400,2,FALSE),"Ticker inconnu")) | C22: 2026 | D22: T3 | N22: =IF(A22="","",COUNT(H22:M22)/6) | O22: =IF(COUNT(H22:M22)=0,"",IF(LEN(IF(COUNT(I22,J22)=2,IF(J22>I22+1,"EBE > VA ",""),"")&IF(COUNT(H22,M22)=2,IF(ABS(M22)>ABS(H22),"RN > CA ",""),"")&IF(COUNT(H22,K22)=2,IF(ABS(K22)>ABS(H22),"RE > CA ",""),""))=0,"OK",IF(COUNT(I22,J22)=2,IF(J22>I22+1,"EBE > VA ",""),"")&IF(COUNT(H22,M22)=2,IF(ABS(M22)>ABS(H22),"RN > CA ",""),"")&IF(COUNT(H22,K22)=2,IF(ABS(K22)>ABS(H22),"RE > CA ",""),""))) | P22: =IF(OR($A22="",H22="",$C22=""),"",IF(COUNTIFS($A$5:$A$639,$A22,$C$5:$C$639,$C22-1,$D$5:$D$639,$D22,H$5:H$639,"<>")=0,"",IF(OR(SUMIFS(H$5:H$639,$A$5:$A$639,$A22,$C$5:$C$639,$C22-1,$D$5:$D$639,$D22)=0,H22*SUMIFS(H$5:H$639,$A$5:$A$639,$A22,$C$5:$C$639,$C22-1,$D$5:$D$639,$D22)<0),"n.s.",ABS(H22)/ABS(SUMIFS(H$5:H$639,$A$5:$A$639,$A22,$C$5:$C$639,$C22-1,$D$5:$D$639,$D22))-1))) | Q22: =IF(OR($A22="",I22="",$C22=""),"",IF(COUNTIFS($A$5:$A$639,$A22,$C$5:$C$639,$C22-1,$D$5:$D$639,$D22,I$5:I$639,"<>")=0,"",IF(OR(SUMIFS(I$5:I$639,$A$5:$A$639,$A22,$C$5:$C$639,$C22-1,$D$5:$D$639,$D22)=0,I22*SUMIFS(I$5:I$639,$A$5:$A$639,$A22,$C$5:$C$639,$C22-1,$D$5:$D$639,$D22)<0),"n.s.",ABS(I22)/ABS(SUMIFS(I$5:I$639,$A$5:$A$639,$A22,$C$5:$C$639,$C22-1,$D$5:$D$639,$D22))-1))) | R22: =IF(OR($A22="",J22="",$C22=""),"",IF(COUNTIFS($A$5:$A$639,$A22,$C$5:$C$639,$C22-1,$D$5:$D$639,$D22,J$5:J$639,"<>")=0,"",IF(OR(SUMIFS(J$5:J$639,$A$5:$A$639,$A22,$C$5:$C$639,$C22-1,$D$5:$D$639,$D22)=0,J22*SUMIFS(J$5:J$639,$A$5:$A$639,$A22,$C$5:$C$639,$C22-1,$D$5:$D$639,$D22)<0),"n.s.",ABS(J22)/ABS(SUMIFS(J$5:J$639,$A$5:$A$639,$A22,$C$5:$C$639,$C22-1,$D$5:$D$639,$D22))-1))) | S22: =IF(OR($A22="",K22="",$C22=""),"",IF(COUNTIFS($A$5:$A$639,$A22,$C$5:$C$639,$C22-1,$D$5:$D$639,$D22,K$5:K$639,"<>")=0,"",IF(OR(SUMIFS(K$5:K$639,$A$5:$A$639,$A22,$C$5:$C$639,$C22-1,$D$5:$D$639,$D22)=0,K22*SUMIFS(K$5:K$639,$A$5:$A$639,$A22,$C$5:$C$639,$C22-1,$D$5:$D$639,$D22)<0),"n.s.",ABS(K22)/ABS(SUMIFS(K$5:K$639,$A$5:$A$639,$A22,$C$5:$C$639,$C22-1,$D$5:$D$639,$D22))-1))) | T22: =IF(OR($A22="",L22="",$C22=""),"",IF(COUNTIFS($A$5:$A$639,$A22,$C$5:$C$639,$C22-1,$D$5:$D$639,$D22,L$5:L$639,"<>")=0,"",IF(OR(SUMIFS(L$5:L$639,$A$5:$A$639,$A22,$C$5:$C$639,$C22-1,$D$5:$D$639,$D22)=0,L22*SUMIFS(L$5:L$639,$A$5:$A$639,$A22,$C$5:$C$639,$C22-1,$D$5:$D$639,$D22)<0),"n.s.",ABS(L22)/ABS(SUMIFS(L$5:L$639,$A$5:$A$639,$A22,$C$5:$C$639,$C22-1,$D$5:$D$639,$D22))-1))) | U22: =IF(OR($A22="",M22="",$C22=""),"",IF(COUNTIFS($A$5:$A$639,$A22,$C$5:$C$639,$C22-1,$D$5:$D$639,$D22,M$5:M$639,"<>")=0,"",IF(OR(SUMIFS(M$5:M$639,$A$5:$A$639,$A22,$C$5:$C$639,$C22-1,$D$5:$D$639,$D22)=0,M22*SUMIFS(M$5:M$639,$A$5:$A$639,$A22,$C$5:$C$639,$C22-1,$D$5:$D$639,$D22)<0),"n.s.",ABS(M22)/ABS(SUMIFS(M$5:M$639,$A$5:$A$639,$A22,$C$5:$C$639,$C22-1,$D$5:$D$639,$D22))-1)))
A23: PALC | B23: =IF(A23="","",IFERROR(VLOOKUP(A23,Titres!$A$2:$B$400,2,FALSE),"Ticker inconnu")) | C23: 2021 | D23: T1 | N23: =IF(A23="","",COUNT(H23:M23)/6) | O23: =IF(COUNT(H23:M23)=0,"",IF(LEN(IF(COUNT(I23,J23)=2,IF(J23>I23+1,"EBE > VA ",""),"")&IF(COUNT(H23,M23)=2,IF(ABS(M23)>ABS(H23),"RN > CA ",""),"")&IF(COUNT(H23,K23)=2,IF(ABS(K23)>ABS(H23),"RE > CA ",""),""))=0,"OK",IF(COUNT(I23,J23)=2,IF(J23>I23+1,"EBE > VA ",""),"")&IF(COUNT(H23,M23)=2,IF(ABS(M23)>ABS(H23),"RN > CA ",""),"")&IF(COUNT(H23,K23)=2,IF(ABS(K23)>ABS(H23),"RE > CA ",""),""))) | P23: =IF(OR($A23="",H23="",$C23=""),"",IF(COUNTIFS($A$5:$A$639,$A23,$C$5:$C$639,$C23-1,$D$5:$D$639,$D23,H$5:H$639,"<>")=0,"",IF(OR(SUMIFS(H$5:H$639,$A$5:$A$639,$A23,$C$5:$C$639,$C23-1,$D$5:$D$639,$D23)=0,H23*SUMIFS(H$5:H$639,$A$5:$A$639,$A23,$C$5:$C$639,$C23-1,$D$5:$D$639,$D23)<0),"n.s.",ABS(H23)/ABS(SUMIFS(H$5:H$639,$A$5:$A$639,$A23,$C$5:$C$639,$C23-1,$D$5:$D$639,$D23))-1))) | Q23: =IF(OR($A23="",I23="",$C23=""),"",IF(COUNTIFS($A$5:$A$639,$A23,$C$5:$C$639,$C23-1,$D$5:$D$639,$D23,I$5:I$639,"<>")=0,"",IF(OR(SUMIFS(I$5:I$639,$A$5:$A$639,$A23,$C$5:$C$639,$C23-1,$D$5:$D$639,$D23)=0,I23*SUMIFS(I$5:I$639,$A$5:$A$639,$A23,$C$5:$C$639,$C23-1,$D$5:$D$639,$D23)<0),"n.s.",ABS(I23)/ABS(SUMIFS(I$5:I$639,$A$5:$A$639,$A23,$C$5:$C$639,$C23-1,$D$5:$D$639,$D23))-1))) | R23: =IF(OR($A23="",J23="",$C23=""),"",IF(COUNTIFS($A$5:$A$639,$A23,$C$5:$C$639,$C23-1,$D$5:$D$639,$D23,J$5:J$639,"<>")=0,"",IF(OR(SUMIFS(J$5:J$639,$A$5:$A$639,$A23,$C$5:$C$639,$C23-1,$D$5:$D$639,$D23)=0,J23*SUMIFS(J$5:J$639,$A$5:$A$639,$A23,$C$5:$C$639,$C23-1,$D$5:$D$639,$D23)<0),"n.s.",ABS(J23)/ABS(SUMIFS(J$5:J$639,$A$5:$A$639,$A23,$C$5:$C$639,$C23-1,$D$5:$D$639,$D23))-1))) | S23: =IF(OR($A23="",K23="",$C23=""),"",IF(COUNTIFS($A$5:$A$639,$A23,$C$5:$C$639,$C23-1,$D$5:$D$639,$D23,K$5:K$639,"<>")=0,"",IF(OR(SUMIFS(K$5:K$639,$A$5:$A$639,$A23,$C$5:$C$639,$C23-1,$D$5:$D$639,$D23)=0,K23*SUMIFS(K$5:K$639,$A$5:$A$639,$A23,$C$5:$C$639,$C23-1,$D$5:$D$639,$D23)<0),"n.s.",ABS(K23)/ABS(SUMIFS(K$5:K$639,$A$5:$A$639,$A23,$C$5:$C$639,$C23-1,$D$5:$D$639,$D23))-1))) | T23: =IF(OR($A23="",L23="",$C23=""),"",IF(COUNTIFS($A$5:$A$639,$A23,$C$5:$C$639,$C23-1,$D$5:$D$639,$D23,L$5:L$639,"<>")=0,"",IF(OR(SUMIFS(L$5:L$639,$A$5:$A$639,$A23,$C$5:$C$639,$C23-1,$D$5:$D$639,$D23)=0,L23*SUMIFS(L$5:L$639,$A$5:$A$639,$A23,$C$5:$C$639,$C23-1,$D$5:$D$639,$D23)<0),"n.s.",ABS(L23)/ABS(SUMIFS(L$5:L$639,$A$5:$A$639,$A23,$C$5:$C$639,$C23-1,$D$5:$D$639,$D23))-1))) | U23: =IF(OR($A23="",M23="",$C23=""),"",IF(COUNTIFS($A$5:$A$639,$A23,$C$5:$C$639,$C23-1,$D$5:$D$639,$D23,M$5:M$639,"<>")=0,"",IF(OR(SUMIFS(M$5:M$639,$A$5:$A$639,$A23,$C$5:$C$639,$C23-1,$D$5:$D$639,$D23)=0,M23*SUMIFS(M$5:M$639,$A$5:$A$639,$A23,$C$5:$C$639,$C23-1,$D$5:$D$639,$D23)<0),"n.s.",ABS(M23)/ABS(SUMIFS(M$5:M$639,$A$5:$A$639,$A23,$C$5:$C$639,$C23-1,$D$5:$D$639,$D23))-1)))
A24: PALC | B24: =IF(A24="","",IFERROR(VLOOKUP(A24,Titres!$A$2:$B$400,2,FALSE),"Ticker inconnu")) | C24: 2021 | D24: S1 | N24: =IF(A24="","",COUNT(H24:M24)/6) | O24: =IF(COUNT(H24:M24)=0,"",IF(LEN(IF(COUNT(I24,J24)=2,IF(J24>I24+1,"EBE > VA ",""),"")&IF(COUNT(H24,M24)=2,IF(ABS(M24)>ABS(H24),"RN > CA ",""),"")&IF(COUNT(H24,K24)=2,IF(ABS(K24)>ABS(H24),"RE > CA ",""),""))=0,"OK",IF(COUNT(I24,J24)=2,IF(J24>I24+1,"EBE > VA ",""),"")&IF(COUNT(H24,M24)=2,IF(ABS(M24)>ABS(H24),"RN > CA ",""),"")&IF(COUNT(H24,K24)=2,IF(ABS(K24)>ABS(H24),"RE > CA ",""),""))) | P24: =IF(OR($A24="",H24="",$C24=""),"",IF(COUNTIFS($A$5:$A$639,$A24,$C$5:$C$639,$C24-1,$D$5:$D$639,$D24,H$5:H$639,"<>")=0,"",IF(OR(SUMIFS(H$5:H$639,$A$5:$A$639,$A24,$C$5:$C$639,$C24-1,$D$5:$D$639,$D24)=0,H24*SUMIFS(H$5:H$639,$A$5:$A$639,$A24,$C$5:$C$639,$C24-1,$D$5:$D$639,$D24)<0),"n.s.",ABS(H24)/ABS(SUMIFS(H$5:H$639,$A$5:$A$639,$A24,$C$5:$C$639,$C24-1,$D$5:$D$639,$D24))-1))) | Q24: =IF(OR($A24="",I24="",$C24=""),"",IF(COUNTIFS($A$5:$A$639,$A24,$C$5:$C$639,$C24-1,$D$5:$D$639,$D24,I$5:I$639,"<>")=0,"",IF(OR(SUMIFS(I$5:I$639,$A$5:$A$639,$A24,$C$5:$C$639,$C24-1,$D$5:$D$639,$D24)=0,I24*SUMIFS(I$5:I$639,$A$5:$A$639,$A24,$C$5:$C$639,$C24-1,$D$5:$D$639,$D24)<0),"n.s.",ABS(I24)/ABS(SUMIFS(I$5:I$639,$A$5:$A$639,$A24,$C$5:$C$639,$C24-1,$D$5:$D$639,$D24))-1))) | R24: =IF(OR($A24="",J24="",$C24=""),"",IF(COUNTIFS($A$5:$A$639,$A24,$C$5:$C$639,$C24-1,$D$5:$D$639,$D24,J$5:J$639,"<>")=0,"",IF(OR(SUMIFS(J$5:J$639,$A$5:$A$639,$A24,$C$5:$C$639,$C24-1,$D$5:$D$639,$D24)=0,J24*SUMIFS(J$5:J$639,$A$5:$A$639,$A24,$C$5:$C$639,$C24-1,$D$5:$D$639,$D24)<0),"n.s.",ABS(J24)/ABS(SUMIFS(J$5:J$639,$A$5:$A$639,$A24,$C$5:$C$639,$C24-1,$D$5:$D$639,$D24))-1))) | S24: =IF(OR($A24="",K24="",$C24=""),"",IF(COUNTIFS($A$5:$A$639,$A24,$C$5:$C$639,$C24-1,$D$5:$D$639,$D24,K$5:K$639,"<>")=0,"",IF(OR(SUMIFS(K$5:K$639,$A$5:$A$639,$A24,$C$5:$C$639,$C24-1,$D$5:$D$639,$D24)=0,K24*SUMIFS(K$5:K$639,$A$5:$A$639,$A24,$C$5:$C$639,$C24-1,$D$5:$D$639,$D24)<0),"n.s.",ABS(K24)/ABS(SUMIFS(K$5:K$639,$A$5:$A$639,$A24,$C$5:$C$639,$C24-1,$D$5:$D$639,$D24))-1))) | T24: =IF(OR($A24="",L24="",$C24=""),"",IF(COUNTIFS($A$5:$A$639,$A24,$C$5:$C$639,$C24-1,$D$5:$D$639,$D24,L$5:L$639,"<>")=0,"",IF(OR(SUMIFS(L$5:L$639,$A$5:$A$639,$A24,$C$5:$C$639,$C24-1,$D$5:$D$639,$D24)=0,L24*SUMIFS(L$5:L$639,$A$5:$A$639,$A24,$C$5:$C$639,$C24-1,$D$5:$D$639,$D24)<0),"n.s.",ABS(L24)/ABS(SUMIFS(L$5:L$639,$A$5:$A$639,$A24,$C$5:$C$639,$C24-1,$D$5:$D$639,$D24))-1))) | U24: =IF(OR($A24="",M24="",$C24=""),"",IF(COUNTIFS($A$5:$A$639,$A24,$C$5:$C$639,$C24-1,$D$5:$D$639,$D24,M$5:M$639,"<>")=0,"",IF(OR(SUMIFS(M$5:M$639,$A$5:$A$639,$A24,$C$5:$C$639,$C24-1,$D$5:$D$639,$D24)=0,M24*SUMIFS(M$5:M$639,$A$5:$A$639,$A24,$C$5:$C$639,$C24-1,$D$5:$D$639,$D24)<0),"n.s.",ABS(M24)/ABS(SUMIFS(M$5:M$639,$A$5:$A$639,$A24,$C$5:$C$639,$C24-1,$D$5:$D$639,$D24))-1)))
A25: PALC | B25: =IF(A25="","",IFERROR(VLOOKUP(A25,Titres!$A$2:$B$400,2,FALSE),"Ticker inconnu")) | C25: 2021 | D25: T3 | N25: =IF(A25="","",COUNT(H25:M25)/6) | O25: =IF(COUNT(H25:M25)=0,"",IF(LEN(IF(COUNT(I25,J25)=2,IF(J25>I25+1,"EBE > VA ",""),"")&IF(COUNT(H25,M25)=2,IF(ABS(M25)>ABS(H25),"RN > CA ",""),"")&IF(COUNT(H25,K25)=2,IF(ABS(K25)>ABS(H25),"RE > CA ",""),""))=0,"OK",IF(COUNT(I25,J25)=2,IF(J25>I25+1,"EBE > VA ",""),"")&IF(COUNT(H25,M25)=2,IF(ABS(M25)>ABS(H25),"RN > CA ",""),"")&IF(COUNT(H25,K25)=2,IF(ABS(K25)>ABS(H25),"RE > CA ",""),""))) | P25: =IF(OR($A25="",H25="",$C25=""),"",IF(COUNTIFS($A$5:$A$639,$A25,$C$5:$C$639,$C25-1,$D$5:$D$639,$D25,H$5:H$639,"<>")=0,"",IF(OR(SUMIFS(H$5:H$639,$A$5:$A$639,$A25,$C$5:$C$639,$C25-1,$D$5:$D$639,$D25)=0,H25*SUMIFS(H$5:H$639,$A$5:$A$639,$A25,$C$5:$C$639,$C25-1,$D$5:$D$639,$D25)<0),"n.s.",ABS(H25)/ABS(SUMIFS(H$5:H$639,$A$5:$A$639,$A25,$C$5:$C$639,$C25-1,$D$5:$D$639,$D25))-1))) | Q25: =IF(OR($A25="",I25="",$C25=""),"",IF(COUNTIFS($A$5:$A$639,$A25,$C$5:$C$639,$C25-1,$D$5:$D$639,$D25,I$5:I$639,"<>")=0,"",IF(OR(SUMIFS(I$5:I$639,$A$5:$A$639,$A25,$C$5:$C$639,$C25-1,$D$5:$D$639,$D25)=0,I25*SUMIFS(I$5:I$639,$A$5:$A$639,$A25,$C$5:$C$639,$C25-1,$D$5:$D$639,$D25)<0),"n.s.",ABS(I25)/ABS(SUMIFS(I$5:I$639,$A$5:$A$639,$A25,$C$5:$C$639,$C25-1,$D$5:$D$639,$D25))-1))) | R25: =IF(OR($A25="",J25="",$C25=""),"",IF(COUNTIFS($A$5:$A$639,$A25,$C$5:$C$639,$C25-1,$D$5:$D$639,$D25,J$5:J$639,"<>")=0,"",IF(OR(SUMIFS(J$5:J$639,$A$5:$A$639,$A25,$C$5:$C$639,$C25-1,$D$5:$D$639,$D25)=0,J25*SUMIFS(J$5:J$639,$A$5:$A$639,$A25,$C$5:$C$639,$C25-1,$D$5:$D$639,$D25)<0),"n.s.",ABS(J25)/ABS(SUMIFS(J$5:J$639,$A$5:$A$639,$A25,$C$5:$C$639,$C25-1,$D$5:$D$639,$D25))-1))) | S25: =IF(OR($A25="",K25="",$C25=""),"",IF(COUNTIFS($A$5:$A$639,$A25,$C$5:$C$639,$C25-1,$D$5:$D$639,$D25,K$5:K$639,"<>")=0,"",IF(OR(SUMIFS(K$5:K$639,$A$5:$A$639,$A25,$C$5:$C$639,$C25-1,$D$5:$D$639,$D25)=0,K25*SUMIFS(K$5:K$639,$A$5:$A$639,$A25,$C$5:$C$639,$C25-1,$D$5:$D$639,$D25)<0),"n.s.",ABS(K25)/ABS(SUMIFS(K$5:K$639,$A$5:$A$639,$A25,$C$5:$C$639,$C25-1,$D$5:$D$639,$D25))-1))) | T25: =IF(OR($A25="",L25="",$C25=""),"",IF(COUNTIFS($A$5:$A$639,$A25,$C$5:$C$639,$C25-1,$D$5:$D$639,$D25,L$5:L$639,"<>")=0,"",IF(OR(SUMIFS(L$5:L$639,$A$5:$A$639,$A25,$C$5:$C$639,$C25-1,$D$5:$D$639,$D25)=0,L25*SUMIFS(L$5:L$639,$A$5:$A$639,$A25,$C$5:$C$639,$C25-1,$D$5:$D$639,$D25)<0),"n.s.",ABS(L25)/ABS(SUMIFS(L$5:L$639,$A$5:$A$639,$A25,$C$5:$C$639,$C25-1,$D$5:$D$639,$D25))-1))) | U25: =IF(OR($A25="",M25="",$C25=""),"",IF(COUNTIFS($A$5:$A$639,$A25,$C$5:$C$639,$C25-1,$D$5:$D$639,$D25,M$5:M$639,"<>")=0,"",IF(OR(SUMIFS(M$5:M$639,$A$5:$A$639,$A25,$C$5:$C$639,$C25-1,$D$5:$D$639,$D25)=0,M25*SUMIFS(M$5:M$639,$A$5:$A$639,$A25,$C$5:$C$639,$C25-1,$D$5:$D$639,$D25)<0),"n.s.",ABS(M25)/ABS(SUMIFS(M$5:M$639,$A$5:$A$639,$A25,$C$5:$C$639,$C25-1,$D$5:$D$639,$D25))-1)))
A26: PALC | B26: =IF(A26="","",IFERROR(VLOOKUP(A26,Titres!$A$2:$B$400,2,FALSE),"Ticker inconnu")) | C26: 2022 | D26: T1 | N26: =IF(A26="","",COUNT(H26:M26)/6) | O26: =IF(COUNT(H26:M26)=0,"",IF(LEN(IF(COUNT(I26,J26)=2,IF(J26>I26+1,"EBE > VA ",""),"")&IF(COUNT(H26,M26)=2,IF(ABS(M26)>ABS(H26),"RN > CA ",""),"")&IF(COUNT(H26,K26)=2,IF(ABS(K26)>ABS(H26),"RE > CA ",""),""))=0,"OK",IF(COUNT(I26,J26)=2,IF(J26>I26+1,"EBE > VA ",""),"")&IF(COUNT(H26,M26)=2,IF(ABS(M26)>ABS(H26),"RN > CA ",""),"")&IF(COUNT(H26,K26)=2,IF(ABS(K26)>ABS(H26),"RE > CA ",""),""))) | P26: =IF(OR($A26="",H26="",$C26=""),"",IF(COUNTIFS($A$5:$A$639,$A26,$C$5:$C$639,$C26-1,$D$5:$D$639,$D26,H$5:H$639,"<>")=0,"",IF(OR(SUMIFS(H$5:H$639,$A$5:$A$639,$A26,$C$5:$C$639,$C26-1,$D$5:$D$639,$D26)=0,H26*SUMIFS(H$5:H$639,$A$5:$A$639,$A26,$C$5:$C$639,$C26-1,$D$5:$D$639,$D26)<0),"n.s.",ABS(H26)/ABS(SUMIFS(H$5:H$639,$A$5:$A$639,$A26,$C$5:$C$639,$C26-1,$D$5:$D$639,$D26))-1))) | Q26: =IF(OR($A26="",I26="",$C26=""),"",IF(COUNTIFS($A$5:$A$639,$A26,$C$5:$C$639,$C26-1,$D$5:$D$639,$D26,I$5:I$639,"<>")=0,"",IF(OR(SUMIFS(I$5:I$639,$A$5:$A$639,$A26,$C$5:$C$639,$C26-1,$D$5:$D$639,$D26)=0,I26*SUMIFS(I$5:I$639,$A$5:$A$639,$A26,$C$5:$C$639,$C26-1,$D$5:$D$639,$D26)<0),"n.s.",ABS(I26)/ABS(SUMIFS(I$5:I$639,$A$5:$A$639,$A26,$C$5:$C$639,$C26-1,$D$5:$D$639,$D26))-1))) | R26: =IF(OR($A26="",J26="",$C26=""),"",IF(COUNTIFS($A$5:$A$639,$A26,$C$5:$C$639,$C26-1,$D$5:$D$639,$D26,J$5:J$639,"<>")=0,"",IF(OR(SUMIFS(J$5:J$639,$A$5:$A$639,$A26,$C$5:$C$639,$C26-1,$D$5:$D$639,$D26)=0,J26*SUMIFS(J$5:J$639,$A$5:$A$639,$A26,$C$5:$C$639,$C26-1,$D$5:$D$639,$D26)<0),"n.s.",ABS(J26)/ABS(SUMIFS(J$5:J$639,$A$5:$A$639,$A26,$C$5:$C$639,$C26-1,$D$5:$D$639,$D26))-1))) | S26: =IF(OR($A26="",K26="",$C26=""),"",IF(COUNTIFS($A$5:$A$639,$A26,$C$5:$C$639,$C26-1,$D$5:$D$639,$D26,K$5:K$639,"<>")=0,"",IF(OR(SUMIFS(K$5:K$639,$A$5:$A$639,$A26,$C$5:$C$639,$C26-1,$D$5:$D$639,$D26)=0,K26*SUMIFS(K$5:K$639,$A$5:$A$639,$A26,$C$5:$C$639,$C26-1,$D$5:$D$639,$D26)<0),"n.s.",ABS(K26)/ABS(SUMIFS(K$5:K$639,$A$5:$A$639,$A26,$C$5:$C$639,$C26-1,$D$5:$D$639,$D26))-1))) | T26: =IF(OR($A26="",L26="",$C26=""),"",IF(COUNTIFS($A$5:$A$639,$A26,$C$5:$C$639,$C26-1,$D$5:$D$639,$D26,L$5:L$639,"<>")=0,"",IF(OR(SUMIFS(L$5:L$639,$A$5:$A$639,$A26,$C$5:$C$639,$C26-1,$D$5:$D$639,$D26)=0,L26*SUMIFS(L$5:L$639,$A$5:$A$639,$A26,$C$5:$C$639,$C26-1,$D$5:$D$639,$D26)<0),"n.s.",ABS(L26)/ABS(SUMIFS(L$5:L$639,$A$5:$A$639,$A26,$C$5:$C$639,$C26-1,$D$5:$D$639,$D26))-1))) | U26: =IF(OR($A26="",M26="",$C26=""),"",IF(COUNTIFS($A$5:$A$639,$A26,$C$5:$C$639,$C26-1,$D$5:$D$639,$D26,M$5:M$639,"<>")=0,"",IF(OR(SUMIFS(M$5:M$639,$A$5:$A$639,$A26,$C$5:$C$639,$C26-1,$D$5:$D$639,$D26)=0,M26*SUMIFS(M$5:M$639,$A$5:$A$639,$A26,$C$5:$C$639,$C26-1,$D$5:$D$639,$D26)<0),"n.s.",ABS(M26)/ABS(SUMIFS(M$5:M$639,$A$5:$A$639,$A26,$C$5:$C$639,$C26-1,$D$5:$D$639,$D26))-1)))
A27: PALC | B27: =IF(A27="","",IFERROR(VLOOKUP(A27,Titres!$A$2:$B$400,2,FALSE),"Ticker inconnu")) | C27: 2022 | D27: S1 | N27: =IF(A27="","",COUNT(H27:M27)/6) | O27: =IF(COUNT(H27:M27)=0,"",IF(LEN(IF(COUNT(I27,J27)=2,IF(J27>I27+1,"EBE > VA ",""),"")&IF(COUNT(H27,M27)=2,IF(ABS(M27)>ABS(H27),"RN > CA ",""),"")&IF(COUNT(H27,K27)=2,IF(ABS(K27)>ABS(H27),"RE > CA ",""),""))=0,"OK",IF(COUNT(I27,J27)=2,IF(J27>I27+1,"EBE > VA ",""),"")&IF(COUNT(H27,M27)=2,IF(ABS(M27)>ABS(H27),"RN > CA ",""),"")&IF(COUNT(H27,K27)=2,IF(ABS(K27)>ABS(H27),"RE > CA ",""),""))) | P27: =IF(OR($A27="",H27="",$C27=""),"",IF(COUNTIFS($A$5:$A$639,$A27,$C$5:$C$639,$C27-1,$D$5:$D$639,$D27,H$5:H$639,"<>")=0,"",IF(OR(SUMIFS(H$5:H$639,$A$5:$A$639,$A27,$C$5:$C$639,$C27-1,$D$5:$D$639,$D27)=0,H27*SUMIFS(H$5:H$639,$A$5:$A$639,$A27,$C$5:$C$639,$C27-1,$D$5:$D$639,$D27)<0),"n.s.",ABS(H27)/ABS(SUMIFS(H$5:H$639,$A$5:$A$639,$A27,$C$5:$C$639,$C27-1,$D$5:$D$639,$D27))-1))) | Q27: =IF(OR($A27="",I27="",$C27=""),"",IF(COUNTIFS($A$5:$A$639,$A27,$C$5:$C$639,$C27-1,$D$5:$D$639,$D27,I$5:I$639,"<>")=0,"",IF(OR(SUMIFS(I$5:I$639,$A$5:$A$639,$A27,$C$5:$C$639,$C27-1,$D$5:$D$639,$D27)=0,I27*SUMIFS(I$5:I$639,$A$5:$A$639,$A27,$C$5:$C$639,$C27-1,$D$5:$D$639,$D27)<0),"n.s.",ABS(I27)/ABS(SUMIFS(I$5:I$639,$A$5:$A$639,$A27,$C$5:$C$639,$C27-1,$D$5:$D$639,$D27))-1))) | R27: =IF(OR($A27="",J27="",$C27=""),"",IF(COUNTIFS($A$5:$A$639,$A27,$C$5:$C$639,$C27-1,$D$5:$D$639,$D27,J$5:J$639,"<>")=0,"",IF(OR(SUMIFS(J$5:J$639,$A$5:$A$639,$A27,$C$5:$C$639,$C27-1,$D$5:$D$639,$D27)=0,J27*SUMIFS(J$5:J$639,$A$5:$A$639,$A27,$C$5:$C$639,$C27-1,$D$5:$D$639,$D27)<0),"n.s.",ABS(J27)/ABS(SUMIFS(J$5:J$639,$A$5:$A$639,$A27,$C$5:$C$639,$C27-1,$D$5:$D$639,$D27))-1))) | S27: =IF(OR($A27="",K27="",$C27=""),"",IF(COUNTIFS($A$5:$A$639,$A27,$C$5:$C$639,$C27-1,$D$5:$D$639,$D27,K$5:K$639,"<>")=0,"",IF(OR(SUMIFS(K$5:K$639,$A$5:$A$639,$A27,$C$5:$C$639,$C27-1,$D$5:$D$639,$D27)=0,K27*SUMIFS(K$5:K$639,$A$5:$A$639,$A27,$C$5:$C$639,$C27-1,$D$5:$D$639,$D27)<0),"n.s.",ABS(K27)/ABS(SUMIFS(K$5:K$639,$A$5:$A$639,$A27,$C$5:$C$639,$C27-1,$D$5:$D$639,$D27))-1))) | T27: =IF(OR($A27="",L27="",$C27=""),"",IF(COUNTIFS($A$5:$A$639,$A27,$C$5:$C$639,$C27-1,$D$5:$D$639,$D27,L$5:L$639,"<>")=0,"",IF(OR(SUMIFS(L$5:L$639,$A$5:$A$639,$A27,$C$5:$C$639,$C27-1,$D$5:$D$639,$D27)=0,L27*SUMIFS(L$5:L$639,$A$5:$A$639,$A27,$C$5:$C$639,$C27-1,$D$5:$D$639,$D27)<0),"n.s.",ABS(L27)/ABS(SUMIFS(L$5:L$639,$A$5:$A$639,$A27,$C$5:$C$639,$C27-1,$D$5:$D$639,$D27))-1))) | U27: =IF(OR($A27="",M27="",$C27=""),"",IF(COUNTIFS($A$5:$A$639,$A27,$C$5:$C$639,$C27-1,$D$5:$D$639,$D27,M$5:M$639,"<>")=0,"",IF(OR(SUMIFS(M$5:M$639,$A$5:$A$639,$A27,$C$5:$C$639,$C27-1,$D$5:$D$639,$D27)=0,M27*SUMIFS(M$5:M$639,$A$5:$A$639,$A27,$C$5:$C$639,$C27-1,$D$5:$D$639,$D27)<0),"n.s.",ABS(M27)/ABS(SUMIFS(M$5:M$639,$A$5:$A$639,$A27,$C$5:$C$639,$C27-1,$D$5:$D$639,$D27))-1)))
A28: PALC | B28: =IF(A28="","",IFERROR(VLOOKUP(A28,Titres!$A$2:$B$400,2,FALSE),"Ticker inconnu")) | C28: 2022 | D28: T3 | N28: =IF(A28="","",COUNT(H28:M28)/6) | O28: =IF(COUNT(H28:M28)=0,"",IF(LEN(IF(COUNT(I28,J28)=2,IF(J28>I28+1,"EBE > VA ",""),"")&IF(COUNT(H28,M28)=2,IF(ABS(M28)>ABS(H28),"RN > CA ",""),"")&IF(COUNT(H28,K28)=2,IF(ABS(K28)>ABS(H28),"RE > CA ",""),""))=0,"OK",IF(COUNT(I28,J28)=2,IF(J28>I28+1,"EBE > VA ",""),"")&IF(COUNT(H28,M28)=2,IF(ABS(M28)>ABS(H28),"RN > CA ",""),"")&IF(COUNT(H28,K28)=2,IF(ABS(K28)>ABS(H28),"RE > CA ",""),""))) | P28: =IF(OR($A28="",H28="",$C28=""),"",IF(COUNTIFS($A$5:$A$639,$A28,$C$5:$C$639,$C28-1,$D$5:$D$639,$D28,H$5:H$639,"<>")=0,"",IF(OR(SUMIFS(H$5:H$639,$A$5:$A$639,$A28,$C$5:$C$639,$C28-1,$D$5:$D$639,$D28)=0,H28*SUMIFS(H$5:H$639,$A$5:$A$639,$A28,$C$5:$C$639,$C28-1,$D$5:$D$639,$D28)<0),"n.s.",ABS(H28)/ABS(SUMIFS(H$5:H$639,$A$5:$A$639,$A28,$C$5:$C$639,$C28-1,$D$5:$D$639,$D28))-1))) | Q28: =IF(OR($A28="",I28="",$C28=""),"",IF(COUNTIFS($A$5:$A$639,$A28,$C$5:$C$639,$C28-1,$D$5:$D$639,$D28,I$5:I$639,"<>")=0,"",IF(OR(SUMIFS(I$5:I$639,$A$5:$A$639,$A28,$C$5:$C$639,$C28-1,$D$5:$D$639,$D28)=0,I28*SUMIFS(I$5:I$639,$A$5:$A$639,$A28,$C$5:$C$639,$C28-1,$D$5:$D$639,$D28)<0),"n.s.",ABS(I28)/ABS(SUMIFS(I$5:I$639,$A$5:$A$639,$A28,$C$5:$C$639,$C28-1,$D$5:$D$639,$D28))-1))) | R28: =IF(OR($A28="",J28="",$C28=""),"",IF(COUNTIFS($A$5:$A$639,$A28,$C$5:$C$639,$C28-1,$D$5:$D$639,$D28,J$5:J$639,"<>")=0,"",IF(OR(SUMIFS(J$5:J$639,$A$5:$A$639,$A28,$C$5:$C$639,$C28-1,$D$5:$D$639,$D28)=0,J28*SUMIFS(J$5:J$639,$A$5:$A$639,$A28,$C$5:$C$639,$C28-1,$D$5:$D$639,$D28)<0),"n.s.",ABS(J28)/ABS(SUMIFS(J$5:J$639,$A$5:$A$639,$A28,$C$5:$C$639,$C28-1,$D$5:$D$639,$D28))-1))) | S28: =IF(OR($A28="",K28="",$C28=""),"",IF(COUNTIFS($A$5:$A$639,$A28,$C$5:$C$639,$C28-1,$D$5:$D$639,$D28,K$5:K$639,"<>")=0,"",IF(OR(SUMIFS(K$5:K$639,$A$5:$A$639,$A28,$C$5:$C$639,$C28-1,$D$5:$D$639,$D28)=0,K28*SUMIFS(K$5:K$639,$A$5:$A$639,$A28,$C$5:$C$639,$C28-1,$D$5:$D$639,$D28)<0),"n.s.",ABS(K28)/ABS(SUMIFS(K$5:K$639,$A$5:$A$639,$A28,$C$5:$C$639,$C28-1,$D$5:$D$639,$D28))-1))) | T28: =IF(OR($A28="",L28="",$C28=""),"",IF(COUNTIFS($A$5:$A$639,$A28,$C$5:$C$639,$C28-1,$D$5:$D$639,$D28,L$5:L$639,"<>")=0,"",IF(OR(SUMIFS(L$5:L$639,$A$5:$A$639,$A28,$C$5:$C$639,$C28-1,$D$5:$D$639,$D28)=0,L28*SUMIFS(L$5:L$639,$A$5:$A$639,$A28,$C$5:$C$639,$C28-1,$D$5:$D$639,$D28)<0),"n.s.",ABS(L28)/ABS(SUMIFS(L$5:L$639,$A$5:$A$639,$A28,$C$5:$C$639,$C28-1,$D$5:$D$639,$D28))-1))) | U28: =IF(OR($A28="",M28="",$C28=""),"",IF(COUNTIFS($A$5:$A$639,$A28,$C$5:$C$639,$C28-1,$D$5:$D$639,$D28,M$5:M$639,"<>")=0,"",IF(OR(SUMIFS(M$5:M$639,$A$5:$A$639,$A28,$C$5:$C$639,$C28-1,$D$5:$D$639,$D28)=0,M28*SUMIFS(M$5:M$639,$A$5:$A$639,$A28,$C$5:$C$639,$C28-1,$D$5:$D$639,$D28)<0),"n.s.",ABS(M28)/ABS(SUMIFS(M$5:M$639,$A$5:$A$639,$A28,$C$5:$C$639,$C28-1,$D$5:$D$639,$D28))-1)))
A29: PALC | B29: =IF(A29="","",IFERROR(VLOOKUP(A29,Titres!$A$2:$B$400,2,FALSE),"Ticker inconnu")) | C29: 2023 | D29: T1 | N29: =IF(A29="","",COUNT(H29:M29)/6) | O29: =IF(COUNT(H29:M29)=0,"",IF(LEN(IF(COUNT(I29,J29)=2,IF(J29>I29+1,"EBE > VA ",""),"")&IF(COUNT(H29,M29)=2,IF(ABS(M29)>ABS(H29),"RN > CA ",""),"")&IF(COUNT(H29,K29)=2,IF(ABS(K29)>ABS(H29),"RE > CA ",""),""))=0,"OK",IF(COUNT(I29,J29)=2,IF(J29>I29+1,"EBE > VA ",""),"")&IF(COUNT(H29,M29)=2,IF(ABS(M29)>ABS(H29),"RN > CA ",""),"")&IF(COUNT(H29,K29)=2,IF(ABS(K29)>ABS(H29),"RE > CA ",""),""))) | P29: =IF(OR($A29="",H29="",$C29=""),"",IF(COUNTIFS($A$5:$A$639,$A29,$C$5:$C$639,$C29-1,$D$5:$D$639,$D29,H$5:H$639,"<>")=0,"",IF(OR(SUMIFS(H$5:H$639,$A$5:$A$639,$A29,$C$5:$C$639,$C29-1,$D$5:$D$639,$D29)=0,H29*SUMIFS(H$5:H$639,$A$5:$A$639,$A29,$C$5:$C$639,$C29-1,$D$5:$D$639,$D29)<0),"n.s.",ABS(H29)/ABS(SUMIFS(H$5:H$639,$A$5:$A$639,$A29,$C$5:$C$639,$C29-1,$D$5:$D$639,$D29))-1))) | Q29: =IF(OR($A29="",I29="",$C29=""),"",IF(COUNTIFS($A$5:$A$639,$A29,$C$5:$C$639,$C29-1,$D$5:$D$639,$D29,I$5:I$639,"<>")=0,"",IF(OR(SUMIFS(I$5:I$639,$A$5:$A$639,$A29,$C$5:$C$639,$C29-1,$D$5:$D$639,$D29)=0,I29*SUMIFS(I$5:I$639,$A$5:$A$639,$A29,$C$5:$C$639,$C29-1,$D$5:$D$639,$D29)<0),"n.s.",ABS(I29)/ABS(SUMIFS(I$5:I$639,$A$5:$A$639,$A29,$C$5:$C$639,$C29-1,$D$5:$D$639,$D29))-1))) | R29: =IF(OR($A29="",J29="",$C29=""),"",IF(COUNTIFS($A$5:$A$639,$A29,$C$5:$C$639,$C29-1,$D$5:$D$639,$D29,J$5:J$639,"<>")=0,"",IF(OR(SUMIFS(J$5:J$639,$A$5:$A$639,$A29,$C$5:$C$639,$C29-1,$D$5:$D$639,$D29)=0,J29*SUMIFS(J$5:J$639,$A$5:$A$639,$A29,$C$5:$C$639,$C29-1,$D$5:$D$639,$D29)<0),"n.s.",ABS(J29)/ABS(SUMIFS(J$5:J$639,$A$5:$A$639,$A29,$C$5:$C$639,$C29-1,$D$5:$D$639,$D29))-1))) | S29: =IF(OR($A29="",K29="",$C29=""),"",IF(COUNTIFS($A$5:$A$639,$A29,$C$5:$C$639,$C29-1,$D$5:$D$639,$D29,K$5:K$639,"<>")=0,"",IF(OR(SUMIFS(K$5:K$639,$A$5:$A$639,$A29,$C$5:$C$639,$C29-1,$D$5:$D$639,$D29)=0,K29*SUMIFS(K$5:K$639,$A$5:$A$639,$A29,$C$5:$C$639,$C29-1,$D$5:$D$639,$D29)<0),"n.s.",ABS(K29)/ABS(SUMIFS(K$5:K$639,$A$5:$A$639,$A29,$C$5:$C$639,$C29-1,$D$5:$D$639,$D29))-1))) | T29: =IF(OR($A29="",L29="",$C29=""),"",IF(COUNTIFS($A$5:$A$639,$A29,$C$5:$C$639,$C29-1,$D$5:$D$639,$D29,L$5:L$639,"<>")=0,"",IF(OR(SUMIFS(L$5:L$639,$A$5:$A$639,$A29,$C$5:$C$639,$C29-1,$D$5:$D$639,$D29)=0,L29*SUMIFS(L$5:L$639,$A$5:$A$639,$A29,$C$5:$C$639,$C29-1,$D$5:$D$639,$D29)<0),"n.s.",ABS(L29)/ABS(SUMIFS(L$5:L$639,$A$5:$A$639,$A29,$C$5:$C$639,$C29-1,$D$5:$D$639,$D29))-1))) | U29: =IF(OR($A29="",M29="",$C29=""),"",IF(COUNTIFS($A$5:$A$639,$A29,$C$5:$C$639,$C29-1,$D$5:$D$639,$D29,M$5:M$639,"<>")=0,"",IF(OR(SUMIFS(M$5:M$639,$A$5:$A$639,$A29,$C$5:$C$639,$C29-1,$D$5:$D$639,$D29)=0,M29*SUMIFS(M$5:M$639,$A$5:$A$639,$A29,$C$5:$C$639,$C29-1,$D$5:$D$639,$D29)<0),"n.s.",ABS(M29)/ABS(SUMIFS(M$5:M$639,$A$5:$A$639,$A29,$C$5:$C$639,$C29-1,$D$5:$D$639,$D29))-1)))
A30: PALC | B30: =IF(A30="","",IFERROR(VLOOKUP(A30,Titres!$A$2:$B$400,2,FALSE),"Ticker inconnu")) | C30: 2023 | D30: S1 | N30: =IF(A30="","",COUNT(H30:M30)/6) | O30: =IF(COUNT(H30:M30)=0,"",IF(LEN(IF(COUNT(I30,J30)=2,IF(J30>I30+1,"EBE > VA ",""),"")&IF(COUNT(H30,M30)=2,IF(ABS(M30)>ABS(H30),"RN > CA ",""),"")&IF(COUNT(H30,K30)=2,IF(ABS(K30)>ABS(H30),"RE > CA ",""),""))=0,"OK",IF(COUNT(I30,J30)=2,IF(J30>I30+1,"EBE > VA ",""),"")&IF(COUNT(H30,M30)=2,IF(ABS(M30)>ABS(H30),"RN > CA ",""),"")&IF(COUNT(H30,K30)=2,IF(ABS(K30)>ABS(H30),"RE > CA ",""),""))) | P30: =IF(OR($A30="",H30="",$C30=""),"",IF(COUNTIFS($A$5:$A$639,$A30,$C$5:$C$639,$C30-1,$D$5:$D$639,$D30,H$5:H$639,"<>")=0,"",IF(OR(SUMIFS(H$5:H$639,$A$5:$A$639,$A30,$C$5:$C$639,$C30-1,$D$5:$D$639,$D30)=0,H30*SUMIFS(H$5:H$639,$A$5:$A$639,$A30,$C$5:$C$639,$C30-1,$D$5:$D$639,$D30)<0),"n.s.",ABS(H30)/ABS(SUMIFS(H$5:H$639,$A$5:$A$639,$A30,$C$5:$C$639,$C30-1,$D$5:$D$639,$D30))-1))) | Q30: =IF(OR($A30="",I30="",$C30=""),"",IF(COUNTIFS($A$5:$A$639,$A30,$C$5:$C$639,$C30-1,$D$5:$D$639,$D30,I$5:I$639,"<>")=0,"",IF(OR(SUMIFS(I$5:I$639,$A$5:$A$639,$A30,$C$5:$C$639,$C30-1,$D$5:$D$639,$D30)=0,I30*SUMIFS(I$5:I$639,$A$5:$A$639,$A30,$C$5:$C$639,$C30-1,$D$5:$D$639,$D30)<0),"n.s.",ABS(I30)/ABS(SUMIFS(I$5:I$639,$A$5:$A$639,$A30,$C$5:$C$639,$C30-1,$D$5:$D$639,$D30))-1))) | R30: =IF(OR($A30="",J30="",$C30=""),"",IF(COUNTIFS($A$5:$A$639,$A30,$C$5:$C$639,$C30-1,$D$5:$D$639,$D30,J$5:J$639,"<>")=0,"",IF(OR(SUMIFS(J$5:J$639,$A$5:$A$639,$A30,$C$5:$C$639,$C30-1,$D$5:$D$639,$D30)=0,J30*SUMIFS(J$5:J$639,$A$5:$A$639,$A30,$C$5:$C$639,$C30-1,$D$5:$D$639,$D30)<0),"n.s.",ABS(J30)/ABS(SUMIFS(J$5:J$639,$A$5:$A$639,$A30,$C$5:$C$639,$C30-1,$D$5:$D$639,$D30))-1))) | S30: =IF(OR($A30="",K30="",$C30=""),"",IF(COUNTIFS($A$5:$A$639,$A30,$C$5:$C$639,$C30-1,$D$5:$D$639,$D30,K$5:K$639,"<>")=0,"",IF(OR(SUMIFS(K$5:K$639,$A$5:$A$639,$A30,$C$5:$C$639,$C30-1,$D$5:$D$639,$D30)=0,K30*SUMIFS(K$5:K$639,$A$5:$A$639,$A30,$C$5:$C$639,$C30-1,$D$5:$D$639,$D30)<0),"n.s.",ABS(K30)/ABS(SUMIFS(K$5:K$639,$A$5:$A$639,$A30,$C$5:$C$639,$C30-1,$D$5:$D$639,$D30))-1))) | T30: =IF(OR($A30="",L30="",$C30=""),"",IF(COUNTIFS($A$5:$A$639,$A30,$C$5:$C$639,$C30-1,$D$5:$D$639,$D30,L$5:L$639,"<>")=0,"",IF(OR(SUMIFS(L$5:L$639,$A$5:$A$639,$A30,$C$5:$C$639,$C30-1,$D$5:$D$639,$D30)=0,L30*SUMIFS(L$5:L$639,$A$5:$A$639,$A30,$C$5:$C$639,$C30-1,$D$5:$D$639,$D30)<0),"n.s.",ABS(L30)/ABS(SUMIFS(L$5:L$639,$A$5:$A$639,$A30,$C$5:$C$639,$C30-1,$D$5:$D$639,$D30))-1))) | U30: =IF(OR($A30="",M30="",$C30=""),"",IF(COUNTIFS($A$5:$A$639,$A30,$C$5:$C$639,$C30-1,$D$5:$D$639,$D30,M$5:M$639,"<>")=0,"",IF(OR(SUMIFS(M$5:M$639,$A$5:$A$639,$A30,$C$5:$C$639,$C30-1,$D$5:$D$639,$D30)=0,M30*SUMIFS(M$5:M$639,$A$5:$A$639,$A30,$C$5:$C$639,$C30-1,$D$5:$D$639,$D30)<0),"n.s.",ABS(M30)/ABS(SUMIFS(M$5:M$639,$A$5:$A$639,$A30,$C$5:$C$639,$C30-1,$D$5:$D$639,$D30))-1)))
A31: PALC | B31: =IF(A31="","",IFERROR(VLOOKUP(A31,Titres!$A$2:$B$400,2,FALSE),"Ticker inconnu")) | C31: 2023 | D31: T3 | N31: =IF(A31="","",COUNT(H31:M31)/6) | O31: =IF(COUNT(H31:M31)=0,"",IF(LEN(IF(COUNT(I31,J31)=2,IF(J31>I31+1,"EBE > VA ",""),"")&IF(COUNT(H31,M31)=2,IF(ABS(M31)>ABS(H31),"RN > CA ",""),"")&IF(COUNT(H31,K31)=2,IF(ABS(K31)>ABS(H31),"RE > CA ",""),""))=0,"OK",IF(COUNT(I31,J31)=2,IF(J31>I31+1,"EBE > VA ",""),"")&IF(COUNT(H31,M31)=2,IF(ABS(M31)>ABS(H31),"RN > CA ",""),"")&IF(COUNT(H31,K31)=2,IF(ABS(K31)>ABS(H31),"RE > CA ",""),""))) | P31: =IF(OR($A31="",H31="",$C31=""),"",IF(COUNTIFS($A$5:$A$639,$A31,$C$5:$C$639,$C31-1,$D$5:$D$639,$D31,H$5:H$639,"<>")=0,"",IF(OR(SUMIFS(H$5:H$639,$A$5:$A$639,$A31,$C$5:$C$639,$C31-1,$D$5:$D$639,$D31)=0,H31*SUMIFS(H$5:H$639,$A$5:$A$639,$A31,$C$5:$C$639,$C31-1,$D$5:$D$639,$D31)<0),"n.s.",ABS(H31)/ABS(SUMIFS(H$5:H$639,$A$5:$A$639,$A31,$C$5:$C$639,$C31-1,$D$5:$D$639,$D31))-1))) | Q31: =IF(OR($A31="",I31="",$C31=""),"",IF(COUNTIFS($A$5:$A$639,$A31,$C$5:$C$639,$C31-1,$D$5:$D$639,$D31,I$5:I$639,"<>")=0,"",IF(OR(SUMIFS(I$5:I$639,$A$5:$A$639,$A31,$C$5:$C$639,$C31-1,$D$5:$D$639,$D31)=0,I31*SUMIFS(I$5:I$639,$A$5:$A$639,$A31,$C$5:$C$639,$C31-1,$D$5:$D$639,$D31)<0),"n.s.",ABS(I31)/ABS(SUMIFS(I$5:I$639,$A$5:$A$639,$A31,$C$5:$C$639,$C31-1,$D$5:$D$639,$D31))-1))) | R31: =IF(OR($A31="",J31="",$C31=""),"",IF(COUNTIFS($A$5:$A$639,$A31,$C$5:$C$639,$C31-1,$D$5:$D$639,$D31,J$5:J$639,"<>")=0,"",IF(OR(SUMIFS(J$5:J$639,$A$5:$A$639,$A31,$C$5:$C$639,$C31-1,$D$5:$D$639,$D31)=0,J31*SUMIFS(J$5:J$639,$A$5:$A$639,$A31,$C$5:$C$639,$C31-1,$D$5:$D$639,$D31)<0),"n.s.",ABS(J31)/ABS(SUMIFS(J$5:J$639,$A$5:$A$639,$A31,$C$5:$C$639,$C31-1,$D$5:$D$639,$D31))-1))) | S31: =IF(OR($A31="",K31="",$C31=""),"",IF(COUNTIFS($A$5:$A$639,$A31,$C$5:$C$639,$C31-1,$D$5:$D$639,$D31,K$5:K$639,"<>")=0,"",IF(OR(SUMIFS(K$5:K$639,$A$5:$A$639,$A31,$C$5:$C$639,$C31-1,$D$5:$D$639,$D31)=0,K31*SUMIFS(K$5:K$639,$A$5:$A$639,$A31,$C$5:$C$639,$C31-1,$D$5:$D$639,$D31)<0),"n.s.",ABS(K31)/ABS(SUMIFS(K$5:K$639,$A$5:$A$639,$A31,$C$5:$C$639,$C31-1,$D$5:$D$639,$D31))-1))) | T31: =IF(OR($A31="",L31="",$C31=""),"",IF(COUNTIFS($A$5:$A$639,$A31,$C$5:$C$639,$C31-1,$D$5:$D$639,$D31,L$5:L$639,"<>")=0,"",IF(OR(SUMIFS(L$5:L$639,$A$5:$A$639,$A31,$C$5:$C$639,$C31-1,$D$5:$D$639,$D31)=0,L31*SUMIFS(L$5:L$639,$A$5:$A$639,$A31,$C$5:$C$639,$C31-1,$D$5:$D$639,$D31)<0),"n.s.",ABS(L31)/ABS(SUMIFS(L$5:L$639,$A$5:$A$639,$A31,$C$5:$C$639,$C31-1,$D$5:$D$639,$D31))-1))) | U31: =IF(OR($A31="",M31="",$C31=""),"",IF(COUNTIFS($A$5:$A$639,$A31,$C$5:$C$639,$C31-1,$D$5:$D$639,$D31,M$5:M$639,"<>")=0,"",IF(OR(SUMIFS(M$5:M$639,$A$5:$A$639,$A31,$C$5:$C$639,$C31-1,$D$5:$D$639,$D31)=0,M31*SUMIFS(M$5:M$639,$A$5:$A$639,$A31,$C$5:$C$639,$C31-1,$D$5:$D$639,$D31)<0),"n.s.",ABS(M31)/ABS(SUMIFS(M$5:M$639,$A$5:$A$639,$A31,$C$5:$C$639,$C31-1,$D$5:$D$639,$D31))-1)))
A32: PALC | B32: =IF(A32="","",IFERROR(VLOOKUP(A32,Titres!$A$2:$B$400,2,FALSE),"Ticker inconnu")) | C32: 2024 | D32: T1 | N32: =IF(A32="","",COUNT(H32:M32)/6) | O32: =IF(COUNT(H32:M32)=0,"",IF(LEN(IF(COUNT(I32,J32)=2,IF(J32>I32+1,"EBE > VA ",""),"")&IF(COUNT(H32,M32)=2,IF(ABS(M32)>ABS(H32),"RN > CA ",""),"")&IF(COUNT(H32,K32)=2,IF(ABS(K32)>ABS(H32),"RE > CA ",""),""))=0,"OK",IF(COUNT(I32,J32)=2,IF(J32>I32+1,"EBE > VA ",""),"")&IF(COUNT(H32,M32)=2,IF(ABS(M32)>ABS(H32),"RN > CA ",""),"")&IF(COUNT(H32,K32)=2,IF(ABS(K32)>ABS(H32),"RE > CA ",""),""))) | P32: =IF(OR($A32="",H32="",$C32=""),"",IF(COUNTIFS($A$5:$A$639,$A32,$C$5:$C$639,$C32-1,$D$5:$D$639,$D32,H$5:H$639,"<>")=0,"",IF(OR(SUMIFS(H$5:H$639,$A$5:$A$639,$A32,$C$5:$C$639,$C32-1,$D$5:$D$639,$D32)=0,H32*SUMIFS(H$5:H$639,$A$5:$A$639,$A32,$C$5:$C$639,$C32-1,$D$5:$D$639,$D32)<0),"n.s.",ABS(H32)/ABS(SUMIFS(H$5:H$639,$A$5:$A$639,$A32,$C$5:$C$639,$C32-1,$D$5:$D$639,$D32))-1))) | Q32: =IF(OR($A32="",I32="",$C32=""),"",IF(COUNTIFS($A$5:$A$639,$A32,$C$5:$C$639,$C32-1,$D$5:$D$639,$D32,I$5:I$639,"<>")=0,"",IF(OR(SUMIFS(I$5:I$639,$A$5:$A$639,$A32,$C$5:$C$639,$C32-1,$D$5:$D$639,$D32)=0,I32*SUMIFS(I$5:I$639,$A$5:$A$639,$A32,$C$5:$C$639,$C32-1,$D$5:$D$639,$D32)<0),"n.s.",ABS(I32)/ABS(SUMIFS(I$5:I$639,$A$5:$A$639,$A32,$C$5:$C$639,$C32-1,$D$5:$D$639,$D32))-1))) | R32: =IF(OR($A32="",J32="",$C32=""),"",IF(COUNTIFS($A$5:$A$639,$A32,$C$5:$C$639,$C32-1,$D$5:$D$639,$D32,J$5:J$639,"<>")=0,"",IF(OR(SUMIFS(J$5:J$639,$A$5:$A$639,$A32,$C$5:$C$639,$C32-1,$D$5:$D$639,$D32)=0,J32*SUMIFS(J$5:J$639,$A$5:$A$639,$A32,$C$5:$C$639,$C32-1,$D$5:$D$639,$D32)<0),"n.s.",ABS(J32)/ABS(SUMIFS(J$5:J$639,$A$5:$A$639,$A32,$C$5:$C$639,$C32-1,$D$5:$D$639,$D32))-1))) | S32: =IF(OR($A32="",K32="",$C32=""),"",IF(COUNTIFS($A$5:$A$639,$A32,$C$5:$C$639,$C32-1,$D$5:$D$639,$D32,K$5:K$639,"<>")=0,"",IF(OR(SUMIFS(K$5:K$639,$A$5:$A$639,$A32,$C$5:$C$639,$C32-1,$D$5:$D$639,$D32)=0,K32*SUMIFS(K$5:K$639,$A$5:$A$639,$A32,$C$5:$C$639,$C32-1,$D$5:$D$639,$D32)<0),"n.s.",ABS(K32)/ABS(SUMIFS(K$5:K$639,$A$5:$A$639,$A32,$C$5:$C$639,$C32-1,$D$5:$D$639,$D32))-1))) | T32: =IF(OR($A32="",L32="",$C32=""),"",IF(COUNTIFS($A$5:$A$639,$A32,$C$5:$C$639,$C32-1,$D$5:$D$639,$D32,L$5:L$639,"<>")=0,"",IF(OR(SUMIFS(L$5:L$639,$A$5:$A$639,$A32,$C$5:$C$639,$C32-1,$D$5:$D$639,$D32)=0,L32*SUMIFS(L$5:L$639,$A$5:$A$639,$A32,$C$5:$C$639,$C32-1,$D$5:$D$639,$D32)<0),"n.s.",ABS(L32)/ABS(SUMIFS(L$5:L$639,$A$5:$A$639,$A32,$C$5:$C$639,$C32-1,$D$5:$D$639,$D32))-1))) | U32: =IF(OR($A32="",M32="",$C32=""),"",IF(COUNTIFS($A$5:$A$639,$A32,$C$5:$C$639,$C32-1,$D$5:$D$639,$D32,M$5:M$639,"<>")=0,"",IF(OR(SUMIFS(M$5:M$639,$A$5:$A$639,$A32,$C$5:$C$639,$C32-1,$D$5:$D$639,$D32)=0,M32*SUMIFS(M$5:M$639,$A$5:$A$639,$A32,$C$5:$C$639,$C32-1,$D$5:$D$639,$D32)<0),"n.s.",ABS(M32)/ABS(SUMIFS(M$5:M$639,$A$5:$A$639,$A32,$C$5:$C$639,$C32-1,$D$5:$D$639,$D32))-1)))
... A34: PALC | B34: =IF(A34="","",IFERROR(VLOOKUP(A34,Titres!$A$2:$B$400,2,FALSE),"Ticker inconnu")) | C34: 2024 | D34: T3 | N34: =IF(A34="","",COUNT(H34:M34)/6) | O34: =IF(COUNT(H34:M34)=0,"",IF(LEN(IF(COUNT(I34,J34)=2,IF(J34>I34+1,"EBE > VA ",""),"")&IF(COUNT(H34,M34)=2,IF(ABS(M34)>ABS(H34),"RN > CA ",""),"")&IF(COUNT(H34,K34)=2,IF(ABS(K34)>ABS(H34),"RE > CA ",""),""))=0,"OK",IF(COUNT(I34,J34)=2,IF(J34>I34+1,"EBE > VA ",""),"")&IF(COUNT(H34,M34)=2,IF(ABS(M34)>ABS(H34),"RN > CA ",""),"")&IF(COUNT(H34,K34)=2,IF(ABS(K34)>ABS(H34),"RE > CA ",""),""))) | P34: =IF(OR($A34="",H34="",$C34=""),"",IF(COUNTIFS($A$5:$A$639,$A34,$C$5:$C$639,$C34-1,$D$5:$D$639,$D34,H$5:H$639,"<>")=0,"",IF(OR(SUMIFS(H$5:H$639,$A$5:$A$639,$A34,$C$5:$C$639,$C34-1,$D$5:$D$639,$D34)=0,H34*SUMIFS(H$5:H$639,$A$5:$A$639,$A34,$C$5:$C$639,$C34-1,$D$5:$D$639,$D34)<0),"n.s.",ABS(H34)/ABS(SUMIFS(H$5:H$639,$A$5:$A$639,$A34,$C$5:$C$639,$C34-1,$D$5:$D$639,$D34))-1))) | Q34: =IF(OR($A34="",I34="",$C34=""),"",IF(COUNTIFS($A$5:$A$639,$A34,$C$5:$C$639,$C34-1,$D$5:$D$639,$D34,I$5:I$639,"<>")=0,"",IF(OR(SUMIFS(I$5:I$639,$A$5:$A$639,$A34,$C$5:$C$639,$C34-1,$D$5:$D$639,$D34)=0,I34*SUMIFS(I$5:I$639,$A$5:$A$639,$A34,$C$5:$C$639,$C34-1,$D$5:$D$639,$D34)<0),"n.s.",ABS(I34)/ABS(SUMIFS(I$5:I$639,$A$5:$A$639,$A34,$C$5:$C$639,$C34-1,$D$5:$D$639,$D34))-1))) | R34: =IF(OR($A34="",J34="",$C34=""),"",IF(COUNTIFS($A$5:$A$639,$A34,$C$5:$C$639,$C34-1,$D$5:$D$639,$D34,J$5:J$639,"<>")=0,"",IF(OR(SUMIFS(J$5:J$639,$A$5:$A$639,$A34,$C$5:$C$639,$C34-1,$D$5:$D$639,$D34)=0,J34*SUMIFS(J$5:J$639,$A$5:$A$639,$A34,$C$5:$C$639,$C34-1,$D$5:$D$639,$D34)<0),"n.s.",ABS(J34)/ABS(SUMIFS(J$5:J$639,$A$5:$A$639,$A34,$C$5:$C$639,$C34-1,$D$5:$D$639,$D34))-1))) | S34: =IF(OR($A34="",K34="",$C34=""),"",IF(COUNTIFS($A$5:$A$639,$A34,$C$5:$C$639,$C34-1,$D$5:$D$639,$D34,K$5:K$639,"<>")=0,"",IF(OR(SUMIFS(K$5:K$639,$A$5:$A$639,$A34,$C$5:$C$639,$C34-1,$D$5:$D$639,$D34)=0,K34*SUMIFS(K$5:K$639,$A$5:$A$639,$A34,$C$5:$C$639,$C34-1,$D$5:$D$639,$D34)<0),"n.s.",ABS(K34)/ABS(SUMIFS(K$5:K$639,$A$5:$A$639,$A34,$C$5:$C$639,$C34-1,$D$5:$D$639,$D34))-1))) | T34: =IF(OR($A34="",L34="",$C34=""),"",IF(COUNTIFS($A$5:$A$639,$A34,$C$5:$C$639,$C34-1,$D$5:$D$639,$D34,L$5:L$639,"<>")=0,"",IF(OR(SUMIFS(L$5:L$639,$A$5:$A$639,$A34,$C$5:$C$639,$C34-1,$D$5:$D$639,$D34)=0,L34*SUMIFS(L$5:L$639,$A$5:$A$639,$A34,$C$5:$C$639,$C34-1,$D$5:$D$639,$D34)<0),"n.s.",ABS(L34)/ABS(SUMIFS(L$5:L$639,$A$5:$A$639,$A34,$C$5:$C$639,$C34-1,$D$5:$D$639,$D34))-1))) | U34: =IF(OR($A34="",M34="",$C34=""),"",IF(COUNTIFS($A$5:$A$639,$A34,$C$5:$C$639,$C34-1,$D$5:$D$639,$D34,M$5:M$639,"<>")=0,"",IF(OR(SUMIFS(M$5:M$639,$A$5:$A$639,$A34,$C$5:$C$639,$C34-1,$D$5:$D$639,$D34)=0,M34*SUMIFS(M$5:M$639,$A$5:$A$639,$A34,$C$5:$C$639,$C34-1,$D$5:$D$639,$D34)<0),"n.s.",ABS(M34)/ABS(SUMIFS(M$5:M$639,$A$5:$A$639,$A34,$C$5:$C$639,$C34-1,$D$5:$D$639,$D34))-1)))
A35: PALC | B35: =IF(A35="","",IFERROR(VLOOKUP(A35,Titres!$A$2:$B$400,2,FALSE),"Ticker inconnu")) | C35: 2025 | D35: T1 | E35: Publié | F35: 46141 | G35: https://www.richbourse.com/common/actualite/afficher-fichier/29-04-2026-palm-ci-rapport-dactivites-1er-trimestre-2026 (comparatif N-1) | H35: 67519.358 | L35: 15417.398 | M35: 11562.398 | N35: =IF(A35="","",COUNT(H35:M35)/6) | O35: =IF(COUNT(H35:M35)=0,"",IF(LEN(IF(COUNT(I35,J35)=2,IF(J35>I35+1,"EBE > VA ",""),"")&IF(COUNT(H35,M35)=2,IF(ABS(M35)>ABS(H35),"RN > CA ",""),"")&IF(COUNT(H35,K35)=2,IF(ABS(K35)>ABS(H35),"RE > CA ",""),""))=0,"OK",IF(COUNT(I35,J35)=2,IF(J35>I35+1,"EBE > VA ",""),"")&IF(COUNT(H35,M35)=2,IF(ABS(M35)>ABS(H35),"RN > CA ",""),"")&IF(COUNT(H35,K35)=2,IF(ABS(K35)>ABS(H35),"RE > CA ",""),""))) | P35: =IF(OR($A35="",H35="",$C35=""),"",IF(COUNTIFS($A$5:$A$639,$A35,$C$5:$C$639,$C35-1,$D$5:$D$639,$D35,H$5:H$639,"<>")=0,"",IF(OR(SUMIFS(H$5:H$639,$A$5:$A$639,$A35,$C$5:$C$639,$C35-1,$D$5:$D$639,$D35)=0,H35*SUMIFS(H$5:H$639,$A$5:$A$639,$A35,$C$5:$C$639,$C35-1,$D$5:$D$639,$D35)<0),"n.s.",ABS(H35)/ABS(SUMIFS(H$5:H$639,$A$5:$A$639,$A35,$C$5:$C$639,$C35-1,$D$5:$D$639,$D35))-1))) | Q35: =IF(OR($A35="",I35="",$C35=""),"",IF(COUNTIFS($A$5:$A$639,$A35,$C$5:$C$639,$C35-1,$D$5:$D$639,$D35,I$5:I$639,"<>")=0,"",IF(OR(SUMIFS(I$5:I$639,$A$5:$A$639,$A35,$C$5:$C$639,$C35-1,$D$5:$D$639,$D35)=0,I35*SUMIFS(I$5:I$639,$A$5:$A$639,$A35,$C$5:$C$639,$C35-1,$D$5:$D$639,$D35)<0),"n.s.",ABS(I35)/ABS(SUMIFS(I$5:I$639,$A$5:$A$639,$A35,$C$5:$C$639,$C35-1,$D$5:$D$639,$D35))-1))) | R35: =IF(OR($A35="",J35="",$C35=""),"",IF(COUNTIFS($A$5:$A$639,$A35,$C$5:$C$639,$C35-1,$D$5:$D$639,$D35,J$5:J$639,"<>")=0,"",IF(OR(SUMIFS(J$5:J$639,$A$5:$A$639,$A35,$C$5:$C$639,$C35-1,$D$5:$D$639,$D35)=0,J35*SUMIFS(J$5:J$639,$A$5:$A$639,$A35,$C$5:$C$639,$C35-1,$D$5:$D$639,$D35)<0),"n.s.",ABS(J35)/ABS(SUMIFS(J$5:J$639,$A$5:$A$639,$A35,$C$5:$C$639,$C35-1,$D$5:$D$639,$D35))-1))) | S35: =IF(OR($A35="",K35="",$C35=""),"",IF(COUNTIFS($A$5:$A$639,$A35,$C$5:$C$639,$C35-1,$D$5:$D$639,$D35,K$5:K$639,"<>")=0,"",IF(OR(SUMIFS(K$5:K$639,$A$5:$A$639,$A35,$C$5:$C$639,$C35-1,$D$5:$D$639,$D35)=0,K35*SUMIFS(K$5:K$639,$A$5:$A$639,$A35,$C$5:$C$639,$C35-1,$D$5:$D$639,$D35)<0),"n.s.",ABS(K35)/ABS(SUMIFS(K$5:K$639,$A$5:$A$639,$A35,$C$5:$C$639,$C35-1,$D$5:$D$639,$D35))-1))) | T35: =IF(OR($A35="",L35="",$C35=""),"",IF(COUNTIFS($A$5:$A$639,$A35,$C$5:$C$639,$C35-1,$D$5:$D$639,$D35,L$5:L$639,"<>")=0,"",IF(OR(SUMIFS(L$5:L$639,$A$5:$A$639,$A35,$C$5:$C$639,$C35-1,$D$5:$D$639,$D35)=0,L35*SUMIFS(L$5:L$639,$A$5:$A$639,$A35,$C$5:$C$639,$C35-1,$D$5:$D$639,$D35)<0),"n.s.",ABS(L35)/ABS(SUMIFS(L$5:L$639,$A$5:$A$639,$A35,$C$5:$C$639,$C35-1,$D$5:$D$639,$D35))-1))) | U35: =IF(OR($A35="",M35="",$C35=""),"",IF(COUNTIFS($A$5:$A$639,$A35,$C$5:$C$639,$C35-1,$D$5:$D$639,$D35,M$5:M$639,"<>")=0,"",IF(OR(SUMIFS(M$5:M$639,$A$5:$A$639,$A35,$C$5:$C$639,$C35-1,$D$5:$D$639,$D35)=0,M35*SUMIFS(M$5:M$639,$A$5:$A$639,$A35,$C$5:$C$639,$C35-1,$D$5:$D$639,$D35)<0),"n.s.",ABS(M35)/ABS(SUMIFS(M$5:M$639,$A$5:$A$639,$A35,$C$5:$C$639,$C35-1,$D$5:$D$639,$D35))-1)))
A36: PALC | B36: =IF(A36="","",IFERROR(VLOOKUP(A36,Titres!$A$2:$B$400,2,FALSE),"Ticker inconnu")) | C36: 2025 | D36: S1 | E36: Publié | F36: 46302 | G36: https://www.richbourse.com/common/actualite/afficher-fichier/07-10-2026-palm-ci-rapport-d-activites-1er-semestre-2026 (comparatif N-1) | H36: 134789.05 | K36: 29803.435 | L36: 31070.451 | M36: 22908.673 | N36: =IF(A36="","",COUNT(H36:M36)/6) | O36: =IF(COUNT(H36:M36)=0,"",IF(LEN(IF(COUNT(I36,J36)=2,IF(J36>I36+1,"EBE > VA ",""),"")&IF(COUNT(H36,M36)=2,IF(ABS(M36)>ABS(H36),"RN > CA ",""),"")&IF(COUNT(H36,K36)=2,IF(ABS(K36)>ABS(H36),"RE > CA ",""),""))=0,"OK",IF(COUNT(I36,J36)=2,IF(J36>I36+1,"EBE > VA ",""),"")&IF(COUNT(H36,M36)=2,IF(ABS(M36)>ABS(H36),"RN > CA ",""),"")&IF(COUNT(H36,K36)=2,IF(ABS(K36)>ABS(H36),"RE > CA ",""),""))) | P36: =IF(OR($A36="",H36="",$C36=""),"",IF(COUNTIFS($A$5:$A$639,$A36,$C$5:$C$639,$C36-1,$D$5:$D$639,$D36,H$5:H$639,"<>")=0,"",IF(OR(SUMIFS(H$5:H$639,$A$5:$A$639,$A36,$C$5:$C$639,$C36-1,$D$5:$D$639,$D36)=0,H36*SUMIFS(H$5:H$639,$A$5:$A$639,$A36,$C$5:$C$639,$C36-1,$D$5:$D$639,$D36)<0),"n.s.",ABS(H36)/ABS(SUMIFS(H$5:H$639,$A$5:$A$639,$A36,$C$5:$C$639,$C36-1,$D$5:$D$639,$D36))-1))) | Q36: =IF(OR($A36="",I36="",$C36=""),"",IF(COUNTIFS($A$5:$A$639,$A36,$C$5:$C$639,$C36-1,$D$5:$D$639,$D36,I$5:I$639,"<>")=0,"",IF(OR(SUMIFS(I$5:I$639,$A$5:$A$639,$A36,$C$5:$C$639,$C36-1,$D$5:$D$639,$D36)=0,I36*SUMIFS(I$5:I$639,$A$5:$A$639,$A36,$C$5:$C$639,$C36-1,$D$5:$D$639,$D36)<0),"n.s.",ABS(I36)/ABS(SUMIFS(I$5:I$639,$A$5:$A$639,$A36,$C$5:$C$639,$C36-1,$D$5:$D$639,$D36))-1))) | R36: =IF(OR($A36="",J36="",$C36=""),"",IF(COUNTIFS($A$5:$A$639,$A36,$C$5:$C$639,$C36-1,$D$5:$D$639,$D36,J$5:J$639,"<>")=0,"",IF(OR(SUMIFS(J$5:J$639,$A$5:$A$639,$A36,$C$5:$C$639,$C36-1,$D$5:$D$639,$D36)=0,J36*SUMIFS(J$5:J$639,$A$5:$A$639,$A36,$C$5:$C$639,$C36-1,$D$5:$D$639,$D36)<0),"n.s.",ABS(J36)/ABS(SUMIFS(J$5:J$639,$A$5:$A$639,$A36,$C$5:$C$639,$C36-1,$D$5:$D$639,$D36))-1))) | S36: =IF(OR($A36="",K36="",$C36=""),"",IF(COUNTIFS($A$5:$A$639,$A36,$C$5:$C$639,$C36-1,$D$5:$D$639,$D36,K$5:K$639,"<>")=0,"",IF(OR(SUMIFS(K$5:K$639,$A$5:$A$639,$A36,$C$5:$C$639,$C36-1,$D$5:$D$639,$D36)=0,K36*SUMIFS(K$5:K$639,$A$5:$A$639,$A36,$C$5:$C$639,$C36-1,$D$5:$D$639,$D36)<0),"n.s.",ABS(K36)/ABS(SUMIFS(K$5:K$639,$A$5:$A$639,$A36,$C$5:$C$639,$C36-1,$D$5:$D$639,$D36))-1))) | T36: =IF(OR($A36="",L36="",$C36=""),"",IF(COUNTIFS($A$5:$A$639,$A36,$C$5:$C$639,$C36-1,$D$5:$D$639,$D36,L$5:L$639,"<>")=0,"",IF(OR(SUMIFS(L$5:L$639,$A$5:$A$639,$A36,$C$5:$C$639,$C36-1,$D$5:$D$639,$D36)=0,L36*SUMIFS(L$5:L$639,$A$5:$A$639,$A36,$C$5:$C$639,$C36-1,$D$5:$D$639,$D36)<0),"n.s.",ABS(L36)/ABS(SUMIFS(L$5:L$639,$A$5:$A$639,$A36,$C$5:$C$639,$C36-1,$D$5:$D$639,$D36))-1))) | U36: =IF(OR($A36="",M36="",$C36=""),"",IF(COUNTIFS($A$5:$A$639,$A36,$C$5:$C$639,$C36-1,$D$5:$D$639,$D36,M$5:M$639,"<>")=0,"",IF(OR(SUMIFS(M$5:M$639,$A$5:$A$639,$A36,$C$5:$C$639,$C36-1,$D$5:$D$639,$D36)=0,M36*SUMIFS(M$5:M$639,$A$5:$A$639,$A36,$C$5:$C$639,$C36-1,$D$5:$D$639,$D36)<0),"n.s.",ABS(M36)/ABS(SUMIFS(M$5:M$639,$A$5:$A$639,$A36,$C$5:$C$639,$C36-1,$D$5:$D$639,$D36))-1)))
A37: PALC | B37: =IF(A37="","",IFERROR(VLOOKUP(A37,Titres!$A$2:$B$400,2,FALSE),"Ticker inconnu")) | C37: 2025 | D37: T3 | N37: =IF(A37="","",COUNT(H37:M37)/6) | O37: =IF(COUNT(H37:M37)=0,"",IF(LEN(IF(COUNT(I37,J37)=2,IF(J37>I37+1,"EBE > VA ",""),"")&IF(COUNT(H37,M37)=2,IF(ABS(M37)>ABS(H37),"RN > CA ",""),"")&IF(COUNT(H37,K37)=2,IF(ABS(K37)>ABS(H37),"RE > CA ",""),""))=0,"OK",IF(COUNT(I37,J37)=2,IF(J37>I37+1,"EBE > VA ",""),"")&IF(COUNT(H37,M37)=2,IF(ABS(M37)>ABS(H37),"RN > CA ",""),"")&IF(COUNT(H37,K37)=2,IF(ABS(K37)>ABS(H37),"RE > CA ",""),""))) | P37: =IF(OR($A37="",H37="",$C37=""),"",IF(COUNTIFS($A$5:$A$639,$A37,$C$5:$C$639,$C37-1,$D$5:$D$639,$D37,H$5:H$639,"<>")=0,"",IF(OR(SUMIFS(H$5:H$639,$A$5:$A$639,$A37,$C$5:$C$639,$C37-1,$D$5:$D$639,$D37)=0,H37*SUMIFS(H$5:H$639,$A$5:$A$639,$A37,$C$5:$C$639,$C37-1,$D$5:$D$639,$D37)<0),"n.s.",ABS(H37)/ABS(SUMIFS(H$5:H$639,$A$5:$A$639,$A37,$C$5:$C$639,$C37-1,$D$5:$D$639,$D37))-1))) | Q37: =IF(OR($A37="",I37="",$C37=""),"",IF(COUNTIFS($A$5:$A$639,$A37,$C$5:$C$639,$C37-1,$D$5:$D$639,$D37,I$5:I$639,"<>")=0,"",IF(OR(SUMIFS(I$5:I$639,$A$5:$A$639,$A37,$C$5:$C$639,$C37-1,$D$5:$D$639,$D37)=0,I37*SUMIFS(I$5:I$639,$A$5:$A$639,$A37,$C$5:$C$639,$C37-1,$D$5:$D$639,$D37)<0),"n.s.",ABS(I37)/ABS(SUMIFS(I$5:I$639,$A$5:$A$639,$A37,$C$5:$C$639,$C37-1,$D$5:$D$639,$D37))-1))) | R37: =IF(OR($A37="",J37="",$C37=""),"",IF(COUNTIFS($A$5:$A$639,$A37,$C$5:$C$639,$C37-1,$D$5:$D$639,$D37,J$5:J$639,"<>")=0,"",IF(OR(SUMIFS(J$5:J$639,$A$5:$A$639,$A37,$C$5:$C$639,$C37-1,$D$5:$D$639,$D37)=0,J37*SUMIFS(J$5:J$639,$A$5:$A$639,$A37,$C$5:$C$639,$C37-1,$D$5:$D$639,$D37)<0),"n.s.",ABS(J37)/ABS(SUMIFS(J$5:J$639,$A$5:$A$639,$A37,$C$5:$C$639,$C37-1,$D$5:$D$639,$D37))-1))) | S37: =IF(OR($A37="",K37="",$C37=""),"",IF(COUNTIFS($A$5:$A$639,$A37,$C$5:$C$639,$C37-1,$D$5:$D$639,$D37,K$5:K$639,"<>")=0,"",IF(OR(SUMIFS(K$5:K$639,$A$5:$A$639,$A37,$C$5:$C$639,$C37-1,$D$5:$D$639,$D37)=0,K37*SUMIFS(K$5:K$639,$A$5:$A$639,$A37,$C$5:$C$639,$C37-1,$D$5:$D$639,$D37)<0),"n.s.",ABS(K37)/ABS(SUMIFS(K$5:K$639,$A$5:$A$639,$A37,$C$5:$C$639,$C37-1,$D$5:$D$639,$D37))-1))) | T37: =IF(OR($A37="",L37="",$C37=""),"",IF(COUNTIFS($A$5:$A$639,$A37,$C$5:$C$639,$C37-1,$D$5:$D$639,$D37,L$5:L$639,"<>")=0,"",IF(OR(SUMIFS(L$5:L$639,$A$5:$A$639,$A37,$C$5:$C$639,$C37-1,$D$5:$D$639,$D37)=0,L37*SUMIFS(L$5:L$639,$A$5:$A$639,$A37,$C$5:$C$639,$C37-1,$D$5:$D$639,$D37)<0),"n.s.",ABS(L37)/ABS(SUMIFS(L$5:L$639,$A$5:$A$639,$A37,$C$5:$C$639,$C37-1,$D$5:$D$639,$D37))-1))) | U37: =IF(OR($A37="",M37="",$C37=""),"",IF(COUNTIFS($A$5:$A$639,$A37,$C$5:$C$639,$C37-1,$D$5:$D$639,$D37,M$5:M$639,"<>")=0,"",IF(OR(SUMIFS(M$5:M$639,$A$5:$A$639,$A37,$C$5:$C$639,$C37-1,$D$5:$D$639,$D37)=0,M37*SUMIFS(M$5:M$639,$A$5:$A$639,$A37,$C$5:$C$639,$C37-1,$D$5:$D$639,$D37)<0),"n.s.",ABS(M37)/ABS(SUMIFS(M$5:M$639,$A$5:$A$639,$A37,$C$5:$C$639,$C37-1,$D$5:$D$639,$D37))-1)))
A38: PALC | B38: =IF(A38="","",IFERROR(VLOOKUP(A38,Titres!$A$2:$B$400,2,FALSE),"Ticker inconnu")) | C38: 2026 | D38: T1 | E38: Publié | F38: 46141 | G38: https://www.richbourse.com/common/actualite/afficher-fichier/29-04-2026-palm-ci-rapport-dactivites-1er-trimestre-2026 | H38: 49384.116 | L38: 2120.132 | M38: 1594.48 | N38: =IF(A38="","",COUNT(H38:M38)/6) | O38: =IF(COUNT(H38:M38)=0,"",IF(LEN(IF(COUNT(I38,J38)=2,IF(J38>I38+1,"EBE > VA ",""),"")&IF(COUNT(H38,M38)=2,IF(ABS(M38)>ABS(H38),"RN > CA ",""),"")&IF(COUNT(H38,K38)=2,IF(ABS(K38)>ABS(H38),"RE > CA ",""),""))=0,"OK",IF(COUNT(I38,J38)=2,IF(J38>I38+1,"EBE > VA ",""),"")&IF(COUNT(H38,M38)=2,IF(ABS(M38)>ABS(H38),"RN > CA ",""),"")&IF(COUNT(H38,K38)=2,IF(ABS(K38)>ABS(H38),"RE > CA ",""),""))) | P38: =IF(OR($A38="",H38="",$C38=""),"",IF(COUNTIFS($A$5:$A$639,$A38,$C$5:$C$639,$C38-1,$D$5:$D$639,$D38,H$5:H$639,"<>")=0,"",IF(OR(SUMIFS(H$5:H$639,$A$5:$A$639,$A38,$C$5:$C$639,$C38-1,$D$5:$D$639,$D38)=0,H38*SUMIFS(H$5:H$639,$A$5:$A$639,$A38,$C$5:$C$639,$C38-1,$D$5:$D$639,$D38)<0),"n.s.",ABS(H38)/ABS(SUMIFS(H$5:H$639,$A$5:$A$639,$A38,$C$5:$C$639,$C38-1,$D$5:$D$639,$D38))-1))) | Q38: =IF(OR($A38="",I38="",$C38=""),"",IF(COUNTIFS($A$5:$A$639,$A38,$C$5:$C$639,$C38-1,$D$5:$D$639,$D38,I$5:I$639,"<>")=0,"",IF(OR(SUMIFS(I$5:I$639,$A$5:$A$639,$A38,$C$5:$C$639,$C38-1,$D$5:$D$639,$D38)=0,I38*SUMIFS(I$5:I$639,$A$5:$A$639,$A38,$C$5:$C$639,$C38-1,$D$5:$D$639,$D38)<0),"n.s.",ABS(I38)/ABS(SUMIFS(I$5:I$639,$A$5:$A$639,$A38,$C$5:$C$639,$C38-1,$D$5:$D$639,$D38))-1))) | R38: =IF(OR($A38="",J38="",$C38=""),"",IF(COUNTIFS($A$5:$A$639,$A38,$C$5:$C$639,$C38-1,$D$5:$D$639,$D38,J$5:J$639,"<>")=0,"",IF(OR(SUMIFS(J$5:J$639,$A$5:$A$639,$A38,$C$5:$C$639,$C38-1,$D$5:$D$639,$D38)=0,J38*SUMIFS(J$5:J$639,$A$5:$A$639,$A38,$C$5:$C$639,$C38-1,$D$5:$D$639,$D38)<0),"n.s.",ABS(J38)/ABS(SUMIFS(J$5:J$639,$A$5:$A$639,$A38,$C$5:$C$639,$C38-1,$D$5:$D$639,$D38))-1))) | S38: =IF(OR($A38="",K38="",$C38=""),"",IF(COUNTIFS($A$5:$A$639,$A38,$C$5:$C$639,$C38-1,$D$5:$D$639,$D38,K$5:K$639,"<>")=0,"",IF(OR(SUMIFS(K$5:K$639,$A$5:$A$639,$A38,$C$5:$C$639,$C38-1,$D$5:$D$639,$D38)=0,K38*SUMIFS(K$5:K$639,$A$5:$A$639,$A38,$C$5:$C$639,$C38-1,$D$5:$D$639,$D38)<0),"n.s.",ABS(K38)/ABS(SUMIFS(K$5:K$639,$A$5:$A$639,$A38,$C$5:$C$639,$C38-1,$D$5:$D$639,$D38))-1))) | T38: =IF(OR($A38="",L38="",$C38=""),"",IF(COUNTIFS($A$5:$A$639,$A38,$C$5:$C$639,$C38-1,$D$5:$D$639,$D38,L$5:L$639,"<>")=0,"",IF(OR(SUMIFS(L$5:L$639,$A$5:$A$639,$A38,$C$5:$C$639,$C38-1,$D$5:$D$639,$D38)=0,L38*SUMIFS(L$5:L$639,$A$5:$A$639,$A38,$C$5:$C$639,$C38-1,$D$5:$D$639,$D38)<0),"n.s.",ABS(L38)/ABS(SUMIFS(L$5:L$639,$A$5:$A$639,$A38,$C$5:$C$639,$C38-1,$D$5:$D$639,$D38))-1))) | U38: =IF(OR($A38="",M38="",$C38=""),"",IF(COUNTIFS($A$5:$A$639,$A38,$C$5:$C$639,$C38-1,$D$5:$D$639,$D38,M$5:M$639,"<>")=0,"",IF(OR(SUMIFS(M$5:M$639,$A$5:$A$639,$A38,$C$5:$C$639,$C38-1,$D$5:$D$639,$D38)=0,M38*SUMIFS(M$5:M$639,$A$5:$A$639,$A38,$C$5:$C$639,$C38-1,$D$5:$D$639,$D38)<0),"n.s.",ABS(M38)/ABS(SUMIFS(M$5:M$639,$A$5:$A$639,$A38,$C$5:$C$639,$C38-1,$D$5:$D$639,$D38))-1)))
A39: PALC | B39: =IF(A39="","",IFERROR(VLOOKUP(A39,Titres!$A$2:$B$400,2,FALSE),"Ticker inconnu")) | C39: 2026 | D39: S1 | E39: Publié | F39: 46302 | G39: https://www.richbourse.com/common/actualite/afficher-fichier/07-10-2026-palm-ci-rapport-d-activites-1er-semestre-2026 | H39: 114725.47 | K39: 17621.502 | L39: 18295.076 | M39: 13526.883 | N39: =IF(A39="","",COUNT(H39:M39)/6) | O39: =IF(COUNT(H39:M39)=0,"",IF(LEN(IF(COUNT(I39,J39)=2,IF(J39>I39+1,"EBE > VA ",""),"")&IF(COUNT(H39,M39)=2,IF(ABS(M39)>ABS(H39),"RN > CA ",""),"")&IF(COUNT(H39,K39)=2,IF(ABS(K39)>ABS(H39),"RE > CA ",""),""))=0,"OK",IF(COUNT(I39,J39)=2,IF(J39>I39+1,"EBE > VA ",""),"")&IF(COUNT(H39,M39)=2,IF(ABS(M39)>ABS(H39),"RN > CA ",""),"")&IF(COUNT(H39,K39)=2,IF(ABS(K39)>ABS(H39),"RE > CA ",""),""))) | P39: =IF(OR($A39="",H39="",$C39=""),"",IF(COUNTIFS($A$5:$A$639,$A39,$C$5:$C$639,$C39-1,$D$5:$D$639,$D39,H$5:H$639,"<>")=0,"",IF(OR(SUMIFS(H$5:H$639,$A$5:$A$639,$A39,$C$5:$C$639,$C39-1,$D$5:$D$639,$D39)=0,H39*SUMIFS(H$5:H$639,$A$5:$A$639,$A39,$C$5:$C$639,$C39-1,$D$5:$D$639,$D39)<0),"n.s.",ABS(H39)/ABS(SUMIFS(H$5:H$639,$A$5:$A$639,$A39,$C$5:$C$639,$C39-1,$D$5:$D$639,$D39))-1))) | Q39: =IF(OR($A39="",I39="",$C39=""),"",IF(COUNTIFS($A$5:$A$639,$A39,$C$5:$C$639,$C39-1,$D$5:$D$639,$D39,I$5:I$639,"<>")=0,"",IF(OR(SUMIFS(I$5:I$639,$A$5:$A$639,$A39,$C$5:$C$639,$C39-1,$D$5:$D$639,$D39)=0,I39*SUMIFS(I$5:I$639,$A$5:$A$639,$A39,$C$5:$C$639,$C39-1,$D$5:$D$639,$D39)<0),"n.s.",ABS(I39)/ABS(SUMIFS(I$5:I$639,$A$5:$A$639,$A39,$C$5:$C$639,$C39-1,$D$5:$D$639,$D39))-1))) | R39: =IF(OR($A39="",J39="",$C39=""),"",IF(COUNTIFS($A$5:$A$639,$A39,$C$5:$C$639,$C39-1,$D$5:$D$639,$D39,J$5:J$639,"<>")=0,"",IF(OR(SUMIFS(J$5:J$639,$A$5:$A$639,$A39,$C$5:$C$639,$C39-1,$D$5:$D$639,$D39)=0,J39*SUMIFS(J$5:J$639,$A$5:$A$639,$A39,$C$5:$C$639,$C39-1,$D$5:$D$639,$D39)<0),"n.s.",ABS(J39)/ABS(SUMIFS(J$5:J$639,$A$5:$A$639,$A39,$C$5:$C$639,$C39-1,$D$5:$D$639,$D39))-1))) | S39: =IF(OR($A39="",K39="",$C39=""),"",IF(COUNTIFS($A$5:$A$639,$A39,$C$5:$C$639,$C39-1,$D$5:$D$639,$D39,K$5:K$639,"<>")=0,"",IF(OR(SUMIFS(K$5:K$639,$A$5:$A$639,$A39,$C$5:$C$639,$C39-1,$D$5:$D$639,$D39)=0,K39*SUMIFS(K$5:K$639,$A$5:$A$639,$A39,$C$5:$C$639,$C39-1,$D$5:$D$639,$D39)<0),"n.s.",ABS(K39)/ABS(SUMIFS(K$5:K$639,$A$5:$A$639,$A39,$C$5:$C$639,$C39-1,$D$5:$D$639,$D39))-1))) | T39: =IF(OR($A39="",L39="",$C39=""),"",IF(COUNTIFS($A$5:$A$639,$A39,$C$5:$C$639,$C39-1,$D$5:$D$639,$D39,L$5:L$639,"<>")=0,"",IF(OR(SUMIFS(L$5:L$639,$A$5:$A$639,$A39,$C$5:$C$639,$C39-1,$D$5:$D$639,$D39)=0,L39*SUMIFS(L$5:L$639,$A$5:$A$639,$A39,$C$5:$C$639,$C39-1,$D$5:$D$639,$D39)<0),"n.s.",ABS(L39)/ABS(SUMIFS(L$5:L$639,$A$5:$A$639,$A39,$C$5:$C$639,$C39-1,$D$5:$D$639,$D39))-1))) | U39: =IF(OR($A39="",M39="",$C39=""),"",IF(COUNTIFS($A$5:$A$639,$A39,$C$5:$C$639,$C39-1,$D$5:$D$639,$D39,M$5:M$639,"<>")=0,"",IF(OR(SUMIFS(M$5:M$639,$A$5:$A$639,$A39,$C$5:$C$639,$C39-1,$D$5:$D$639,$D39)=0,M39*SUMIFS(M$5:M$639,$A$5:$A$639,$A39,$C$5:$C$639,$C39-1,$D$5:$D$639,$D39)<0),"n.s.",ABS(M39)/ABS(SUMIFS(M$5:M$639,$A$5:$A$639,$A39,$C$5:$C$639,$C39-1,$D$5:$D$639,$D39))-1)))
A40: PALC | B40: =IF(A40="","",IFERROR(VLOOKUP(A40,Titres!$A$2:$B$400,2,FALSE),"Ticker inconnu")) | C40: 2026 | D40: T3 | N40: =IF(A40="","",COUNT(H40:M40)/6) | O40: =IF(COUNT(H40:M40)=0,"",IF(LEN(IF(COUNT(I40,J40)=2,IF(J40>I40+1,"EBE > VA ",""),"")&IF(COUNT(H40,M40)=2,IF(ABS(M40)>ABS(H40),"RN > CA ",""),"")&IF(COUNT(H40,K40)=2,IF(ABS(K40)>ABS(H40),"RE > CA ",""),""))=0,"OK",IF(COUNT(I40,J40)=2,IF(J40>I40+1,"EBE > VA ",""),"")&IF(COUNT(H40,M40)=2,IF(ABS(M40)>ABS(H40),"RN > CA ",""),"")&IF(COUNT(H40,K40)=2,IF(ABS(K40)>ABS(H40),"RE > CA ",""),""))) | P40: =IF(OR($A40="",H40="",$C40=""),"",IF(COUNTIFS($A$5:$A$639,$A40,$C$5:$C$639,$C40-1,$D$5:$D$639,$D40,H$5:H$639,"<>")=0,"",IF(OR(SUMIFS(H$5:H$639,$A$5:$A$639,$A40,$C$5:$C$639,$C40-1,$D$5:$D$639,$D40)=0,H40*SUMIFS(H$5:H$639,$A$5:$A$639,$A40,$C$5:$C$639,$C40-1,$D$5:$D$639,$D40)<0),"n.s.",ABS(H40)/ABS(SUMIFS(H$5:H$639,$A$5:$A$639,$A40,$C$5:$C$639,$C40-1,$D$5:$D$639,$D40))-1))) | Q40: =IF(OR($A40="",I40="",$C40=""),"",IF(COUNTIFS($A$5:$A$639,$A40,$C$5:$C$639,$C40-1,$D$5:$D$639,$D40,I$5:I$639,"<>")=0,"",IF(OR(SUMIFS(I$5:I$639,$A$5:$A$639,$A40,$C$5:$C$639,$C40-1,$D$5:$D$639,$D40)=0,I40*SUMIFS(I$5:I$639,$A$5:$A$639,$A40,$C$5:$C$639,$C40-1,$D$5:$D$639,$D40)<0),"n.s.",ABS(I40)/ABS(SUMIFS(I$5:I$639,$A$5:$A$639,$A40,$C$5:$C$639,$C40-1,$D$5:$D$639,$D40))-1))) | R40: =IF(OR($A40="",J40="",$C40=""),"",IF(COUNTIFS($A$5:$A$639,$A40,$C$5:$C$639,$C40-1,$D$5:$D$639,$D40,J$5:J$639,"<>")=0,"",IF(OR(SUMIFS(J$5:J$639,$A$5:$A$639,$A40,$C$5:$C$639,$C40-1,$D$5:$D$639,$D40)=0,J40*SUMIFS(J$5:J$639,$A$5:$A$639,$A40,$C$5:$C$639,$C40-1,$D$5:$D$639,$D40)<0),"n.s.",ABS(J40)/ABS(SUMIFS(J$5:J$639,$A$5:$A$639,$A40,$C$5:$C$639,$C40-1,$D$5:$D$639,$D40))-1))) | S40: =IF(OR($A40="",K40="",$C40=""),"",IF(COUNTIFS($A$5:$A$639,$A40,$C$5:$C$639,$C40-1,$D$5:$D$639,$D40,K$5:K$639,"<>")=0,"",IF(OR(SUMIFS(K$5:K$639,$A$5:$A$639,$A40,$C$5:$C$639,$C40-1,$D$5:$D$639,$D40)=0,K40*SUMIFS(K$5:K$639,$A$5:$A$639,$A40,$C$5:$C$639,$C40-1,$D$5:$D$639,$D40)<0),"n.s.",ABS(K40)/ABS(SUMIFS(K$5:K$639,$A$5:$A$639,$A40,$C$5:$C$639,$C40-1,$D$5:$D$639,$D40))-1))) | T40: =IF(OR($A40="",L40="",$C40=""),"",IF(COUNTIFS($A$5:$A$639,$A40,$C$5:$C$639,$C40-1,$D$5:$D$639,$D40,L$5:L$639,"<>")=0,"",IF(OR(SUMIFS(L$5:L$639,$A$5:$A$639,$A40,$C$5:$C$639,$C40-1,$D$5:$D$639,$D40)=0,L40*SUMIFS(L$5:L$639,$A$5:$A$639,$A40,$C$5:$C$639,$C40-1,$D$5:$D$639,$D40)<0),"n.s.",ABS(L40)/ABS(SUMIFS(L$5:L$639,$A$5:$A$639,$A40,$C$5:$C$639,$C40-1,$D$5:$D$639,$D40))-1))) | U40: =IF(OR($A40="",M40="",$C40=""),"",IF(COUNTIFS($A$5:$A$639,$A40,$C$5:$C$639,$C40-1,$D$5:$D$639,$D40,M$5:M$639,"<>")=0,"",IF(OR(SUMIFS(M$5:M$639,$A$5:$A$639,$A40,$C$5:$C$639,$C40-1,$D$5:$D$639,$D40)=0,M40*SUMIFS(M$5:M$639,$A$5:$A$639,$A40,$C$5:$C$639,$C40-1,$D$5:$D$639,$D40)<0),"n.s.",ABS(M40)/ABS(SUMIFS(M$5:M$639,$A$5:$A$639,$A40,$C$5:$C$639,$C40-1,$D$5:$D$639,$D40))-1)))
A41: SCRC | B41: =IF(A41="","",IFERROR(VLOOKUP(A41,Titres!$A$2:$B$400,2,FALSE),"Ticker inconnu")) | C41: 2021 | D41: T1 | N41: =IF(A41="","",COUNT(H41:M41)/6) | O41: =IF(COUNT(H41:M41)=0,"",IF(LEN(IF(COUNT(I41,J41)=2,IF(J41>I41+1,"EBE > VA ",""),"")&IF(COUNT(H41,M41)=2,IF(ABS(M41)>ABS(H41),"RN > CA ",""),"")&IF(COUNT(H41,K41)=2,IF(ABS(K41)>ABS(H41),"RE > CA ",""),""))=0,"OK",IF(COUNT(I41,J41)=2,IF(J41>I41+1,"EBE > VA ",""),"")&IF(COUNT(H41,M41)=2,IF(ABS(M41)>ABS(H41),"RN > CA ",""),"")&IF(COUNT(H41,K41)=2,IF(ABS(K41)>ABS(H41),"RE > CA ",""),""))) | P41: =IF(OR($A41="",H41="",$C41=""),"",IF(COUNTIFS($A$5:$A$639,$A41,$C$5:$C$639,$C41-1,$D$5:$D$639,$D41,H$5:H$639,"<>")=0,"",IF(OR(SUMIFS(H$5:H$639,$A$5:$A$639,$A41,$C$5:$C$639,$C41-1,$D$5:$D$639,$D41)=0,H41*SUMIFS(H$5:H$639,$A$5:$A$639,$A41,$C$5:$C$639,$C41-1,$D$5:$D$639,$D41)<0),"n.s.",ABS(H41)/ABS(SUMIFS(H$5:H$639,$A$5:$A$639,$A41,$C$5:$C$639,$C41-1,$D$5:$D$639,$D41))-1))) | Q41: =IF(OR($A41="",I41="",$C41=""),"",IF(COUNTIFS($A$5:$A$639,$A41,$C$5:$C$639,$C41-1,$D$5:$D$639,$D41,I$5:I$639,"<>")=0,"",IF(OR(SUMIFS(I$5:I$639,$A$5:$A$639,$A41,$C$5:$C$639,$C41-1,$D$5:$D$639,$D41)=0,I41*SUMIFS(I$5:I$639,$A$5:$A$639,$A41,$C$5:$C$639,$C41-1,$D$5:$D$639,$D41)<0),"n.s.",ABS(I41)/ABS(SUMIFS(I$5:I$639,$A$5:$A$639,$A41,$C$5:$C$639,$C41-1,$D$5:$D$639,$D41))-1))) | R41: =IF(OR($A41="",J41="",$C41=""),"",IF(COUNTIFS($A$5:$A$639,$A41,$C$5:$C$639,$C41-1,$D$5:$D$639,$D41,J$5:J$639,"<>")=0,"",IF(OR(SUMIFS(J$5:J$639,$A$5:$A$639,$A41,$C$5:$C$639,$C41-1,$D$5:$D$639,$D41)=0,J41*SUMIFS(J$5:J$639,$A$5:$A$639,$A41,$C$5:$C$639,$C41-1,$D$5:$D$639,$D41)<0),"n.s.",ABS(J41)/ABS(SUMIFS(J$5:J$639,$A$5:$A$639,$A41,$C$5:$C$639,$C41-1,$D$5:$D$639,$D41))-1))) | S41: =IF(OR($A41="",K41="",$C41=""),"",IF(COUNTIFS($A$5:$A$639,$A41,$C$5:$C$639,$C41-1,$D$5:$D$639,$D41,K$5:K$639,"<>")=0,"",IF(OR(SUMIFS(K$5:K$639,$A$5:$A$639,$A41,$C$5:$C$639,$C41-1,$D$5:$D$639,$D41)=0,K41*SUMIFS(K$5:K$639,$A$5:$A$639,$A41,$C$5:$C$639,$C41-1,$D$5:$D$639,$D41)<0),"n.s.",ABS(K41)/ABS(SUMIFS(K$5:K$639,$A$5:$A$639,$A41,$C$5:$C$639,$C41-1,$D$5:$D$639,$D41))-1))) | T41: =IF(OR($A41="",L41="",$C41=""),"",IF(COUNTIFS($A$5:$A$639,$A41,$C$5:$C$639,$C41-1,$D$5:$D$639,$D41,L$5:L$639,"<>")=0,"",IF(OR(SUMIFS(L$5:L$639,$A$5:$A$639,$A41,$C$5:$C$639,$C41-1,$D$5:$D$639,$D41)=0,L41*SUMIFS(L$5:L$639,$A$5:$A$639,$A41,$C$5:$C$639,$C41-1,$D$5:$D$639,$D41)<0),"n.s.",ABS(L41)/ABS(SUMIFS(L$5:L$639,$A$5:$A$639,$A41,$C$5:$C$639,$C41-1,$D$5:$D$639,$D41))-1))) | U41: =IF(OR($A41="",M41="",$C41=""),"",IF(COUNTIFS($A$5:$A$639,$A41,$C$5:$C$639,$C41-1,$D$5:$D$639,$D41,M$5:M$639,"<>")=0,"",IF(OR(SUMIFS(M$5:M$639,$A$5:$A$639,$A41,$C$5:$C$639,$C41-1,$D$5:$D$639,$D41)=0,M41*SUMIFS(M$5:M$639,$A$5:$A$639,$A41,$C$5:$C$639,$C41-1,$D$5:$D$639,$D41)<0),"n.s.",ABS(M41)/ABS(SUMIFS(M$5:M$639,$A$5:$A$639,$A41,$C$5:$C$639,$C41-1,$D$5:$D$639,$D41))-1)))
A42: SCRC | B42: =IF(A42="","",IFERROR(VLOOKUP(A42,Titres!$A$2:$B$400,2,FALSE),"Ticker inconnu")) | C42: 2021 | D42: S1 | N42: =IF(A42="","",COUNT(H42:M42)/6) | O42: =IF(COUNT(H42:M42)=0,"",IF(LEN(IF(COUNT(I42,J42)=2,IF(J42>I42+1,"EBE > VA ",""),"")&IF(COUNT(H42,M42)=2,IF(ABS(M42)>ABS(H42),"RN > CA ",""),"")&IF(COUNT(H42,K42)=2,IF(ABS(K42)>ABS(H42),"RE > CA ",""),""))=0,"OK",IF(COUNT(I42,J42)=2,IF(J42>I42+1,"EBE > VA ",""),"")&IF(COUNT(H42,M42)=2,IF(ABS(M42)>ABS(H42),"RN > CA ",""),"")&IF(COUNT(H42,K42)=2,IF(ABS(K42)>ABS(H42),"RE > CA ",""),""))) | P42: =IF(OR($A42="",H42="",$C42=""),"",IF(COUNTIFS($A$5:$A$639,$A42,$C$5:$C$639,$C42-1,$D$5:$D$639,$D42,H$5:H$639,"<>")=0,"",IF(OR(SUMIFS(H$5:H$639,$A$5:$A$639,$A42,$C$5:$C$639,$C42-1,$D$5:$D$639,$D42)=0,H42*SUMIFS(H$5:H$639,$A$5:$A$639,$A42,$C$5:$C$639,$C42-1,$D$5:$D$639,$D42)<0),"n.s.",ABS(H42)/ABS(SUMIFS(H$5:H$639,$A$5:$A$639,$A42,$C$5:$C$639,$C42-1,$D$5:$D$639,$D42))-1))) | Q42: =IF(OR($A42="",I42="",$C42=""),"",IF(COUNTIFS($A$5:$A$639,$A42,$C$5:$C$639,$C42-1,$D$5:$D$639,$D42,I$5:I$639,"<>")=0,"",IF(OR(SUMIFS(I$5:I$639,$A$5:$A$639,$A42,$C$5:$C$639,$C42-1,$D$5:$D$639,$D42)=0,I42*SUMIFS(I$5:I$639,$A$5:$A$639,$A42,$C$5:$C$639,$C42-1,$D$5:$D$639,$D42)<0),"n.s.",ABS(I42)/ABS(SUMIFS(I$5:I$639,$A$5:$A$639,$A42,$C$5:$C$639,$C42-1,$D$5:$D$639,$D42))-1))) | R42: =IF(OR($A42="",J42="",$C42=""),"",IF(COUNTIFS($A$5:$A$639,$A42,$C$5:$C$639,$C42-1,$D$5:$D$639,$D42,J$5:J$639,"<>")=0,"",IF(OR(SUMIFS(J$5:J$639,$A$5:$A$639,$A42,$C$5:$C$639,$C42-1,$D$5:$D$639,$D42)=0,J42*SUMIFS(J$5:J$639,$A$5:$A$639,$A42,$C$5:$C$639,$C42-1,$D$5:$D$639,$D42)<0),"n.s.",ABS(J42)/ABS(SUMIFS(J$5:J$639,$A$5:$A$639,$A42,$C$5:$C$639,$C42-1,$D$5:$D$639,$D42))-1))) | S42: =IF(OR($A42="",K42="",$C42=""),"",IF(COUNTIFS($A$5:$A$639,$A42,$C$5:$C$639,$C42-1,$D$5:$D$639,$D42,K$5:K$639,"<>")=0,"",IF(OR(SUMIFS(K$5:K$639,$A$5:$A$639,$A42,$C$5:$C$639,$C42-1,$D$5:$D$639,$D42)=0,K42*SUMIFS(K$5:K$639,$A$5:$A$639,$A42,$C$5:$C$639,$C42-1,$D$5:$D$639,$D42)<0),"n.s.",ABS(K42)/ABS(SUMIFS(K$5:K$639,$A$5:$A$639,$A42,$C$5:$C$639,$C42-1,$D$5:$D$639,$D42))-1))) | T42: =IF(OR($A42="",L42="",$C42=""),"",IF(COUNTIFS($A$5:$A$639,$A42,$C$5:$C$639,$C42-1,$D$5:$D$639,$D42,L$5:L$639,"<>")=0,"",IF(OR(SUMIFS(L$5:L$639,$A$5:$A$639,$A42,$C$5:$C$639,$C42-1,$D$5:$D$639,$D42)=0,L42*SUMIFS(L$5:L$639,$A$5:$A$639,$A42,$C$5:$C$639,$C42-1,$D$5:$D$639,$D42)<0),"n.s.",ABS(L42)/ABS(SUMIFS(L$5:L$639,$A$5:$A$639,$A42,$C$5:$C$639,$C42-1,$D$5:$D$639,$D42))-1))) | U42: =IF(OR($A42="",M42="",$C42=""),"",IF(COUNTIFS($A$5:$A$639,$A42,$C$5:$C$639,$C42-1,$D$5:$D$639,$D42,M$5:M$639,"<>")=0,"",IF(OR(SUMIFS(M$5:M$639,$A$5:$A$639,$A42,$C$5:$C$639,$C42-1,$D$5:$D$639,$D42)=0,M42*SUMIFS(M$5:M$639,$A$5:$A$639,$A42,$C$5:$C$639,$C42-1,$D$5:$D$639,$D42)<0),"n.s.",ABS(M42)/ABS(SUMIFS(M$5:M$639,$A$5:$A$639,$A42,$C$5:$C$639,$C42-1,$D$5:$D$639,$D42))-1)))
A43: SCRC | B43: =IF(A43="","",IFERROR(VLOOKUP(A43,Titres!$A$2:$B$400,2,FALSE),"Ticker inconnu")) | C43: 2021 | D43: T3 | N43: =IF(A43="","",COUNT(H43:M43)/6) | O43: =IF(COUNT(H43:M43)=0,"",IF(LEN(IF(COUNT(I43,J43)=2,IF(J43>I43+1,"EBE > VA ",""),"")&IF(COUNT(H43,M43)=2,IF(ABS(M43)>ABS(H43),"RN > CA ",""),"")&IF(COUNT(H43,K43)=2,IF(ABS(K43)>ABS(H43),"RE > CA ",""),""))=0,"OK",IF(COUNT(I43,J43)=2,IF(J43>I43+1,"EBE > VA ",""),"")&IF(COUNT(H43,M43)=2,IF(ABS(M43)>ABS(H43),"RN > CA ",""),"")&IF(COUNT(H43,K43)=2,IF(ABS(K43)>ABS(H43),"RE > CA ",""),""))) | P43: =IF(OR($A43="",H43="",$C43=""),"",IF(COUNTIFS($A$5:$A$639,$A43,$C$5:$C$639,$C43-1,$D$5:$D$639,$D43,H$5:H$639,"<>")=0,"",IF(OR(SUMIFS(H$5:H$639,$A$5:$A$639,$A43,$C$5:$C$639,$C43-1,$D$5:$D$639,$D43)=0,H43*SUMIFS(H$5:H$639,$A$5:$A$639,$A43,$C$5:$C$639,$C43-1,$D$5:$D$639,$D43)<0),"n.s.",ABS(H43)/ABS(SUMIFS(H$5:H$639,$A$5:$A$639,$A43,$C$5:$C$639,$C43-1,$D$5:$D$639,$D43))-1))) | Q43: =IF(OR($A43="",I43="",$C43=""),"",IF(COUNTIFS($A$5:$A$639,$A43,$C$5:$C$639,$C43-1,$D$5:$D$639,$D43,I$5:I$639,"<>")=0,"",IF(OR(SUMIFS(I$5:I$639,$A$5:$A$639,$A43,$C$5:$C$639,$C43-1,$D$5:$D$639,$D43)=0,I43*SUMIFS(I$5:I$639,$A$5:$A$639,$A43,$C$5:$C$639,$C43-1,$D$5:$D$639,$D43)<0),"n.s.",ABS(I43)/ABS(SUMIFS(I$5:I$639,$A$5:$A$639,$A43,$C$5:$C$639,$C43-1,$D$5:$D$639,$D43))-1))) | R43: =IF(OR($A43="",J43="",$C43=""),"",IF(COUNTIFS($A$5:$A$639,$A43,$C$5:$C$639,$C43-1,$D$5:$D$639,$D43,J$5:J$639,"<>")=0,"",IF(OR(SUMIFS(J$5:J$639,$A$5:$A$639,$A43,$C$5:$C$639,$C43-1,$D$5:$D$639,$D43)=0,J43*SUMIFS(J$5:J$639,$A$5:$A$639,$A43,$C$5:$C$639,$C43-1,$D$5:$D$639,$D43)<0),"n.s.",ABS(J43)/ABS(SUMIFS(J$5:J$639,$A$5:$A$639,$A43,$C$5:$C$639,$C43-1,$D$5:$D$639,$D43))-1))) | S43: =IF(OR($A43="",K43="",$C43=""),"",IF(COUNTIFS($A$5:$A$639,$A43,$C$5:$C$639,$C43-1,$D$5:$D$639,$D43,K$5:K$639,"<>")=0,"",IF(OR(SUMIFS(K$5:K$639,$A$5:$A$639,$A43,$C$5:$C$639,$C43-1,$D$5:$D$639,$D43)=0,K43*SUMIFS(K$5:K$639,$A$5:$A$639,$A43,$C$5:$C$639,$C43-1,$D$5:$D$639,$D43)<0),"n.s.",ABS(K43)/ABS(SUMIFS(K$5:K$639,$A$5:$A$639,$A43,$C$5:$C$639,$C43-1,$D$5:$D$639,$D43))-1))) | T43: =IF(OR($A43="",L43="",$C43=""),"",IF(COUNTIFS($A$5:$A$639,$A43,$C$5:$C$639,$C43-1,$D$5:$D$639,$D43,L$5:L$639,"<>")=0,"",IF(OR(SUMIFS(L$5:L$639,$A$5:$A$639,$A43,$C$5:$C$639,$C43-1,$D$5:$D$639,$D43)=0,L43*SUMIFS(L$5:L$639,$A$5:$A$639,$A43,$C$5:$C$639,$C43-1,$D$5:$D$639,$D43)<0),"n.s.",ABS(L43)/ABS(SUMIFS(L$5:L$639,$A$5:$A$639,$A43,$C$5:$C$639,$C43-1,$D$5:$D$639,$D43))-1))) | U43: =IF(OR($A43="",M43="",$C43=""),"",IF(COUNTIFS($A$5:$A$639,$A43,$C$5:$C$639,$C43-1,$D$5:$D$639,$D43,M$5:M$639,"<>")=0,"",IF(OR(SUMIFS(M$5:M$639,$A$5:$A$639,$A43,$C$5:$C$639,$C43-1,$D$5:$D$639,$D43)=0,M43*SUMIFS(M$5:M$639,$A$5:$A$639,$A43,$C$5:$C$639,$C43-1,$D$5:$D$639,$D43)<0),"n.s.",ABS(M43)/ABS(SUMIFS(M$5:M$639,$A$5:$A$639,$A43,$C$5:$C$639,$C43-1,$D$5:$D$639,$D43))-1)))
A44: SCRC | B44: =IF(A44="","",IFERROR(VLOOKUP(A44,Titres!$A$2:$B$400,2,FALSE),"Ticker inconnu")) | C44: 2022 | D44: T1 | N44: =IF(A44="","",COUNT(H44:M44)/6) | O44: =IF(COUNT(H44:M44)=0,"",IF(LEN(IF(COUNT(I44,J44)=2,IF(J44>I44+1,"EBE > VA ",""),"")&IF(COUNT(H44,M44)=2,IF(ABS(M44)>ABS(H44),"RN > CA ",""),"")&IF(COUNT(H44,K44)=2,IF(ABS(K44)>ABS(H44),"RE > CA ",""),""))=0,"OK",IF(COUNT(I44,J44)=2,IF(J44>I44+1,"EBE > VA ",""),"")&IF(COUNT(H44,M44)=2,IF(ABS(M44)>ABS(H44),"RN > CA ",""),"")&IF(COUNT(H44,K44)=2,IF(ABS(K44)>ABS(H44),"RE > CA ",""),""))) | P44: =IF(OR($A44="",H44="",$C44=""),"",IF(COUNTIFS($A$5:$A$639,$A44,$C$5:$C$639,$C44-1,$D$5:$D$639,$D44,H$5:H$639,"<>")=0,"",IF(OR(SUMIFS(H$5:H$639,$A$5:$A$639,$A44,$C$5:$C$639,$C44-1,$D$5:$D$639,$D44)=0,H44*SUMIFS(H$5:H$639,$A$5:$A$639,$A44,$C$5:$C$639,$C44-1,$D$5:$D$639,$D44)<0),"n.s.",ABS(H44)/ABS(SUMIFS(H$5:H$639,$A$5:$A$639,$A44,$C$5:$C$639,$C44-1,$D$5:$D$639,$D44))-1))) | Q44: =IF(OR($A44="",I44="",$C44=""),"",IF(COUNTIFS($A$5:$A$639,$A44,$C$5:$C$639,$C44-1,$D$5:$D$639,$D44,I$5:I$639,"<>")=0,"",IF(OR(SUMIFS(I$5:I$639,$A$5:$A$639,$A44,$C$5:$C$639,$C44-1,$D$5:$D$639,$D44)=0,I44*SUMIFS(I$5:I$639,$A$5:$A$639,$A44,$C$5:$C$639,$C44-1,$D$5:$D$639,$D44)<0),"n.s.",ABS(I44)/ABS(SUMIFS(I$5:I$639,$A$5:$A$639,$A44,$C$5:$C$639,$C44-1,$D$5:$D$639,$D44))-1))) | R44: =IF(OR($A44="",J44="",$C44=""),"",IF(COUNTIFS($A$5:$A$639,$A44,$C$5:$C$639,$C44-1,$D$5:$D$639,$D44,J$5:J$639,"<>")=0,"",IF(OR(SUMIFS(J$5:J$639,$A$5:$A$639,$A44,$C$5:$C$639,$C44-1,$D$5:$D$639,$D44)=0,J44*SUMIFS(J$5:J$639,$A$5:$A$639,$A44,$C$5:$C$639,$C44-1,$D$5:$D$639,$D44)<0),"n.s.",ABS(J44)/ABS(SUMIFS(J$5:J$639,$A$5:$A$639,$A44,$C$5:$C$639,$C44-1,$D$5:$D$639,$D44))-1))) | S44: =IF(OR($A44="",K44="",$C44=""),"",IF(COUNTIFS($A$5:$A$639,$A44,$C$5:$C$639,$C44-1,$D$5:$D$639,$D44,K$5:K$639,"<>")=0,"",IF(OR(SUMIFS(K$5:K$639,$A$5:$A$639,$A44,$C$5:$C$639,$C44-1,$D$5:$D$639,$D44)=0,K44*SUMIFS(K$5:K$639,$A$5:$A$639,$A44,$C$5:$C$639,$C44-1,$D$5:$D$639,$D44)<0),"n.s.",ABS(K44)/ABS(SUMIFS(K$5:K$639,$A$5:$A$639,$A44,$C$5:$C$639,$C44-1,$D$5:$D$639,$D44))-1))) | T44: =IF(OR($A44="",L44="",$C44=""),"",IF(COUNTIFS($A$5:$A$639,$A44,$C$5:$C$639,$C44-1,$D$5:$D$639,$D44,L$5:L$639,"<>")=0,"",IF(OR(SUMIFS(L$5:L$639,$A$5:$A$639,$A44,$C$5:$C$639,$C44-1,$D$5:$D$639,$D44)=0,L44*SUMIFS(L$5:L$639,$A$5:$A$639,$A44,$C$5:$C$639,$C44-1,$D$5:$D$639,$D44)<0),"n.s.",ABS(L44)/ABS(SUMIFS(L$5:L$639,$A$5:$A$639,$A44,$C$5:$C$639,$C44-1,$D$5:$D$639,$D44))-1))) | U44: =IF(OR($A44="",M44="",$C44=""),"",IF(COUNTIFS($A$5:$A$639,$A44,$C$5:$C$639,$C44-1,$D$5:$D$639,$D44,M$5:M$639,"<>")=0,"",IF(OR(SUMIFS(M$5:M$639,$A$5:$A$639,$A44,$C$5:$C$639,$C44-1,$D$5:$D$639,$D44)=0,M44*SUMIFS(M$5:M$639,$A$5:$A$639,$A44,$C$5:$C$639,$C44-1,$D$5:$D$639,$D44)<0),"n.s.",ABS(M44)/ABS(SUMIFS(M$5:M$639,$A$5:$A$639,$A44,$C$5:$C$639,$C44-1,$D$5:$D$639,$D44))-1)))
A45: SCRC | B45: =IF(A45="","",IFERROR(VLOOKUP(A45,Titres!$A$2:$B$400,2,FALSE),"Ticker inconnu")) | C45: 2022 | D45: S1 | N45: =IF(A45="","",COUNT(H45:M45)/6) | O45: =IF(COUNT(H45:M45)=0,"",IF(LEN(IF(COUNT(I45,J45)=2,IF(J45>I45+1,"EBE > VA ",""),"")&IF(COUNT(H45,M45)=2,IF(ABS(M45)>ABS(H45),"RN > CA ",""),"")&IF(COUNT(H45,K45)=2,IF(ABS(K45)>ABS(H45),"RE > CA ",""),""))=0,"OK",IF(COUNT(I45,J45)=2,IF(J45>I45+1,"EBE > VA ",""),"")&IF(COUNT(H45,M45)=2,IF(ABS(M45)>ABS(H45),"RN > CA ",""),"")&IF(COUNT(H45,K45)=2,IF(ABS(K45)>ABS(H45),"RE > CA ",""),""))) | P45: =IF(OR($A45="",H45="",$C45=""),"",IF(COUNTIFS($A$5:$A$639,$A45,$C$5:$C$639,$C45-1,$D$5:$D$639,$D45,H$5:H$639,"<>")=0,"",IF(OR(SUMIFS(H$5:H$639,$A$5:$A$639,$A45,$C$5:$C$639,$C45-1,$D$5:$D$639,$D45)=0,H45*SUMIFS(H$5:H$639,$A$5:$A$639,$A45,$C$5:$C$639,$C45-1,$D$5:$D$639,$D45)<0),"n.s.",ABS(H45)/ABS(SUMIFS(H$5:H$639,$A$5:$A$639,$A45,$C$5:$C$639,$C45-1,$D$5:$D$639,$D45))-1))) | Q45: =IF(OR($A45="",I45="",$C45=""),"",IF(COUNTIFS($A$5:$A$639,$A45,$C$5:$C$639,$C45-1,$D$5:$D$639,$D45,I$5:I$639,"<>")=0,"",IF(OR(SUMIFS(I$5:I$639,$A$5:$A$639,$A45,$C$5:$C$639,$C45-1,$D$5:$D$639,$D45)=0,I45*SUMIFS(I$5:I$639,$A$5:$A$639,$A45,$C$5:$C$639,$C45-1,$D$5:$D$639,$D45)<0),"n.s.",ABS(I45)/ABS(SUMIFS(I$5:I$639,$A$5:$A$639,$A45,$C$5:$C$639,$C45-1,$D$5:$D$639,$D45))-1))) | R45: =IF(OR($A45="",J45="",$C45=""),"",IF(COUNTIFS($A$5:$A$639,$A45,$C$5:$C$639,$C45-1,$D$5:$D$639,$D45,J$5:J$639,"<>")=0,"",IF(OR(SUMIFS(J$5:J$639,$A$5:$A$639,$A45,$C$5:$C$639,$C45-1,$D$5:$D$639,$D45)=0,J45*SUMIFS(J$5:J$639,$A$5:$A$639,$A45,$C$5:$C$639,$C45-1,$D$5:$D$639,$D45)<0),"n.s.",ABS(J45)/ABS(SUMIFS(J$5:J$639,$A$5:$A$639,$A45,$C$5:$C$639,$C45-1,$D$5:$D$639,$D45))-1))) | S45: =IF(OR($A45="",K45="",$C45=""),"",IF(COUNTIFS($A$5:$A$639,$A45,$C$5:$C$639,$C45-1,$D$5:$D$639,$D45,K$5:K$639,"<>")=0,"",IF(OR(SUMIFS(K$5:K$639,$A$5:$A$639,$A45,$C$5:$C$639,$C45-1,$D$5:$D$639,$D45)=0,K45*SUMIFS(K$5:K$639,$A$5:$A$639,$A45,$C$5:$C$639,$C45-1,$D$5:$D$639,$D45)<0),"n.s.",ABS(K45)/ABS(SUMIFS(K$5:K$639,$A$5:$A$639,$A45,$C$5:$C$639,$C45-1,$D$5:$D$639,$D45))-1))) | T45: =IF(OR($A45="",L45="",$C45=""),"",IF(COUNTIFS($A$5:$A$639,$A45,$C$5:$C$639,$C45-1,$D$5:$D$639,$D45,L$5:L$639,"<>")=0,"",IF(OR(SUMIFS(L$5:L$639,$A$5:$A$639,$A45,$C$5:$C$639,$C45-1,$D$5:$D$639,$D45)=0,L45*SUMIFS(L$5:L$639,$A$5:$A$639,$A45,$C$5:$C$639,$C45-1,$D$5:$D$639,$D45)<0),"n.s.",ABS(L45)/ABS(SUMIFS(L$5:L$639,$A$5:$A$639,$A45,$C$5:$C$639,$C45-1,$D$5:$D$639,$D45))-1))) | U45: =IF(OR($A45="",M45="",$C45=""),"",IF(COUNTIFS($A$5:$A$639,$A45,$C$5:$C$639,$C45-1,$D$5:$D$639,$D45,M$5:M$639,"<>")=0,"",IF(OR(SUMIFS(M$5:M$639,$A$5:$A$639,$A45,$C$5:$C$639,$C45-1,$D$5:$D$639,$D45)=0,M45*SUMIFS(M$5:M$639,$A$5:$A$639,$A45,$C$5:$C$639,$C45-1,$D$5:$D$639,$D45)<0),"n.s.",ABS(M45)/ABS(SUMIFS(M$5:M$639,$A$5:$A$639,$A45,$C$5:$C$639,$C45-1,$D$5:$D$639,$D45))-1)))
A46: SCRC | B46: =IF(A46="","",IFERROR(VLOOKUP(A46,Titres!$A$2:$B$400,2,FALSE),"Ticker inconnu")) | C46: 2022 | D46: T3 | N46: =IF(A46="","",COUNT(H46:M46)/6) | O46: =IF(COUNT(H46:M46)=0,"",IF(LEN(IF(COUNT(I46,J46)=2,IF(J46>I46+1,"EBE > VA ",""),"")&IF(COUNT(H46,M46)=2,IF(ABS(M46)>ABS(H46),"RN > CA ",""),"")&IF(COUNT(H46,K46)=2,IF(ABS(K46)>ABS(H46),"RE > CA ",""),""))=0,"OK",IF(COUNT(I46,J46)=2,IF(J46>I46+1,"EBE > VA ",""),"")&IF(COUNT(H46,M46)=2,IF(ABS(M46)>ABS(H46),"RN > CA ",""),"")&IF(COUNT(H46,K46)=2,IF(ABS(K46)>ABS(H46),"RE > CA ",""),""))) | P46: =IF(OR($A46="",H46="",$C46=""),"",IF(COUNTIFS($A$5:$A$639,$A46,$C$5:$C$639,$C46-1,$D$5:$D$639,$D46,H$5:H$639,"<>")=0,"",IF(OR(SUMIFS(H$5:H$639,$A$5:$A$639,$A46,$C$5:$C$639,$C46-1,$D$5:$D$639,$D46)=0,H46*SUMIFS(H$5:H$639,$A$5:$A$639,$A46,$C$5:$C$639,$C46-1,$D$5:$D$639,$D46)<0),"n.s.",ABS(H46)/ABS(SUMIFS(H$5:H$639,$A$5:$A$639,$A46,$C$5:$C$639,$C46-1,$D$5:$D$639,$D46))-1))) | Q46: =IF(OR($A46="",I46="",$C46=""),"",IF(COUNTIFS($A$5:$A$639,$A46,$C$5:$C$639,$C46-1,$D$5:$D$639,$D46,I$5:I$639,"<>")=0,"",IF(OR(SUMIFS(I$5:I$639,$A$5:$A$639,$A46,$C$5:$C$639,$C46-1,$D$5:$D$639,$D46)=0,I46*SUMIFS(I$5:I$639,$A$5:$A$639,$A46,$C$5:$C$639,$C46-1,$D$5:$D$639,$D46)<0),"n.s.",ABS(I46)/ABS(SUMIFS(I$5:I$639,$A$5:$A$639,$A46,$C$5:$C$639,$C46-1,$D$5:$D$639,$D46))-1))) | R46: =IF(OR($A46="",J46="",$C46=""),"",IF(COUNTIFS($A$5:$A$639,$A46,$C$5:$C$639,$C46-1,$D$5:$D$639,$D46,J$5:J$639,"<>")=0,"",IF(OR(SUMIFS(J$5:J$639,$A$5:$A$639,$A46,$C$5:$C$639,$C46-1,$D$5:$D$639,$D46)=0,J46*SUMIFS(J$5:J$639,$A$5:$A$639,$A46,$C$5:$C$639,$C46-1,$D$5:$D$639,$D46)<0),"n.s.",ABS(J46)/ABS(SUMIFS(J$5:J$639,$A$5:$A$639,$A46,$C$5:$C$639,$C46-1,$D$5:$D$639,$D46))-1))) | S46: =IF(OR($A46="",K46="",$C46=""),"",IF(COUNTIFS($A$5:$A$639,$A46,$C$5:$C$639,$C46-1,$D$5:$D$639,$D46,K$5:K$639,"<>")=0,"",IF(OR(SUMIFS(K$5:K$639,$A$5:$A$639,$A46,$C$5:$C$639,$C46-1,$D$5:$D$639,$D46)=0,K46*SUMIFS(K$5:K$639,$A$5:$A$639,$A46,$C$5:$C$639,$C46-1,$D$5:$D$639,$D46)<0),"n.s.",ABS(K46)/ABS(SUMIFS(K$5:K$639,$A$5:$A$639,$A46,$C$5:$C$639,$C46-1,$D$5:$D$639,$D46))-1))) | T46: =IF(OR($A46="",L46="",$C46=""),"",IF(COUNTIFS($A$5:$A$639,$A46,$C$5:$C$639,$C46-1,$D$5:$D$639,$D46,L$5:L$639,"<>")=0,"",IF(OR(SUMIFS(L$5:L$639,$A$5:$A$639,$A46,$C$5:$C$639,$C46-1,$D$5:$D$639,$D46)=0,L46*SUMIFS(L$5:L$639,$A$5:$A$639,$A46,$C$5:$C$639,$C46-1,$D$5:$D$639,$D46)<0),"n.s.",ABS(L46)/ABS(SUMIFS(L$5:L$639,$A$5:$A$639,$A46,$C$5:$C$639,$C46-1,$D$5:$D$639,$D46))-1))) | U46: =IF(OR($A46="",M46="",$C46=""),"",IF(COUNTIFS($A$5:$A$639,$A46,$C$5:$C$639,$C46-1,$D$5:$D$639,$D46,M$5:M$639,"<>")=0,"",IF(OR(SUMIFS(M$5:M$639,$A$5:$A$639,$A46,$C$5:$C$639,$C46-1,$D$5:$D$639,$D46)=0,M46*SUMIFS(M$5:M$639,$A$5:$A$639,$A46,$C$5:$C$639,$C46-1,$D$5:$D$639,$D46)<0),"n.s.",ABS(M46)/ABS(SUMIFS(M$5:M$639,$A$5:$A$639,$A46,$C$5:$C$639,$C46-1,$D$5:$D$639,$D46))-1)))
A47: SCRC | B47: =IF(A47="","",IFERROR(VLOOKUP(A47,Titres!$A$2:$B$400,2,FALSE),"Ticker inconnu")) | C47: 2023 | D47: T1 | N47: =IF(A47="","",COUNT(H47:M47)/6) | O47: =IF(COUNT(H47:M47)=0,"",IF(LEN(IF(COUNT(I47,J47)=2,IF(J47>I47+1,"EBE > VA ",""),"")&IF(COUNT(H47,M47)=2,IF(ABS(M47)>ABS(H47),"RN > CA ",""),"")&IF(COUNT(H47,K47)=2,IF(ABS(K47)>ABS(H47),"RE > CA ",""),""))=0,"OK",IF(COUNT(I47,J47)=2,IF(J47>I47+1,"EBE > VA ",""),"")&IF(COUNT(H47,M47)=2,IF(ABS(M47)>ABS(H47),"RN > CA ",""),"")&IF(COUNT(H47,K47)=2,IF(ABS(K47)>ABS(H47),"RE > CA ",""),""))) | P47: =IF(OR($A47="",H47="",$C47=""),"",IF(COUNTIFS($A$5:$A$639,$A47,$C$5:$C$639,$C47-1,$D$5:$D$639,$D47,H$5:H$639,"<>")=0,"",IF(OR(SUMIFS(H$5:H$639,$A$5:$A$639,$A47,$C$5:$C$639,$C47-1,$D$5:$D$639,$D47)=0,H47*SUMIFS(H$5:H$639,$A$5:$A$639,$A47,$C$5:$C$639,$C47-1,$D$5:$D$639,$D47)<0),"n.s.",ABS(H47)/ABS(SUMIFS(H$5:H$639,$A$5:$A$639,$A47,$C$5:$C$639,$C47-1,$D$5:$D$639,$D47))-1))) | Q47: =IF(OR($A47="",I47="",$C47=""),"",IF(COUNTIFS($A$5:$A$639,$A47,$C$5:$C$639,$C47-1,$D$5:$D$639,$D47,I$5:I$639,"<>")=0,"",IF(OR(SUMIFS(I$5:I$639,$A$5:$A$639,$A47,$C$5:$C$639,$C47-1,$D$5:$D$639,$D47)=0,I47*SUMIFS(I$5:I$639,$A$5:$A$639,$A47,$C$5:$C$639,$C47-1,$D$5:$D$639,$D47)<0),"n.s.",ABS(I47)/ABS(SUMIFS(I$5:I$639,$A$5:$A$639,$A47,$C$5:$C$639,$C47-1,$D$5:$D$639,$D47))-1))) | R47: =IF(OR($A47="",J47="",$C47=""),"",IF(COUNTIFS($A$5:$A$639,$A47,$C$5:$C$639,$C47-1,$D$5:$D$639,$D47,J$5:J$639,"<>")=0,"",IF(OR(SUMIFS(J$5:J$639,$A$5:$A$639,$A47,$C$5:$C$639,$C47-1,$D$5:$D$639,$D47)=0,J47*SUMIFS(J$5:J$639,$A$5:$A$639,$A47,$C$5:$C$639,$C47-1,$D$5:$D$639,$D47)<0),"n.s.",ABS(J47)/ABS(SUMIFS(J$5:J$639,$A$5:$A$639,$A47,$C$5:$C$639,$C47-1,$D$5:$D$639,$D47))-1))) | S47: =IF(OR($A47="",K47="",$C47=""),"",IF(COUNTIFS($A$5:$A$639,$A47,$C$5:$C$639,$C47-1,$D$5:$D$639,$D47,K$5:K$639,"<>")=0,"",IF(OR(SUMIFS(K$5:K$639,$A$5:$A$639,$A47,$C$5:$C$639,$C47-1,$D$5:$D$639,$D47)=0,K47*SUMIFS(K$5:K$639,$A$5:$A$639,$A47,$C$5:$C$639,$C47-1,$D$5:$D$639,$D47)<0),"n.s.",ABS(K47)/ABS(SUMIFS(K$5:K$639,$A$5:$A$639,$A47,$C$5:$C$639,$C47-1,$D$5:$D$639,$D47))-1))) | T47: =IF(OR($A47="",L47="",$C47=""),"",IF(COUNTIFS($A$5:$A$639,$A47,$C$5:$C$639,$C47-1,$D$5:$D$639,$D47,L$5:L$639,"<>")=0,"",IF(OR(SUMIFS(L$5:L$639,$A$5:$A$639,$A47,$C$5:$C$639,$C47-1,$D$5:$D$639,$D47)=0,L47*SUMIFS(L$5:L$639,$A$5:$A$639,$A47,$C$5:$C$639,$C47-1,$D$5:$D$639,$D47)<0),"n.s.",ABS(L47)/ABS(SUMIFS(L$5:L$639,$A$5:$A$639,$A47,$C$5:$C$639,$C47-1,$D$5:$D$639,$D47))-1))) | U47: =IF(OR($A47="",M47="",$C47=""),"",IF(COUNTIFS($A$5:$A$639,$A47,$C$5:$C$639,$C47-1,$D$5:$D$639,$D47,M$5:M$639,"<>")=0,"",IF(OR(SUMIFS(M$5:M$639,$A$5:$A$639,$A47,$C$5:$C$639,$C47-1,$D$5:$D$639,$D47)=0,M47*SUMIFS(M$5:M$639,$A$5:$A$639,$A47,$C$5:$C$639,$C47-1,$D$5:$D$639,$D47)<0),"n.s.",ABS(M47)/ABS(SUMIFS(M$5:M$639,$A$5:$A$639,$A47,$C$5:$C$639,$C47-1,$D$5:$D$639,$D47))-1)))
A48: SCRC | B48: =IF(A48="","",IFERROR(VLOOKUP(A48,Titres!$A$2:$B$400,2,FALSE),"Ticker inconnu")) | C48: 2023 | D48: S1 | N48: =IF(A48="","",COUNT(H48:M48)/6) | O48: =IF(COUNT(H48:M48)=0,"",IF(LEN(IF(COUNT(I48,J48)=2,IF(J48>I48+1,"EBE > VA ",""),"")&IF(COUNT(H48,M48)=2,IF(ABS(M48)>ABS(H48),"RN > CA ",""),"")&IF(COUNT(H48,K48)=2,IF(ABS(K48)>ABS(H48),"RE > CA ",""),""))=0,"OK",IF(COUNT(I48,J48)=2,IF(J48>I48+1,"EBE > VA ",""),"")&IF(COUNT(H48,M48)=2,IF(ABS(M48)>ABS(H48),"RN > CA ",""),"")&IF(COUNT(H48,K48)=2,IF(ABS(K48)>ABS(H48),"RE > CA ",""),""))) | P48: =IF(OR($A48="",H48="",$C48=""),"",IF(COUNTIFS($A$5:$A$639,$A48,$C$5:$C$639,$C48-1,$D$5:$D$639,$D48,H$5:H$639,"<>")=0,"",IF(OR(SUMIFS(H$5:H$639,$A$5:$A$639,$A48,$C$5:$C$639,$C48-1,$D$5:$D$639,$D48)=0,H48*SUMIFS(H$5:H$639,$A$5:$A$639,$A48,$C$5:$C$639,$C48-1,$D$5:$D$639,$D48)<0),"n.s.",ABS(H48)/ABS(SUMIFS(H$5:H$639,$A$5:$A$639,$A48,$C$5:$C$639,$C48-1,$D$5:$D$639,$D48))-1))) | Q48: =IF(OR($A48="",I48="",$C48=""),"",IF(COUNTIFS($A$5:$A$639,$A48,$C$5:$C$639,$C48-1,$D$5:$D$639,$D48,I$5:I$639,"<>")=0,"",IF(OR(SUMIFS(I$5:I$639,$A$5:$A$639,$A48,$C$5:$C$639,$C48-1,$D$5:$D$639,$D48)=0,I48*SUMIFS(I$5:I$639,$A$5:$A$639,$A48,$C$5:$C$639,$C48-1,$D$5:$D$639,$D48)<0),"n.s.",ABS(I48)/ABS(SUMIFS(I$5:I$639,$A$5:$A$639,$A48,$C$5:$C$639,$C48-1,$D$5:$D$639,$D48))-1))) | R48: =IF(OR($A48="",J48="",$C48=""),"",IF(COUNTIFS($A$5:$A$639,$A48,$C$5:$C$639,$C48-1,$D$5:$D$639,$D48,J$5:J$639,"<>")=0,"",IF(OR(SUMIFS(J$5:J$639,$A$5:$A$639,$A48,$C$5:$C$639,$C48-1,$D$5:$D$639,$D48)=0,J48*SUMIFS(J$5:J$639,$A$5:$A$639,$A48,$C$5:$C$639,$C48-1,$D$5:$D$639,$D48)<0),"n.s.",ABS(J48)/ABS(SUMIFS(J$5:J$639,$A$5:$A$639,$A48,$C$5:$C$639,$C48-1,$D$5:$D$639,$D48))-1))) | S48: =IF(OR($A48="",K48="",$C48=""),"",IF(COUNTIFS($A$5:$A$639,$A48,$C$5:$C$639,$C48-1,$D$5:$D$639,$D48,K$5:K$639,"<>")=0,"",IF(OR(SUMIFS(K$5:K$639,$A$5:$A$639,$A48,$C$5:$C$639,$C48-1,$D$5:$D$639,$D48)=0,K48*SUMIFS(K$5:K$639,$A$5:$A$639,$A48,$C$5:$C$639,$C48-1,$D$5:$D$639,$D48)<0),"n.s.",ABS(K48)/ABS(SUMIFS(K$5:K$639,$A$5:$A$639,$A48,$C$5:$C$639,$C48-1,$D$5:$D$639,$D48))-1))) | T48: =IF(OR($A48="",L48="",$C48=""),"",IF(COUNTIFS($A$5:$A$639,$A48,$C$5:$C$639,$C48-1,$D$5:$D$639,$D48,L$5:L$639,"<>")=0,"",IF(OR(SUMIFS(L$5:L$639,$A$5:$A$639,$A48,$C$5:$C$639,$C48-1,$D$5:$D$639,$D48)=0,L48*SUMIFS(L$5:L$639,$A$5:$A$639,$A48,$C$5:$C$639,$C48-1,$D$5:$D$639,$D48)<0),"n.s.",ABS(L48)/ABS(SUMIFS(L$5:L$639,$A$5:$A$639,$A48,$C$5:$C$639,$C48-1,$D$5:$D$639,$D48))-1))) | U48: =IF(OR($A48="",M48="",$C48=""),"",IF(COUNTIFS($A$5:$A$639,$A48,$C$5:$C$639,$C48-1,$D$5:$D$639,$D48,M$5:M$639,"<>")=0,"",IF(OR(SUMIFS(M$5:M$639,$A$5:$A$639,$A48,$C$5:$C$639,$C48-1,$D$5:$D$639,$D48)=0,M48*SUMIFS(M$5:M$639,$A$5:$A$639,$A48,$C$5:$C$639,$C48-1,$D$5:$D$639,$D48)<0),"n.s.",ABS(M48)/ABS(SUMIFS(M$5:M$639,$A$5:$A$639,$A48,$C$5:$C$639,$C48-1,$D$5:$D$639,$D48))-1)))
A49: SCRC | B49: =IF(A49="","",IFERROR(VLOOKUP(A49,Titres!$A$2:$B$400,2,FALSE),"Ticker inconnu")) | C49: 2023 | D49: T3 | N49: =IF(A49="","",COUNT(H49:M49)/6) | O49: =IF(COUNT(H49:M49)=0,"",IF(LEN(IF(COUNT(I49,J49)=2,IF(J49>I49+1,"EBE > VA ",""),"")&IF(COUNT(H49,M49)=2,IF(ABS(M49)>ABS(H49),"RN > CA ",""),"")&IF(COUNT(H49,K49)=2,IF(ABS(K49)>ABS(H49),"RE > CA ",""),""))=0,"OK",IF(COUNT(I49,J49)=2,IF(J49>I49+1,"EBE > VA ",""),"")&IF(COUNT(H49,M49)=2,IF(ABS(M49)>ABS(H49),"RN > CA ",""),"")&IF(COUNT(H49,K49)=2,IF(ABS(K49)>ABS(H49),"RE > CA ",""),""))) | P49: =IF(OR($A49="",H49="",$C49=""),"",IF(COUNTIFS($A$5:$A$639,$A49,$C$5:$C$639,$C49-1,$D$5:$D$639,$D49,H$5:H$639,"<>")=0,"",IF(OR(SUMIFS(H$5:H$639,$A$5:$A$639,$A49,$C$5:$C$639,$C49-1,$D$5:$D$639,$D49)=0,H49*SUMIFS(H$5:H$639,$A$5:$A$639,$A49,$C$5:$C$639,$C49-1,$D$5:$D$639,$D49)<0),"n.s.",ABS(H49)/ABS(SUMIFS(H$5:H$639,$A$5:$A$639,$A49,$C$5:$C$639,$C49-1,$D$5:$D$639,$D49))-1))) | Q49: =IF(OR($A49="",I49="",$C49=""),"",IF(COUNTIFS($A$5:$A$639,$A49,$C$5:$C$639,$C49-1,$D$5:$D$639,$D49,I$5:I$639,"<>")=0,"",IF(OR(SUMIFS(I$5:I$639,$A$5:$A$639,$A49,$C$5:$C$639,$C49-1,$D$5:$D$639,$D49)=0,I49*SUMIFS(I$5:I$639,$A$5:$A$639,$A49,$C$5:$C$639,$C49-1,$D$5:$D$639,$D49)<0),"n.s.",ABS(I49)/ABS(SUMIFS(I$5:I$639,$A$5:$A$639,$A49,$C$5:$C$639,$C49-1,$D$5:$D$639,$D49))-1))) | R49: =IF(OR($A49="",J49="",$C49=""),"",IF(COUNTIFS($A$5:$A$639,$A49,$C$5:$C$639,$C49-1,$D$5:$D$639,$D49,J$5:J$639,"<>")=0,"",IF(OR(SUMIFS(J$5:J$639,$A$5:$A$639,$A49,$C$5:$C$639,$C49-1,$D$5:$D$639,$D49)=0,J49*SUMIFS(J$5:J$639,$A$5:$A$639,$A49,$C$5:$C$639,$C49-1,$D$5:$D$639,$D49)<0),"n.s.",ABS(J49)/ABS(SUMIFS(J$5:J$639,$A$5:$A$639,$A49,$C$5:$C$639,$C49-1,$D$5:$D$639,$D49))-1))) | S49: =IF(OR($A49="",K49="",$C49=""),"",IF(COUNTIFS($A$5:$A$639,$A49,$C$5:$C$639,$C49-1,$D$5:$D$639,$D49,K$5:K$639,"<>")=0,"",IF(OR(SUMIFS(K$5:K$639,$A$5:$A$639,$A49,$C$5:$C$639,$C49-1,$D$5:$D$639,$D49)=0,K49*SUMIFS(K$5:K$639,$A$5:$A$639,$A49,$C$5:$C$639,$C49-1,$D$5:$D$639,$D49)<0),"n.s.",ABS(K49)/ABS(SUMIFS(K$5:K$639,$A$5:$A$639,$A49,$C$5:$C$639,$C49-1,$D$5:$D$639,$D49))-1))) | T49: =IF(OR($A49="",L49="",$C49=""),"",IF(COUNTIFS($A$5:$A$639,$A49,$C$5:$C$639,$C49-1,$D$5:$D$639,$D49,L$5:L$639,"<>")=0,"",IF(OR(SUMIFS(L$5:L$639,$A$5:$A$639,$A49,$C$5:$C$639,$C49-1,$D$5:$D$639,$D49)=0,L49*SUMIFS(L$5:L$639,$A$5:$A$639,$A49,$C$5:$C$639,$C49-1,$D$5:$D$639,$D49)<0),"n.s.",ABS(L49)/ABS(SUMIFS(L$5:L$639,$A$5:$A$639,$A49,$C$5:$C$639,$C49-1,$D$5:$D$639,$D49))-1))) | U49: =IF(OR($A49="",M49="",$C49=""),"",IF(COUNTIFS($A$5:$A$639,$A49,$C$5:$C$639,$C49-1,$D$5:$D$639,$D49,M$5:M$639,"<>")=0,"",IF(OR(SUMIFS(M$5:M$639,$A$5:$A$639,$A49,$C$5:$C$639,$C49-1,$D$5:$D$639,$D49)=0,M49*SUMIFS(M$5:M$639,$A$5:$A$639,$A49,$C$5:$C$639,$C49-1,$D$5:$D$639,$D49)<0),"n.s.",ABS(M49)/ABS(SUMIFS(M$5:M$639,$A$5:$A$639,$A49,$C$5:$C$639,$C49-1,$D$5:$D$639,$D49))-1)))
A50: SCRC | B50: =IF(A50="","",IFERROR(VLOOKUP(A50,Titres!$A$2:$B$400,2,FALSE),"Ticker inconnu")) | C50: 2024 | D50: T1 | N50: =IF(A50="","",COUNT(H50:M50)/6) | O50: =IF(COUNT(H50:M50)=0,"",IF(LEN(IF(COUNT(I50,J50)=2,IF(J50>I50+1,"EBE > VA ",""),"")&IF(COUNT(H50,M50)=2,IF(ABS(M50)>ABS(H50),"RN > CA ",""),"")&IF(COUNT(H50,K50)=2,IF(ABS(K50)>ABS(H50),"RE > CA ",""),""))=0,"OK",IF(COUNT(I50,J50)=2,IF(J50>I50+1,"EBE > VA ",""),"")&IF(COUNT(H50,M50)=2,IF(ABS(M50)>ABS(H50),"RN > CA ",""),"")&IF(COUNT(H50,K50)=2,IF(ABS(K50)>ABS(H50),"RE > CA ",""),""))) | P50: =IF(OR($A50="",H50="",$C50=""),"",IF(COUNTIFS($A$5:$A$639,$A50,$C$5:$C$639,$C50-1,$D$5:$D$639,$D50,H$5:H$639,"<>")=0,"",IF(OR(SUMIFS(H$5:H$639,$A$5:$A$639,$A50,$C$5:$C$639,$C50-1,$D$5:$D$639,$D50)=0,H50*SUMIFS(H$5:H$639,$A$5:$A$639,$A50,$C$5:$C$639,$C50-1,$D$5:$D$639,$D50)<0),"n.s.",ABS(H50)/ABS(SUMIFS(H$5:H$639,$A$5:$A$639,$A50,$C$5:$C$639,$C50-1,$D$5:$D$639,$D50))-1))) | Q50: =IF(OR($A50="",I50="",$C50=""),"",IF(COUNTIFS($A$5:$A$639,$A50,$C$5:$C$639,$C50-1,$D$5:$D$639,$D50,I$5:I$639,"<>")=0,"",IF(OR(SUMIFS(I$5:I$639,$A$5:$A$639,$A50,$C$5:$C$639,$C50-1,$D$5:$D$639,$D50)=0,I50*SUMIFS(I$5:I$639,$A$5:$A$639,$A50,$C$5:$C$639,$C50-1,$D$5:$D$639,$D50)<0),"n.s.",ABS(I50)/ABS(SUMIFS(I$5:I$639,$A$5:$A$639,$A50,$C$5:$C$639,$C50-1,$D$5:$D$639,$D50))-1))) | R50: =IF(OR($A50="",J50="",$C50=""),"",IF(COUNTIFS($A$5:$A$639,$A50,$C$5:$C$639,$C50-1,$D$5:$D$639,$D50,J$5:J$639,"<>")=0,"",IF(OR(SUMIFS(J$5:J$639,$A$5:$A$639,$A50,$C$5:$C$639,$C50-1,$D$5:$D$639,$D50)=0,J50*SUMIFS(J$5:J$639,$A$5:$A$639,$A50,$C$5:$C$639,$C50-1,$D$5:$D$639,$D50)<0),"n.s.",ABS(J50)/ABS(SUMIFS(J$5:J$639,$A$5:$A$639,$A50,$C$5:$C$639,$C50-1,$D$5:$D$639,$D50))-1))) | S50: =IF(OR($A50="",K50="",$C50=""),"",IF(COUNTIFS($A$5:$A$639,$A50,$C$5:$C$639,$C50-1,$D$5:$D$639,$D50,K$5:K$639,"<>")=0,"",IF(OR(SUMIFS(K$5:K$639,$A$5:$A$639,$A50,$C$5:$C$639,$C50-1,$D$5:$D$639,$D50)=0,K50*SUMIFS(K$5:K$639,$A$5:$A$639,$A50,$C$5:$C$639,$C50-1,$D$5:$D$639,$D50)<0),"n.s.",ABS(K50)/ABS(SUMIFS(K$5:K$639,$A$5:$A$639,$A50,$C$5:$C$639,$C50-1,$D$5:$D$639,$D50))-1))) | T50: =IF(OR($A50="",L50="",$C50=""),"",IF(COUNTIFS($A$5:$A$639,$A50,$C$5:$C$639,$C50-1,$D$5:$D$639,$D50,L$5:L$639,"<>")=0,"",IF(OR(SUMIFS(L$5:L$639,$A$5:$A$639,$A50,$C$5:$C$639,$C50-1,$D$5:$D$639,$D50)=0,L50*SUMIFS(L$5:L$639,$A$5:$A$639,$A50,$C$5:$C$639,$C50-1,$D$5:$D$639,$D50)<0),"n.s.",ABS(L50)/ABS(SUMIFS(L$5:L$639,$A$5:$A$639,$A50,$C$5:$C$639,$C50-1,$D$5:$D$639,$D50))-1))) | U50: =IF(OR($A50="",M50="",$C50=""),"",IF(COUNTIFS($A$5:$A$639,$A50,$C$5:$C$639,$C50-1,$D$5:$D$639,$D50,M$5:M$639,"<>")=0,"",IF(OR(SUMIFS(M$5:M$639,$A$5:$A$639,$A50,$C$5:$C$639,$C50-1,$D$5:$D$639,$D50)=0,M50*SUMIFS(M$5:M$639,$A$5:$A$639,$A50,$C$5:$C$639,$C50-1,$D$5:$D$639,$D50)<0),"n.s.",ABS(M50)/ABS(SUMIFS(M$5:M$639,$A$5:$A$639,$A50,$C$5:$C$639,$C50-1,$D$5:$D$639,$D50))-1)))
A51: SCRC | B51: =IF(A51="","",IFERROR(VLOOKUP(A51,Titres!$A$2:$B$400,2,FALSE),"Ticker inconnu")) | C51: 2024 | D51: S1 | N51: =IF(A51="","",COUNT(H51:M51)/6) | O51: =IF(COUNT(H51:M51)=0,"",IF(LEN(IF(COUNT(I51,J51)=2,IF(J51>I51+1,"EBE > VA ",""),"")&IF(COUNT(H51,M51)=2,IF(ABS(M51)>ABS(H51),"RN > CA ",""),"")&IF(COUNT(H51,K51)=2,IF(ABS(K51)>ABS(H51),"RE > CA ",""),""))=0,"OK",IF(COUNT(I51,J51)=2,IF(J51>I51+1,"EBE > VA ",""),"")&IF(COUNT(H51,M51)=2,IF(ABS(M51)>ABS(H51),"RN > CA ",""),"")&IF(COUNT(H51,K51)=2,IF(ABS(K51)>ABS(H51),"RE > CA ",""),""))) | P51: =IF(OR($A51="",H51="",$C51=""),"",IF(COUNTIFS($A$5:$A$639,$A51,$C$5:$C$639,$C51-1,$D$5:$D$639,$D51,H$5:H$639,"<>")=0,"",IF(OR(SUMIFS(H$5:H$639,$A$5:$A$639,$A51,$C$5:$C$639,$C51-1,$D$5:$D$639,$D51)=0,H51*SUMIFS(H$5:H$639,$A$5:$A$639,$A51,$C$5:$C$639,$C51-1,$D$5:$D$639,$D51)<0),"n.s.",ABS(H51)/ABS(SUMIFS(H$5:H$639,$A$5:$A$639,$A51,$C$5:$C$639,$C51-1,$D$5:$D$639,$D51))-1))) | Q51: =IF(OR($A51="",I51="",$C51=""),"",IF(COUNTIFS($A$5:$A$639,$A51,$C$5:$C$639,$C51-1,$D$5:$D$639,$D51,I$5:I$639,"<>")=0,"",IF(OR(SUMIFS(I$5:I$639,$A$5:$A$639,$A51,$C$5:$C$639,$C51-1,$D$5:$D$639,$D51)=0,I51*SUMIFS(I$5:I$639,$A$5:$A$639,$A51,$C$5:$C$639,$C51-1,$D$5:$D$639,$D51)<0),"n.s.",ABS(I51)/ABS(SUMIFS(I$5:I$639,$A$5:$A$639,$A51,$C$5:$C$639,$C51-1,$D$5:$D$639,$D51))-1))) | R51: =IF(OR($A51="",J51="",$C51=""),"",IF(COUNTIFS($A$5:$A$639,$A51,$C$5:$C$639,$C51-1,$D$5:$D$639,$D51,J$5:J$639,"<>")=0,"",IF(OR(SUMIFS(J$5:J$639,$A$5:$A$639,$A51,$C$5:$C$639,$C51-1,$D$5:$D$639,$D51)=0,J51*SUMIFS(J$5:J$639,$A$5:$A$639,$A51,$C$5:$C$639,$C51-1,$D$5:$D$639,$D51)<0),"n.s.",ABS(J51)/ABS(SUMIFS(J$5:J$639,$A$5:$A$639,$A51,$C$5:$C$639,$C51-1,$D$5:$D$639,$D51))-1))) | S51: =IF(OR($A51="",K51="",$C51=""),"",IF(COUNTIFS($A$5:$A$639,$A51,$C$5:$C$639,$C51-1,$D$5:$D$639,$D51,K$5:K$639,"<>")=0,"",IF(OR(SUMIFS(K$5:K$639,$A$5:$A$639,$A51,$C$5:$C$639,$C51-1,$D$5:$D$639,$D51)=0,K51*SUMIFS(K$5:K$639,$A$5:$A$639,$A51,$C$5:$C$639,$C51-1,$D$5:$D$639,$D51)<0),"n.s.",ABS(K51)/ABS(SUMIFS(K$5:K$639,$A$5:$A$639,$A51,$C$5:$C$639,$C51-1,$D$5:$D$639,$D51))-1))) | T51: =IF(OR($A51="",L51="",$C51=""),"",IF(COUNTIFS($A$5:$A$639,$A51,$C$5:$C$639,$C51-1,$D$5:$D$639,$D51,L$5:L$639,"<>")=0,"",IF(OR(SUMIFS(L$5:L$639,$A$5:$A$639,$A51,$C$5:$C$639,$C51-1,$D$5:$D$639,$D51)=0,L51*SUMIFS(L$5:L$639,$A$5:$A$639,$A51,$C$5:$C$639,$C51-1,$D$5:$D$639,$D51)<0),"n.s.",ABS(L51)/ABS(SUMIFS(L$5:L$639,$A$5:$A$639,$A51,$C$5:$C$639,$C51-1,$D$5:$D$639,$D51))-1))) | U51: =IF(OR($A51="",M51="",$C51=""),"",IF(COUNTIFS($A$5:$A$639,$A51,$C$5:$C$639,$C51-1,$D$5:$D$639,$D51,M$5:M$639,"<>")=0,"",IF(OR(SUMIFS(M$5:M$639,$A$5:$A$639,$A51,$C$5:$C$639,$C51-1,$D$5:$D$639,$D51)=0,M51*SUMIFS(M$5:M$639,$A$5:$A$639,$A51,$C$5:$C$639,$C51-1,$D$5:$D$639,$D51)<0),"n.s.",ABS(M51)/ABS(SUMIFS(M$5:M$639,$A$5:$A$639,$A51,$C$5:$C$639,$C51-1,$D$5:$D$639,$D51))-1)))
... A124: SPHC | B124: =IF(A124="","",IFERROR(VLOOKUP(A124,Titres!$A$2:$B$400,2,FALSE),"Ticker inconnu")) | C124: 2024 | D124: T3 | N124: =IF(A124="","",COUNT(H124:M124)/6) | O124: =IF(COUNT(H124:M124)=0,"",IF(LEN(IF(COUNT(I124,J124)=2,IF(J124>I124+1,"EBE > VA ",""),"")&IF(COUNT(H124,M124)=2,IF(ABS(M124)>ABS(H124),"RN > CA ",""),"")&IF(COUNT(H124,K124)=2,IF(ABS(K124)>ABS(H124),"RE > CA ",""),""))=0,"OK",IF(COUNT(I124,J124)=2,IF(J124>I124+1,"EBE > VA ",""),"")&IF(COUNT(H124,M124)=2,IF(ABS(M124)>ABS(H124),"RN > CA ",""),"")&IF(COUNT(H124,K124)=2,IF(ABS(K124)>ABS(H124),"RE > CA ",""),""))) | P124: =IF(OR($A124="",H124="",$C124=""),"",IF(COUNTIFS($A$5:$A$639,$A124,$C$5:$C$639,$C124-1,$D$5:$D$639,$D124,H$5:H$639,"<>")=0,"",IF(OR(SUMIFS(H$5:H$639,$A$5:$A$639,$A124,$C$5:$C$639,$C124-1,$D$5:$D$639,$D124)=0,H124*SUMIFS(H$5:H$639,$A$5:$A$639,$A124,$C$5:$C$639,$C124-1,$D$5:$D$639,$D124)<0),"n.s.",ABS(H124)/ABS(SUMIFS(H$5:H$639,$A$5:$A$639,$A124,$C$5:$C$639,$C124-1,$D$5:$D$639,$D124))-1))) | Q124: =IF(OR($A124="",I124="",$C124=""),"",IF(COUNTIFS($A$5:$A$639,$A124,$C$5:$C$639,$C124-1,$D$5:$D$639,$D124,I$5:I$639,"<>")=0,"",IF(OR(SUMIFS(I$5:I$639,$A$5:$A$639,$A124,$C$5:$C$639,$C124-1,$D$5:$D$639,$D124)=0,I124*SUMIFS(I$5:I$639,$A$5:$A$639,$A124,$C$5:$C$639,$C124-1,$D$5:$D$639,$D124)<0),"n.s.",ABS(I124)/ABS(SUMIFS(I$5:I$639,$A$5:$A$639,$A124,$C$5:$C$639,$C124-1,$D$5:$D$639,$D124))-1))) | R124: =IF(OR($A124="",J124="",$C124=""),"",IF(COUNTIFS($A$5:$A$639,$A124,$C$5:$C$639,$C124-1,$D$5:$D$639,$D124,J$5:J$639,"<>")=0,"",IF(OR(SUMIFS(J$5:J$639,$A$5:$A$639,$A124,$C$5:$C$639,$C124-1,$D$5:$D$639,$D124)=0,J124*SUMIFS(J$5:J$639,$A$5:$A$639,$A124,$C$5:$C$639,$C124-1,$D$5:$D$639,$D124)<0),"n.s.",ABS(J124)/ABS(SUMIFS(J$5:J$639,$A$5:$A$639,$A124,$C$5:$C$639,$C124-1,$D$5:$D$639,$D124))-1))) | S124: =IF(OR($A124="",K124="",$C124=""),"",IF(COUNTIFS($A$5:$A$639,$A124,$C$5:$C$639,$C124-1,$D$5:$D$639,$D124,K$5:K$639,"<>")=0,"",IF(OR(SUMIFS(K$5:K$639,$A$5:$A$639,$A124,$C$5:$C$639,$C124-1,$D$5:$D$639,$D124)=0,K124*SUMIFS(K$5:K$639,$A$5:$A$639,$A124,$C$5:$C$639,$C124-1,$D$5:$D$639,$D124)<0),"n.s.",ABS(K124)/ABS(SUMIFS(K$5:K$639,$A$5:$A$639,$A124,$C$5:$C$639,$C124-1,$D$5:$D$639,$D124))-1))) | T124: =IF(OR($A124="",L124="",$C124=""),"",IF(COUNTIFS($A$5:$A$639,$A124,$C$5:$C$639,$C124-1,$D$5:$D$639,$D124,L$5:L$639,"<>")=0,"",IF(OR(SUMIFS(L$5:L$639,$A$5:$A$639,$A124,$C$5:$C$639,$C124-1,$D$5:$D$639,$D124)=0,L124*SUMIFS(L$5:L$639,$A$5:$A$639,$A124,$C$5:$C$639,$C124-1,$D$5:$D$639,$D124)<0),"n.s.",ABS(L124)/ABS(SUMIFS(L$5:L$639,$A$5:$A$639,$A124,$C$5:$C$639,$C124-1,$D$5:$D$639,$D124))-1))) | U124: =IF(OR($A124="",M124="",$C124=""),"",IF(COUNTIFS($A$5:$A$639,$A124,$C$5:$C$639,$C124-1,$D$5:$D$639,$D124,M$5:M$639,"<>")=0,"",IF(OR(SUMIFS(M$5:M$639,$A$5:$A$639,$A124,$C$5:$C$639,$C124-1,$D$5:$D$639,$D124)=0,M124*SUMIFS(M$5:M$639,$A$5:$A$639,$A124,$C$5:$C$639,$C124-1,$D$5:$D$639,$D124)<0),"n.s.",ABS(M124)/ABS(SUMIFS(M$5:M$639,$A$5:$A$639,$A124,$C$5:$C$639,$C124-1,$D$5:$D$639,$D124))-1)))
A125: SPHC | B125: =IF(A125="","",IFERROR(VLOOKUP(A125,Titres!$A$2:$B$400,2,FALSE),"Ticker inconnu")) | C125: 2025 | D125: T1 | E125: Publié | F125: 46141 | G125: https://www.richbourse.com/common/actualite/afficher-fichier/29-04-2026-saph-ci-rapport-dactivites-1er-trimestre-2026 (comparatif N-1) | H125: 94319 | K125: 16772 | L125: 15763 | M125: 11804 | N125: =IF(A125="","",COUNT(H125:M125)/6) | O125: =IF(COUNT(H125:M125)=0,"",IF(LEN(IF(COUNT(I125,J125)=2,IF(J125>I125+1,"EBE > VA ",""),"")&IF(COUNT(H125,M125)=2,IF(ABS(M125)>ABS(H125),"RN > CA ",""),"")&IF(COUNT(H125,K125)=2,IF(ABS(K125)>ABS(H125),"RE > CA ",""),""))=0,"OK",IF(COUNT(I125,J125)=2,IF(J125>I125+1,"EBE > VA ",""),"")&IF(COUNT(H125,M125)=2,IF(ABS(M125)>ABS(H125),"RN > CA ",""),"")&IF(COUNT(H125,K125)=2,IF(ABS(K125)>ABS(H125),"RE > CA ",""),""))) | P125: =IF(OR($A125="",H125="",$C125=""),"",IF(COUNTIFS($A$5:$A$639,$A125,$C$5:$C$639,$C125-1,$D$5:$D$639,$D125,H$5:H$639,"<>")=0,"",IF(OR(SUMIFS(H$5:H$639,$A$5:$A$639,$A125,$C$5:$C$639,$C125-1,$D$5:$D$639,$D125)=0,H125*SUMIFS(H$5:H$639,$A$5:$A$639,$A125,$C$5:$C$639,$C125-1,$D$5:$D$639,$D125)<0),"n.s.",ABS(H125)/ABS(SUMIFS(H$5:H$639,$A$5:$A$639,$A125,$C$5:$C$639,$C125-1,$D$5:$D$639,$D125))-1))) | Q125: =IF(OR($A125="",I125="",$C125=""),"",IF(COUNTIFS($A$5:$A$639,$A125,$C$5:$C$639,$C125-1,$D$5:$D$639,$D125,I$5:I$639,"<>")=0,"",IF(OR(SUMIFS(I$5:I$639,$A$5:$A$639,$A125,$C$5:$C$639,$C125-1,$D$5:$D$639,$D125)=0,I125*SUMIFS(I$5:I$639,$A$5:$A$639,$A125,$C$5:$C$639,$C125-1,$D$5:$D$639,$D125)<0),"n.s.",ABS(I125)/ABS(SUMIFS(I$5:I$639,$A$5:$A$639,$A125,$C$5:$C$639,$C125-1,$D$5:$D$639,$D125))-1))) | R125: =IF(OR($A125="",J125="",$C125=""),"",IF(COUNTIFS($A$5:$A$639,$A125,$C$5:$C$639,$C125-1,$D$5:$D$639,$D125,J$5:J$639,"<>")=0,"",IF(OR(SUMIFS(J$5:J$639,$A$5:$A$639,$A125,$C$5:$C$639,$C125-1,$D$5:$D$639,$D125)=0,J125*SUMIFS(J$5:J$639,$A$5:$A$639,$A125,$C$5:$C$639,$C125-1,$D$5:$D$639,$D125)<0),"n.s.",ABS(J125)/ABS(SUMIFS(J$5:J$639,$A$5:$A$639,$A125,$C$5:$C$639,$C125-1,$D$5:$D$639,$D125))-1))) | S125: =IF(OR($A125="",K125="",$C125=""),"",IF(COUNTIFS($A$5:$A$639,$A125,$C$5:$C$639,$C125-1,$D$5:$D$639,$D125,K$5:K$639,"<>")=0,"",IF(OR(SUMIFS(K$5:K$639,$A$5:$A$639,$A125,$C$5:$C$639,$C125-1,$D$5:$D$639,$D125)=0,K125*SUMIFS(K$5:K$639,$A$5:$A$639,$A125,$C$5:$C$639,$C125-1,$D$5:$D$639,$D125)<0),"n.s.",ABS(K125)/ABS(SUMIFS(K$5:K$639,$A$5:$A$639,$A125,$C$5:$C$639,$C125-1,$D$5:$D$639,$D125))-1))) | T125: =IF(OR($A125="",L125="",$C125=""),"",IF(COUNTIFS($A$5:$A$639,$A125,$C$5:$C$639,$C125-1,$D$5:$D$639,$D125,L$5:L$639,"<>")=0,"",IF(OR(SUMIFS(L$5:L$639,$A$5:$A$639,$A125,$C$5:$C$639,$C125-1,$D$5:$D$639,$D125)=0,L125*SUMIFS(L$5:L$639,$A$5:$A$639,$A125,$C$5:$C$639,$C125-1,$D$5:$D$639,$D125)<0),"n.s.",ABS(L125)/ABS(SUMIFS(L$5:L$639,$A$5:$A$639,$A125,$C$5:$C$639,$C125-1,$D$5:$D$639,$D125))-1))) | U125: =IF(OR($A125="",M125="",$C125=""),"",IF(COUNTIFS($A$5:$A$639,$A125,$C$5:$C$639,$C125-1,$D$5:$D$639,$D125,M$5:M$639,"<>")=0,"",IF(OR(SUMIFS(M$5:M$639,$A$5:$A$639,$A125,$C$5:$C$639,$C125-1,$D$5:$D$639,$D125)=0,M125*SUMIFS(M$5:M$639,$A$5:$A$639,$A125,$C$5:$C$639,$C125-1,$D$5:$D$639,$D125)<0),"n.s.",ABS(M125)/ABS(SUMIFS(M$5:M$639,$A$5:$A$639,$A125,$C$5:$C$639,$C125-1,$D$5:$D$639,$D125))-1)))
A126: SPHC | B126: =IF(A126="","",IFERROR(VLOOKUP(A126,Titres!$A$2:$B$400,2,FALSE),"Ticker inconnu")) | C126: 2025 | D126: S1 | N126: =IF(A126="","",COUNT(H126:M126)/6) | O126: =IF(COUNT(H126:M126)=0,"",IF(LEN(IF(COUNT(I126,J126)=2,IF(J126>I126+1,"EBE > VA ",""),"")&IF(COUNT(H126,M126)=2,IF(ABS(M126)>ABS(H126),"RN > CA ",""),"")&IF(COUNT(H126,K126)=2,IF(ABS(K126)>ABS(H126),"RE > CA ",""),""))=0,"OK",IF(COUNT(I126,J126)=2,IF(J126>I126+1,"EBE > VA ",""),"")&IF(COUNT(H126,M126)=2,IF(ABS(M126)>ABS(H126),"RN > CA ",""),"")&IF(COUNT(H126,K126)=2,IF(ABS(K126)>ABS(H126),"RE > CA ",""),""))) | P126: =IF(OR($A126="",H126="",$C126=""),"",IF(COUNTIFS($A$5:$A$639,$A126,$C$5:$C$639,$C126-1,$D$5:$D$639,$D126,H$5:H$639,"<>")=0,"",IF(OR(SUMIFS(H$5:H$639,$A$5:$A$639,$A126,$C$5:$C$639,$C126-1,$D$5:$D$639,$D126)=0,H126*SUMIFS(H$5:H$639,$A$5:$A$639,$A126,$C$5:$C$639,$C126-1,$D$5:$D$639,$D126)<0),"n.s.",ABS(H126)/ABS(SUMIFS(H$5:H$639,$A$5:$A$639,$A126,$C$5:$C$639,$C126-1,$D$5:$D$639,$D126))-1))) | Q126: =IF(OR($A126="",I126="",$C126=""),"",IF(COUNTIFS($A$5:$A$639,$A126,$C$5:$C$639,$C126-1,$D$5:$D$639,$D126,I$5:I$639,"<>")=0,"",IF(OR(SUMIFS(I$5:I$639,$A$5:$A$639,$A126,$C$5:$C$639,$C126-1,$D$5:$D$639,$D126)=0,I126*SUMIFS(I$5:I$639,$A$5:$A$639,$A126,$C$5:$C$639,$C126-1,$D$5:$D$639,$D126)<0),"n.s.",ABS(I126)/ABS(SUMIFS(I$5:I$639,$A$5:$A$639,$A126,$C$5:$C$639,$C126-1,$D$5:$D$639,$D126))-1))) | R126: =IF(OR($A126="",J126="",$C126=""),"",IF(COUNTIFS($A$5:$A$639,$A126,$C$5:$C$639,$C126-1,$D$5:$D$639,$D126,J$5:J$639,"<>")=0,"",IF(OR(SUMIFS(J$5:J$639,$A$5:$A$639,$A126,$C$5:$C$639,$C126-1,$D$5:$D$639,$D126)=0,J126*SUMIFS(J$5:J$639,$A$5:$A$639,$A126,$C$5:$C$639,$C126-1,$D$5:$D$639,$D126)<0),"n.s.",ABS(J126)/ABS(SUMIFS(J$5:J$639,$A$5:$A$639,$A126,$C$5:$C$639,$C126-1,$D$5:$D$639,$D126))-1))) | S126: =IF(OR($A126="",K126="",$C126=""),"",IF(COUNTIFS($A$5:$A$639,$A126,$C$5:$C$639,$C126-1,$D$5:$D$639,$D126,K$5:K$639,"<>")=0,"",IF(OR(SUMIFS(K$5:K$639,$A$5:$A$639,$A126,$C$5:$C$639,$C126-1,$D$5:$D$639,$D126)=0,K126*SUMIFS(K$5:K$639,$A$5:$A$639,$A126,$C$5:$C$639,$C126-1,$D$5:$D$639,$D126)<0),"n.s.",ABS(K126)/ABS(SUMIFS(K$5:K$639,$A$5:$A$639,$A126,$C$5:$C$639,$C126-1,$D$5:$D$639,$D126))-1))) | T126: =IF(OR($A126="",L126="",$C126=""),"",IF(COUNTIFS($A$5:$A$639,$A126,$C$5:$C$639,$C126-1,$D$5:$D$639,$D126,L$5:L$639,"<>")=0,"",IF(OR(SUMIFS(L$5:L$639,$A$5:$A$639,$A126,$C$5:$C$639,$C126-1,$D$5:$D$639,$D126)=0,L126*SUMIFS(L$5:L$639,$A$5:$A$639,$A126,$C$5:$C$639,$C126-1,$D$5:$D$639,$D126)<0),"n.s.",ABS(L126)/ABS(SUMIFS(L$5:L$639,$A$5:$A$639,$A126,$C$5:$C$639,$C126-1,$D$5:$D$639,$D126))-1))) | U126: =IF(OR($A126="",M126="",$C126=""),"",IF(COUNTIFS($A$5:$A$639,$A126,$C$5:$C$639,$C126-1,$D$5:$D$639,$D126,M$5:M$639,"<>")=0,"",IF(OR(SUMIFS(M$5:M$639,$A$5:$A$639,$A126,$C$5:$C$639,$C126-1,$D$5:$D$639,$D126)=0,M126*SUMIFS(M$5:M$639,$A$5:$A$639,$A126,$C$5:$C$639,$C126-1,$D$5:$D$639,$D126)<0),"n.s.",ABS(M126)/ABS(SUMIFS(M$5:M$639,$A$5:$A$639,$A126,$C$5:$C$639,$C126-1,$D$5:$D$639,$D126))-1)))
A127: SPHC | B127: =IF(A127="","",IFERROR(VLOOKUP(A127,Titres!$A$2:$B$400,2,FALSE),"Ticker inconnu")) | C127: 2025 | D127: T3 | N127: =IF(A127="","",COUNT(H127:M127)/6) | O127: =IF(COUNT(H127:M127)=0,"",IF(LEN(IF(COUNT(I127,J127)=2,IF(J127>I127+1,"EBE > VA ",""),"")&IF(COUNT(H127,M127)=2,IF(ABS(M127)>ABS(H127),"RN > CA ",""),"")&IF(COUNT(H127,K127)=2,IF(ABS(K127)>ABS(H127),"RE > CA ",""),""))=0,"OK",IF(COUNT(I127,J127)=2,IF(J127>I127+1,"EBE > VA ",""),"")&IF(COUNT(H127,M127)=2,IF(ABS(M127)>ABS(H127),"RN > CA ",""),"")&IF(COUNT(H127,K127)=2,IF(ABS(K127)>ABS(H127),"RE > CA ",""),""))) | P127: =IF(OR($A127="",H127="",$C127=""),"",IF(COUNTIFS($A$5:$A$639,$A127,$C$5:$C$639,$C127-1,$D$5:$D$639,$D127,H$5:H$639,"<>")=0,"",IF(OR(SUMIFS(H$5:H$639,$A$5:$A$639,$A127,$C$5:$C$639,$C127-1,$D$5:$D$639,$D127)=0,H127*SUMIFS(H$5:H$639,$A$5:$A$639,$A127,$C$5:$C$639,$C127-1,$D$5:$D$639,$D127)<0),"n.s.",ABS(H127)/ABS(SUMIFS(H$5:H$639,$A$5:$A$639,$A127,$C$5:$C$639,$C127-1,$D$5:$D$639,$D127))-1))) | Q127: =IF(OR($A127="",I127="",$C127=""),"",IF(COUNTIFS($A$5:$A$639,$A127,$C$5:$C$639,$C127-1,$D$5:$D$639,$D127,I$5:I$639,"<>")=0,"",IF(OR(SUMIFS(I$5:I$639,$A$5:$A$639,$A127,$C$5:$C$639,$C127-1,$D$5:$D$639,$D127)=0,I127*SUMIFS(I$5:I$639,$A$5:$A$639,$A127,$C$5:$C$639,$C127-1,$D$5:$D$639,$D127)<0),"n.s.",ABS(I127)/ABS(SUMIFS(I$5:I$639,$A$5:$A$639,$A127,$C$5:$C$639,$C127-1,$D$5:$D$639,$D127))-1))) | R127: =IF(OR($A127="",J127="",$C127=""),"",IF(COUNTIFS($A$5:$A$639,$A127,$C$5:$C$639,$C127-1,$D$5:$D$639,$D127,J$5:J$639,"<>")=0,"",IF(OR(SUMIFS(J$5:J$639,$A$5:$A$639,$A127,$C$5:$C$639,$C127-1,$D$5:$D$639,$D127)=0,J127*SUMIFS(J$5:J$639,$A$5:$A$639,$A127,$C$5:$C$639,$C127-1,$D$5:$D$639,$D127)<0),"n.s.",ABS(J127)/ABS(SUMIFS(J$5:J$639,$A$5:$A$639,$A127,$C$5:$C$639,$C127-1,$D$5:$D$639,$D127))-1))) | S127: =IF(OR($A127="",K127="",$C127=""),"",IF(COUNTIFS($A$5:$A$639,$A127,$C$5:$C$639,$C127-1,$D$5:$D$639,$D127,K$5:K$639,"<>")=0,"",IF(OR(SUMIFS(K$5:K$639,$A$5:$A$639,$A127,$C$5:$C$639,$C127-1,$D$5:$D$639,$D127)=0,K127*SUMIFS(K$5:K$639,$A$5:$A$639,$A127,$C$5:$C$639,$C127-1,$D$5:$D$639,$D127)<0),"n.s.",ABS(K127)/ABS(SUMIFS(K$5:K$639,$A$5:$A$639,$A127,$C$5:$C$639,$C127-1,$D$5:$D$639,$D127))-1))) | T127: =IF(OR($A127="",L127="",$C127=""),"",IF(COUNTIFS($A$5:$A$639,$A127,$C$5:$C$639,$C127-1,$D$5:$D$639,$D127,L$5:L$639,"<>")=0,"",IF(OR(SUMIFS(L$5:L$639,$A$5:$A$639,$A127,$C$5:$C$639,$C127-1,$D$5:$D$639,$D127)=0,L127*SUMIFS(L$5:L$639,$A$5:$A$639,$A127,$C$5:$C$639,$C127-1,$D$5:$D$639,$D127)<0),"n.s.",ABS(L127)/ABS(SUMIFS(L$5:L$639,$A$5:$A$639,$A127,$C$5:$C$639,$C127-1,$D$5:$D$639,$D127))-1))) | U127: =IF(OR($A127="",M127="",$C127=""),"",IF(COUNTIFS($A$5:$A$639,$A127,$C$5:$C$639,$C127-1,$D$5:$D$639,$D127,M$5:M$639,"<>")=0,"",IF(OR(SUMIFS(M$5:M$639,$A$5:$A$639,$A127,$C$5:$C$639,$C127-1,$D$5:$D$639,$D127)=0,M127*SUMIFS(M$5:M$639,$A$5:$A$639,$A127,$C$5:$C$639,$C127-1,$D$5:$D$639,$D127)<0),"n.s.",ABS(M127)/ABS(SUMIFS(M$5:M$639,$A$5:$A$639,$A127,$C$5:$C$639,$C127-1,$D$5:$D$639,$D127))-1)))
A128: SPHC | B128: =IF(A128="","",IFERROR(VLOOKUP(A128,Titres!$A$2:$B$400,2,FALSE),"Ticker inconnu")) | C128: 2026 | D128: T1 | E128: Publié | F128: 46141 | G128: https://www.richbourse.com/common/actualite/afficher-fichier/29-04-2026-saph-ci-rapport-dactivites-1er-trimestre-2026 | H128: 71772 | K128: 4456 | L128: 3575 | M128: 2633 | N128: =IF(A128="","",COUNT(H128:M128)/6) | O128: =IF(COUNT(H128:M128)=0,"",IF(LEN(IF(COUNT(I128,J128)=2,IF(J128>I128+1,"EBE > VA ",""),"")&IF(COUNT(H128,M128)=2,IF(ABS(M128)>ABS(H128),"RN > CA ",""),"")&IF(COUNT(H128,K128)=2,IF(ABS(K128)>ABS(H128),"RE > CA ",""),""))=0,"OK",IF(COUNT(I128,J128)=2,IF(J128>I128+1,"EBE > VA ",""),"")&IF(COUNT(H128,M128)=2,IF(ABS(M128)>ABS(H128),"RN > CA ",""),"")&IF(COUNT(H128,K128)=2,IF(ABS(K128)>ABS(H128),"RE > CA ",""),""))) | P128: =IF(OR($A128="",H128="",$C128=""),"",IF(COUNTIFS($A$5:$A$639,$A128,$C$5:$C$639,$C128-1,$D$5:$D$639,$D128,H$5:H$639,"<>")=0,"",IF(OR(SUMIFS(H$5:H$639,$A$5:$A$639,$A128,$C$5:$C$639,$C128-1,$D$5:$D$639,$D128)=0,H128*SUMIFS(H$5:H$639,$A$5:$A$639,$A128,$C$5:$C$639,$C128-1,$D$5:$D$639,$D128)<0),"n.s.",ABS(H128)/ABS(SUMIFS(H$5:H$639,$A$5:$A$639,$A128,$C$5:$C$639,$C128-1,$D$5:$D$639,$D128))-1))) | Q128: =IF(OR($A128="",I128="",$C128=""),"",IF(COUNTIFS($A$5:$A$639,$A128,$C$5:$C$639,$C128-1,$D$5:$D$639,$D128,I$5:I$639,"<>")=0,"",IF(OR(SUMIFS(I$5:I$639,$A$5:$A$639,$A128,$C$5:$C$639,$C128-1,$D$5:$D$639,$D128)=0,I128*SUMIFS(I$5:I$639,$A$5:$A$639,$A128,$C$5:$C$639,$C128-1,$D$5:$D$639,$D128)<0),"n.s.",ABS(I128)/ABS(SUMIFS(I$5:I$639,$A$5:$A$639,$A128,$C$5:$C$639,$C128-1,$D$5:$D$639,$D128))-1))) | R128: =IF(OR($A128="",J128="",$C128=""),"",IF(COUNTIFS($A$5:$A$639,$A128,$C$5:$C$639,$C128-1,$D$5:$D$639,$D128,J$5:J$639,"<>")=0,"",IF(OR(SUMIFS(J$5:J$639,$A$5:$A$639,$A128,$C$5:$C$639,$C128-1,$D$5:$D$639,$D128)=0,J128*SUMIFS(J$5:J$639,$A$5:$A$639,$A128,$C$5:$C$639,$C128-1,$D$5:$D$639,$D128)<0),"n.s.",ABS(J128)/ABS(SUMIFS(J$5:J$639,$A$5:$A$639,$A128,$C$5:$C$639,$C128-1,$D$5:$D$639,$D128))-1))) | S128: =IF(OR($A128="",K128="",$C128=""),"",IF(COUNTIFS($A$5:$A$639,$A128,$C$5:$C$639,$C128-1,$D$5:$D$639,$D128,K$5:K$639,"<>")=0,"",IF(OR(SUMIFS(K$5:K$639,$A$5:$A$639,$A128,$C$5:$C$639,$C128-1,$D$5:$D$639,$D128)=0,K128*SUMIFS(K$5:K$639,$A$5:$A$639,$A128,$C$5:$C$639,$C128-1,$D$5:$D$639,$D128)<0),"n.s.",ABS(K128)/ABS(SUMIFS(K$5:K$639,$A$5:$A$639,$A128,$C$5:$C$639,$C128-1,$D$5:$D$639,$D128))-1))) | T128: =IF(OR($A128="",L128="",$C128=""),"",IF(COUNTIFS($A$5:$A$639,$A128,$C$5:$C$639,$C128-1,$D$5:$D$639,$D128,L$5:L$639,"<>")=0,"",IF(OR(SUMIFS(L$5:L$639,$A$5:$A$639,$A128,$C$5:$C$639,$C128-1,$D$5:$D$639,$D128)=0,L128*SUMIFS(L$5:L$639,$A$5:$A$639,$A128,$C$5:$C$639,$C128-1,$D$5:$D$639,$D128)<0),"n.s.",ABS(L128)/ABS(SUMIFS(L$5:L$639,$A$5:$A$639,$A128,$C$5:$C$639,$C128-1,$D$5:$D$639,$D128))-1))) | U128: =IF(OR($A128="",M128="",$C128=""),"",IF(COUNTIFS($A$5:$A$639,$A128,$C$5:$C$639,$C128-1,$D$5:$D$639,$D128,M$5:M$639,"<>")=0,"",IF(OR(SUMIFS(M$5:M$639,$A$5:$A$639,$A128,$C$5:$C$639,$C128-1,$D$5:$D$639,$D128)=0,M128*SUMIFS(M$5:M$639,$A$5:$A$639,$A128,$C$5:$C$639,$C128-1,$D$5:$D$639,$D128)<0),"n.s.",ABS(M128)/ABS(SUMIFS(M$5:M$639,$A$5:$A$639,$A128,$C$5:$C$639,$C128-1,$D$5:$D$639,$D128))-1)))
A129: SPHC | B129: =IF(A129="","",IFERROR(VLOOKUP(A129,Titres!$A$2:$B$400,2,FALSE),"Ticker inconnu")) | C129: 2026 | D129: S1 | N129: =IF(A129="","",COUNT(H129:M129)/6) | O129: =IF(COUNT(H129:M129)=0,"",IF(LEN(IF(COUNT(I129,J129)=2,IF(J129>I129+1,"EBE > VA ",""),"")&IF(COUNT(H129,M129)=2,IF(ABS(M129)>ABS(H129),"RN > CA ",""),"")&IF(COUNT(H129,K129)=2,IF(ABS(K129)>ABS(H129),"RE > CA ",""),""))=0,"OK",IF(COUNT(I129,J129)=2,IF(J129>I129+1,"EBE > VA ",""),"")&IF(COUNT(H129,M129)=2,IF(ABS(M129)>ABS(H129),"RN > CA ",""),"")&IF(COUNT(H129,K129)=2,IF(ABS(K129)>ABS(H129),"RE > CA ",""),""))) | P129: =IF(OR($A129="",H129="",$C129=""),"",IF(COUNTIFS($A$5:$A$639,$A129,$C$5:$C$639,$C129-1,$D$5:$D$639,$D129,H$5:H$639,"<>")=0,"",IF(OR(SUMIFS(H$5:H$639,$A$5:$A$639,$A129,$C$5:$C$639,$C129-1,$D$5:$D$639,$D129)=0,H129*SUMIFS(H$5:H$639,$A$5:$A$639,$A129,$C$5:$C$639,$C129-1,$D$5:$D$639,$D129)<0),"n.s.",ABS(H129)/ABS(SUMIFS(H$5:H$639,$A$5:$A$639,$A129,$C$5:$C$639,$C129-1,$D$5:$D$639,$D129))-1))) | Q129: =IF(OR($A129="",I129="",$C129=""),"",IF(COUNTIFS($A$5:$A$639,$A129,$C$5:$C$639,$C129-1,$D$5:$D$639,$D129,I$5:I$639,"<>")=0,"",IF(OR(SUMIFS(I$5:I$639,$A$5:$A$639,$A129,$C$5:$C$639,$C129-1,$D$5:$D$639,$D129)=0,I129*SUMIFS(I$5:I$639,$A$5:$A$639,$A129,$C$5:$C$639,$C129-1,$D$5:$D$639,$D129)<0),"n.s.",ABS(I129)/ABS(SUMIFS(I$5:I$639,$A$5:$A$639,$A129,$C$5:$C$639,$C129-1,$D$5:$D$639,$D129))-1))) | R129: =IF(OR($A129="",J129="",$C129=""),"",IF(COUNTIFS($A$5:$A$639,$A129,$C$5:$C$639,$C129-1,$D$5:$D$639,$D129,J$5:J$639,"<>")=0,"",IF(OR(SUMIFS(J$5:J$639,$A$5:$A$639,$A129,$C$5:$C$639,$C129-1,$D$5:$D$639,$D129)=0,J129*SUMIFS(J$5:J$639,$A$5:$A$639,$A129,$C$5:$C$639,$C129-1,$D$5:$D$639,$D129)<0),"n.s.",ABS(J129)/ABS(SUMIFS(J$5:J$639,$A$5:$A$639,$A129,$C$5:$C$639,$C129-1,$D$5:$D$639,$D129))-1))) | S129: =IF(OR($A129="",K129="",$C129=""),"",IF(COUNTIFS($A$5:$A$639,$A129,$C$5:$C$639,$C129-1,$D$5:$D$639,$D129,K$5:K$639,"<>")=0,"",IF(OR(SUMIFS(K$5:K$639,$A$5:$A$639,$A129,$C$5:$C$639,$C129-1,$D$5:$D$639,$D129)=0,K129*SUMIFS(K$5:K$639,$A$5:$A$639,$A129,$C$5:$C$639,$C129-1,$D$5:$D$639,$D129)<0),"n.s.",ABS(K129)/ABS(SUMIFS(K$5:K$639,$A$5:$A$639,$A129,$C$5:$C$639,$C129-1,$D$5:$D$639,$D129))-1))) | T129: =IF(OR($A129="",L129="",$C129=""),"",IF(COUNTIFS($A$5:$A$639,$A129,$C$5:$C$639,$C129-1,$D$5:$D$639,$D129,L$5:L$639,"<>")=0,"",IF(OR(SUMIFS(L$5:L$639,$A$5:$A$639,$A129,$C$5:$C$639,$C129-1,$D$5:$D$639,$D129)=0,L129*SUMIFS(L$5:L$639,$A$5:$A$639,$A129,$C$5:$C$639,$C129-1,$D$5:$D$639,$D129)<0),"n.s.",ABS(L129)/ABS(SUMIFS(L$5:L$639,$A$5:$A$639,$A129,$C$5:$C$639,$C129-1,$D$5:$D$639,$D129))-1))) | U129: =IF(OR($A129="",M129="",$C129=""),"",IF(COUNTIFS($A$5:$A$639,$A129,$C$5:$C$639,$C129-1,$D$5:$D$639,$D129,M$5:M$639,"<>")=0,"",IF(OR(SUMIFS(M$5:M$639,$A$5:$A$639,$A129,$C$5:$C$639,$C129-1,$D$5:$D$639,$D129)=0,M129*SUMIFS(M$5:M$639,$A$5:$A$639,$A129,$C$5:$C$639,$C129-1,$D$5:$D$639,$D129)<0),"n.s.",ABS(M129)/ABS(SUMIFS(M$5:M$639,$A$5:$A$639,$A129,$C$5:$C$639,$C129-1,$D$5:$D$639,$D129))-1)))
A130: SPHC | B130: =IF(A130="","",IFERROR(VLOOKUP(A130,Titres!$A$2:$B$400,2,FALSE),"Ticker inconnu")) | C130: 2026 | D130: T3 | N130: =IF(A130="","",COUNT(H130:M130)/6) | O130: =IF(COUNT(H130:M130)=0,"",IF(LEN(IF(COUNT(I130,J130)=2,IF(J130>I130+1,"EBE > VA ",""),"")&IF(COUNT(H130,M130)=2,IF(ABS(M130)>ABS(H130),"RN > CA ",""),"")&IF(COUNT(H130,K130)=2,IF(ABS(K130)>ABS(H130),"RE > CA ",""),""))=0,"OK",IF(COUNT(I130,J130)=2,IF(J130>I130+1,"EBE > VA ",""),"")&IF(COUNT(H130,M130)=2,IF(ABS(M130)>ABS(H130),"RN > CA ",""),"")&IF(COUNT(H130,K130)=2,IF(ABS(K130)>ABS(H130),"RE > CA ",""),""))) | P130: =IF(OR($A130="",H130="",$C130=""),"",IF(COUNTIFS($A$5:$A$639,$A130,$C$5:$C$639,$C130-1,$D$5:$D$639,$D130,H$5:H$639,"<>")=0,"",IF(OR(SUMIFS(H$5:H$639,$A$5:$A$639,$A130,$C$5:$C$639,$C130-1,$D$5:$D$639,$D130)=0,H130*SUMIFS(H$5:H$639,$A$5:$A$639,$A130,$C$5:$C$639,$C130-1,$D$5:$D$639,$D130)<0),"n.s.",ABS(H130)/ABS(SUMIFS(H$5:H$639,$A$5:$A$639,$A130,$C$5:$C$639,$C130-1,$D$5:$D$639,$D130))-1))) | Q130: =IF(OR($A130="",I130="",$C130=""),"",IF(COUNTIFS($A$5:$A$639,$A130,$C$5:$C$639,$C130-1,$D$5:$D$639,$D130,I$5:I$639,"<>")=0,"",IF(OR(SUMIFS(I$5:I$639,$A$5:$A$639,$A130,$C$5:$C$639,$C130-1,$D$5:$D$639,$D130)=0,I130*SUMIFS(I$5:I$639,$A$5:$A$639,$A130,$C$5:$C$639,$C130-1,$D$5:$D$639,$D130)<0),"n.s.",ABS(I130)/ABS(SUMIFS(I$5:I$639,$A$5:$A$639,$A130,$C$5:$C$639,$C130-1,$D$5:$D$639,$D130))-1))) | R130: =IF(OR($A130="",J130="",$C130=""),"",IF(COUNTIFS($A$5:$A$639,$A130,$C$5:$C$639,$C130-1,$D$5:$D$639,$D130,J$5:J$639,"<>")=0,"",IF(OR(SUMIFS(J$5:J$639,$A$5:$A$639,$A130,$C$5:$C$639,$C130-1,$D$5:$D$639,$D130)=0,J130*SUMIFS(J$5:J$639,$A$5:$A$639,$A130,$C$5:$C$639,$C130-1,$D$5:$D$639,$D130)<0),"n.s.",ABS(J130)/ABS(SUMIFS(J$5:J$639,$A$5:$A$639,$A130,$C$5:$C$639,$C130-1,$D$5:$D$639,$D130))-1))) | S130: =IF(OR($A130="",K130="",$C130=""),"",IF(COUNTIFS($A$5:$A$639,$A130,$C$5:$C$639,$C130-1,$D$5:$D$639,$D130,K$5:K$639,"<>")=0,"",IF(OR(SUMIFS(K$5:K$639,$A$5:$A$639,$A130,$C$5:$C$639,$C130-1,$D$5:$D$639,$D130)=0,K130*SUMIFS(K$5:K$639,$A$5:$A$639,$A130,$C$5:$C$639,$C130-1,$D$5:$D$639,$D130)<0),"n.s.",ABS(K130)/ABS(SUMIFS(K$5:K$639,$A$5:$A$639,$A130,$C$5:$C$639,$C130-1,$D$5:$D$639,$D130))-1))) | T130: =IF(OR($A130="",L130="",$C130=""),"",IF(COUNTIFS($A$5:$A$639,$A130,$C$5:$C$639,$C130-1,$D$5:$D$639,$D130,L$5:L$639,"<>")=0,"",IF(OR(SUMIFS(L$5:L$639,$A$5:$A$639,$A130,$C$5:$C$639,$C130-1,$D$5:$D$639,$D130)=0,L130*SUMIFS(L$5:L$639,$A$5:$A$639,$A130,$C$5:$C$639,$C130-1,$D$5:$D$639,$D130)<0),"n.s.",ABS(L130)/ABS(SUMIFS(L$5:L$639,$A$5:$A$639,$A130,$C$5:$C$639,$C130-1,$D$5:$D$639,$D130))-1))) | U130: =IF(OR($A130="",M130="",$C130=""),"",IF(COUNTIFS($A$5:$A$639,$A130,$C$5:$C$639,$C130-1,$D$5:$D$639,$D130,M$5:M$639,"<>")=0,"",IF(OR(SUMIFS(M$5:M$639,$A$5:$A$639,$A130,$C$5:$C$639,$C130-1,$D$5:$D$639,$D130)=0,M130*SUMIFS(M$5:M$639,$A$5:$A$639,$A130,$C$5:$C$639,$C130-1,$D$5:$D$639,$D130)<0),"n.s.",ABS(M130)/ABS(SUMIFS(M$5:M$639,$A$5:$A$639,$A130,$C$5:$C$639,$C130-1,$D$5:$D$639,$D130))-1)))
A131: STBC | B131: =IF(A131="","",IFERROR(VLOOKUP(A131,Titres!$A$2:$B$400,2,FALSE),"Ticker inconnu")) | C131: 2021 | D131: T1 | N131: =IF(A131="","",COUNT(H131:M131)/6) | O131: =IF(COUNT(H131:M131)=0,"",IF(LEN(IF(COUNT(I131,J131)=2,IF(J131>I131+1,"EBE > VA ",""),"")&IF(COUNT(H131,M131)=2,IF(ABS(M131)>ABS(H131),"RN > CA ",""),"")&IF(COUNT(H131,K131)=2,IF(ABS(K131)>ABS(H131),"RE > CA ",""),""))=0,"OK",IF(COUNT(I131,J131)=2,IF(J131>I131+1,"EBE > VA ",""),"")&IF(COUNT(H131,M131)=2,IF(ABS(M131)>ABS(H131),"RN > CA ",""),"")&IF(COUNT(H131,K131)=2,IF(ABS(K131)>ABS(H131),"RE > CA ",""),""))) | P131: =IF(OR($A131="",H131="",$C131=""),"",IF(COUNTIFS($A$5:$A$639,$A131,$C$5:$C$639,$C131-1,$D$5:$D$639,$D131,H$5:H$639,"<>")=0,"",IF(OR(SUMIFS(H$5:H$639,$A$5:$A$639,$A131,$C$5:$C$639,$C131-1,$D$5:$D$639,$D131)=0,H131*SUMIFS(H$5:H$639,$A$5:$A$639,$A131,$C$5:$C$639,$C131-1,$D$5:$D$639,$D131)<0),"n.s.",ABS(H131)/ABS(SUMIFS(H$5:H$639,$A$5:$A$639,$A131,$C$5:$C$639,$C131-1,$D$5:$D$639,$D131))-1))) | Q131: =IF(OR($A131="",I131="",$C131=""),"",IF(COUNTIFS($A$5:$A$639,$A131,$C$5:$C$639,$C131-1,$D$5:$D$639,$D131,I$5:I$639,"<>")=0,"",IF(OR(SUMIFS(I$5:I$639,$A$5:$A$639,$A131,$C$5:$C$639,$C131-1,$D$5:$D$639,$D131)=0,I131*SUMIFS(I$5:I$639,$A$5:$A$639,$A131,$C$5:$C$639,$C131-1,$D$5:$D$639,$D131)<0),"n.s.",ABS(I131)/ABS(SUMIFS(I$5:I$639,$A$5:$A$639,$A131,$C$5:$C$639,$C131-1,$D$5:$D$639,$D131))-1))) | R131: =IF(OR($A131="",J131="",$C131=""),"",IF(COUNTIFS($A$5:$A$639,$A131,$C$5:$C$639,$C131-1,$D$5:$D$639,$D131,J$5:J$639,"<>")=0,"",IF(OR(SUMIFS(J$5:J$639,$A$5:$A$639,$A131,$C$5:$C$639,$C131-1,$D$5:$D$639,$D131)=0,J131*SUMIFS(J$5:J$639,$A$5:$A$639,$A131,$C$5:$C$639,$C131-1,$D$5:$D$639,$D131)<0),"n.s.",ABS(J131)/ABS(SUMIFS(J$5:J$639,$A$5:$A$639,$A131,$C$5:$C$639,$C131-1,$D$5:$D$639,$D131))-1))) | S131: =IF(OR($A131="",K131="",$C131=""),"",IF(COUNTIFS($A$5:$A$639,$A131,$C$5:$C$639,$C131-1,$D$5:$D$639,$D131,K$5:K$639,"<>")=0,"",IF(OR(SUMIFS(K$5:K$639,$A$5:$A$639,$A131,$C$5:$C$639,$C131-1,$D$5:$D$639,$D131)=0,K131*SUMIFS(K$5:K$639,$A$5:$A$639,$A131,$C$5:$C$639,$C131-1,$D$5:$D$639,$D131)<0),"n.s.",ABS(K131)/ABS(SUMIFS(K$5:K$639,$A$5:$A$639,$A131,$C$5:$C$639,$C131-1,$D$5:$D$639,$D131))-1))) | T131: =IF(OR($A131="",L131="",$C131=""),"",IF(COUNTIFS($A$5:$A$639,$A131,$C$5:$C$639,$C131-1,$D$5:$D$639,$D131,L$5:L$639,"<>")=0,"",IF(OR(SUMIFS(L$5:L$639,$A$5:$A$639,$A131,$C$5:$C$639,$C131-1,$D$5:$D$639,$D131)=0,L131*SUMIFS(L$5:L$639,$A$5:$A$639,$A131,$C$5:$C$639,$C131-1,$D$5:$D$639,$D131)<0),"n.s.",ABS(L131)/ABS(SUMIFS(L$5:L$639,$A$5:$A$639,$A131,$C$5:$C$639,$C131-1,$D$5:$D$639,$D131))-1))) | U131: =IF(OR($A131="",M131="",$C131=""),"",IF(COUNTIFS($A$5:$A$639,$A131,$C$5:$C$639,$C131-1,$D$5:$D$639,$D131,M$5:M$639,"<>")=0,"",IF(OR(SUMIFS(M$5:M$639,$A$5:$A$639,$A131,$C$5:$C$639,$C131-1,$D$5:$D$639,$D131)=0,M131*SUMIFS(M$5:M$639,$A$5:$A$639,$A131,$C$5:$C$639,$C131-1,$D$5:$D$639,$D131)<0),"n.s.",ABS(M131)/ABS(SUMIFS(M$5:M$639,$A$5:$A$639,$A131,$C$5:$C$639,$C131-1,$D$5:$D$639,$D131))-1)))
A132: STBC | B132: =IF(A132="","",IFERROR(VLOOKUP(A132,Titres!$A$2:$B$400,2,FALSE),"Ticker inconnu")) | C132: 2021 | D132: S1 | N132: =IF(A132="","",COUNT(H132:M132)/6) | O132: =IF(COUNT(H132:M132)=0,"",IF(LEN(IF(COUNT(I132,J132)=2,IF(J132>I132+1,"EBE > VA ",""),"")&IF(COUNT(H132,M132)=2,IF(ABS(M132)>ABS(H132),"RN > CA ",""),"")&IF(COUNT(H132,K132)=2,IF(ABS(K132)>ABS(H132),"RE > CA ",""),""))=0,"OK",IF(COUNT(I132,J132)=2,IF(J132>I132+1,"EBE > VA ",""),"")&IF(COUNT(H132,M132)=2,IF(ABS(M132)>ABS(H132),"RN > CA ",""),"")&IF(COUNT(H132,K132)=2,IF(ABS(K132)>ABS(H132),"RE > CA ",""),""))) | P132: =IF(OR($A132="",H132="",$C132=""),"",IF(COUNTIFS($A$5:$A$639,$A132,$C$5:$C$639,$C132-1,$D$5:$D$639,$D132,H$5:H$639,"<>")=0,"",IF(OR(SUMIFS(H$5:H$639,$A$5:$A$639,$A132,$C$5:$C$639,$C132-1,$D$5:$D$639,$D132)=0,H132*SUMIFS(H$5:H$639,$A$5:$A$639,$A132,$C$5:$C$639,$C132-1,$D$5:$D$639,$D132)<0),"n.s.",ABS(H132)/ABS(SUMIFS(H$5:H$639,$A$5:$A$639,$A132,$C$5:$C$639,$C132-1,$D$5:$D$639,$D132))-1))) | Q132: =IF(OR($A132="",I132="",$C132=""),"",IF(COUNTIFS($A$5:$A$639,$A132,$C$5:$C$639,$C132-1,$D$5:$D$639,$D132,I$5:I$639,"<>")=0,"",IF(OR(SUMIFS(I$5:I$639,$A$5:$A$639,$A132,$C$5:$C$639,$C132-1,$D$5:$D$639,$D132)=0,I132*SUMIFS(I$5:I$639,$A$5:$A$639,$A132,$C$5:$C$639,$C132-1,$D$5:$D$639,$D132)<0),"n.s.",ABS(I132)/ABS(SUMIFS(I$5:I$639,$A$5:$A$639,$A132,$C$5:$C$639,$C132-1,$D$5:$D$639,$D132))-1))) | R132: =IF(OR($A132="",J132="",$C132=""),"",IF(COUNTIFS($A$5:$A$639,$A132,$C$5:$C$639,$C132-1,$D$5:$D$639,$D132,J$5:J$639,"<>")=0,"",IF(OR(SUMIFS(J$5:J$639,$A$5:$A$639,$A132,$C$5:$C$639,$C132-1,$D$5:$D$639,$D132)=0,J132*SUMIFS(J$5:J$639,$A$5:$A$639,$A132,$C$5:$C$639,$C132-1,$D$5:$D$639,$D132)<0),"n.s.",ABS(J132)/ABS(SUMIFS(J$5:J$639,$A$5:$A$639,$A132,$C$5:$C$639,$C132-1,$D$5:$D$639,$D132))-1))) | S132: =IF(OR($A132="",K132="",$C132=""),"",IF(COUNTIFS($A$5:$A$639,$A132,$C$5:$C$639,$C132-1,$D$5:$D$639,$D132,K$5:K$639,"<>")=0,"",IF(OR(SUMIFS(K$5:K$639,$A$5:$A$639,$A132,$C$5:$C$639,$C132-1,$D$5:$D$639,$D132)=0,K132*SUMIFS(K$5:K$639,$A$5:$A$639,$A132,$C$5:$C$639,$C132-1,$D$5:$D$639,$D132)<0),"n.s.",ABS(K132)/ABS(SUMIFS(K$5:K$639,$A$5:$A$639,$A132,$C$5:$C$639,$C132-1,$D$5:$D$639,$D132))-1))) | T132: =IF(OR($A132="",L132="",$C132=""),"",IF(COUNTIFS($A$5:$A$639,$A132,$C$5:$C$639,$C132-1,$D$5:$D$639,$D132,L$5:L$639,"<>")=0,"",IF(OR(SUMIFS(L$5:L$639,$A$5:$A$639,$A132,$C$5:$C$639,$C132-1,$D$5:$D$639,$D132)=0,L132*SUMIFS(L$5:L$639,$A$5:$A$639,$A132,$C$5:$C$639,$C132-1,$D$5:$D$639,$D132)<0),"n.s.",ABS(L132)/ABS(SUMIFS(L$5:L$639,$A$5:$A$639,$A132,$C$5:$C$639,$C132-1,$D$5:$D$639,$D132))-1))) | U132: =IF(OR($A132="",M132="",$C132=""),"",IF(COUNTIFS($A$5:$A$639,$A132,$C$5:$C$639,$C132-1,$D$5:$D$639,$D132,M$5:M$639,"<>")=0,"",IF(OR(SUMIFS(M$5:M$639,$A$5:$A$639,$A132,$C$5:$C$639,$C132-1,$D$5:$D$639,$D132)=0,M132*SUMIFS(M$5:M$639,$A$5:$A$639,$A132,$C$5:$C$639,$C132-1,$D$5:$D$639,$D132)<0),"n.s.",ABS(M132)/ABS(SUMIFS(M$5:M$639,$A$5:$A$639,$A132,$C$5:$C$639,$C132-1,$D$5:$D$639,$D132))-1)))
A133: STBC | B133: =IF(A133="","",IFERROR(VLOOKUP(A133,Titres!$A$2:$B$400,2,FALSE),"Ticker inconnu")) | C133: 2021 | D133: T3 | N133: =IF(A133="","",COUNT(H133:M133)/6) | O133: =IF(COUNT(H133:M133)=0,"",IF(LEN(IF(COUNT(I133,J133)=2,IF(J133>I133+1,"EBE > VA ",""),"")&IF(COUNT(H133,M133)=2,IF(ABS(M133)>ABS(H133),"RN > CA ",""),"")&IF(COUNT(H133,K133)=2,IF(ABS(K133)>ABS(H133),"RE > CA ",""),""))=0,"OK",IF(COUNT(I133,J133)=2,IF(J133>I133+1,"EBE > VA ",""),"")&IF(COUNT(H133,M133)=2,IF(ABS(M133)>ABS(H133),"RN > CA ",""),"")&IF(COUNT(H133,K133)=2,IF(ABS(K133)>ABS(H133),"RE > CA ",""),""))) | P133: =IF(OR($A133="",H133="",$C133=""),"",IF(COUNTIFS($A$5:$A$639,$A133,$C$5:$C$639,$C133-1,$D$5:$D$639,$D133,H$5:H$639,"<>")=0,"",IF(OR(SUMIFS(H$5:H$639,$A$5:$A$639,$A133,$C$5:$C$639,$C133-1,$D$5:$D$639,$D133)=0,H133*SUMIFS(H$5:H$639,$A$5:$A$639,$A133,$C$5:$C$639,$C133-1,$D$5:$D$639,$D133)<0),"n.s.",ABS(H133)/ABS(SUMIFS(H$5:H$639,$A$5:$A$639,$A133,$C$5:$C$639,$C133-1,$D$5:$D$639,$D133))-1))) | Q133: =IF(OR($A133="",I133="",$C133=""),"",IF(COUNTIFS($A$5:$A$639,$A133,$C$5:$C$639,$C133-1,$D$5:$D$639,$D133,I$5:I$639,"<>")=0,"",IF(OR(SUMIFS(I$5:I$639,$A$5:$A$639,$A133,$C$5:$C$639,$C133-1,$D$5:$D$639,$D133)=0,I133*SUMIFS(I$5:I$639,$A$5:$A$639,$A133,$C$5:$C$639,$C133-1,$D$5:$D$639,$D133)<0),"n.s.",ABS(I133)/ABS(SUMIFS(I$5:I$639,$A$5:$A$639,$A133,$C$5:$C$639,$C133-1,$D$5:$D$639,$D133))-1))) | R133: =IF(OR($A133="",J133="",$C133=""),"",IF(COUNTIFS($A$5:$A$639,$A133,$C$5:$C$639,$C133-1,$D$5:$D$639,$D133,J$5:J$639,"<>")=0,"",IF(OR(SUMIFS(J$5:J$639,$A$5:$A$639,$A133,$C$5:$C$639,$C133-1,$D$5:$D$639,$D133)=0,J133*SUMIFS(J$5:J$639,$A$5:$A$639,$A133,$C$5:$C$639,$C133-1,$D$5:$D$639,$D133)<0),"n.s.",ABS(J133)/ABS(SUMIFS(J$5:J$639,$A$5:$A$639,$A133,$C$5:$C$639,$C133-1,$D$5:$D$639,$D133))-1))) | S133: =IF(OR($A133="",K133="",$C133=""),"",IF(COUNTIFS($A$5:$A$639,$A133,$C$5:$C$639,$C133-1,$D$5:$D$639,$D133,K$5:K$639,"<>")=0,"",IF(OR(SUMIFS(K$5:K$639,$A$5:$A$639,$A133,$C$5:$C$639,$C133-1,$D$5:$D$639,$D133)=0,K133*SUMIFS(K$5:K$639,$A$5:$A$639,$A133,$C$5:$C$639,$C133-1,$D$5:$D$639,$D133)<0),"n.s.",ABS(K133)/ABS(SUMIFS(K$5:K$639,$A$5:$A$639,$A133,$C$5:$C$639,$C133-1,$D$5:$D$639,$D133))-1))) | T133: =IF(OR($A133="",L133="",$C133=""),"",IF(COUNTIFS($A$5:$A$639,$A133,$C$5:$C$639,$C133-1,$D$5:$D$639,$D133,L$5:L$639,"<>")=0,"",IF(OR(SUMIFS(L$5:L$639,$A$5:$A$639,$A133,$C$5:$C$639,$C133-1,$D$5:$D$639,$D133)=0,L133*SUMIFS(L$5:L$639,$A$5:$A$639,$A133,$C$5:$C$639,$C133-1,$D$5:$D$639,$D133)<0),"n.s.",ABS(L133)/ABS(SUMIFS(L$5:L$639,$A$5:$A$639,$A133,$C$5:$C$639,$C133-1,$D$5:$D$639,$D133))-1))) | U133: =IF(OR($A133="",M133="",$C133=""),"",IF(COUNTIFS($A$5:$A$639,$A133,$C$5:$C$639,$C133-1,$D$5:$D$639,$D133,M$5:M$639,"<>")=0,"",IF(OR(SUMIFS(M$5:M$639,$A$5:$A$639,$A133,$C$5:$C$639,$C133-1,$D$5:$D$639,$D133)=0,M133*SUMIFS(M$5:M$639,$A$5:$A$639,$A133,$C$5:$C$639,$C133-1,$D$5:$D$639,$D133)<0),"n.s.",ABS(M133)/ABS(SUMIFS(M$5:M$639,$A$5:$A$639,$A133,$C$5:$C$639,$C133-1,$D$5:$D$639,$D133))-1)))
A134: STBC | B134: =IF(A134="","",IFERROR(VLOOKUP(A134,Titres!$A$2:$B$400,2,FALSE),"Ticker inconnu")) | C134: 2022 | D134: T1 | N134: =IF(A134="","",COUNT(H134:M134)/6) | O134: =IF(COUNT(H134:M134)=0,"",IF(LEN(IF(COUNT(I134,J134)=2,IF(J134>I134+1,"EBE > VA ",""),"")&IF(COUNT(H134,M134)=2,IF(ABS(M134)>ABS(H134),"RN > CA ",""),"")&IF(COUNT(H134,K134)=2,IF(ABS(K134)>ABS(H134),"RE > CA ",""),""))=0,"OK",IF(COUNT(I134,J134)=2,IF(J134>I134+1,"EBE > VA ",""),"")&IF(COUNT(H134,M134)=2,IF(ABS(M134)>ABS(H134),"RN > CA ",""),"")&IF(COUNT(H134,K134)=2,IF(ABS(K134)>ABS(H134),"RE > CA ",""),""))) | P134: =IF(OR($A134="",H134="",$C134=""),"",IF(COUNTIFS($A$5:$A$639,$A134,$C$5:$C$639,$C134-1,$D$5:$D$639,$D134,H$5:H$639,"<>")=0,"",IF(OR(SUMIFS(H$5:H$639,$A$5:$A$639,$A134,$C$5:$C$639,$C134-1,$D$5:$D$639,$D134)=0,H134*SUMIFS(H$5:H$639,$A$5:$A$639,$A134,$C$5:$C$639,$C134-1,$D$5:$D$639,$D134)<0),"n.s.",ABS(H134)/ABS(SUMIFS(H$5:H$639,$A$5:$A$639,$A134,$C$5:$C$639,$C134-1,$D$5:$D$639,$D134))-1))) | Q134: =IF(OR($A134="",I134="",$C134=""),"",IF(COUNTIFS($A$5:$A$639,$A134,$C$5:$C$639,$C134-1,$D$5:$D$639,$D134,I$5:I$639,"<>")=0,"",IF(OR(SUMIFS(I$5:I$639,$A$5:$A$639,$A134,$C$5:$C$639,$C134-1,$D$5:$D$639,$D134)=0,I134*SUMIFS(I$5:I$639,$A$5:$A$639,$A134,$C$5:$C$639,$C134-1,$D$5:$D$639,$D134)<0),"n.s.",ABS(I134)/ABS(SUMIFS(I$5:I$639,$A$5:$A$639,$A134,$C$5:$C$639,$C134-1,$D$5:$D$639,$D134))-1))) | R134: =IF(OR($A134="",J134="",$C134=""),"",IF(COUNTIFS($A$5:$A$639,$A134,$C$5:$C$639,$C134-1,$D$5:$D$639,$D134,J$5:J$639,"<>")=0,"",IF(OR(SUMIFS(J$5:J$639,$A$5:$A$639,$A134,$C$5:$C$639,$C134-1,$D$5:$D$639,$D134)=0,J134*SUMIFS(J$5:J$639,$A$5:$A$639,$A134,$C$5:$C$639,$C134-1,$D$5:$D$639,$D134)<0),"n.s.",ABS(J134)/ABS(SUMIFS(J$5:J$639,$A$5:$A$639,$A134,$C$5:$C$639,$C134-1,$D$5:$D$639,$D134))-1))) | S134: =IF(OR($A134="",K134="",$C134=""),"",IF(COUNTIFS($A$5:$A$639,$A134,$C$5:$C$639,$C134-1,$D$5:$D$639,$D134,K$5:K$639,"<>")=0,"",IF(OR(SUMIFS(K$5:K$639,$A$5:$A$639,$A134,$C$5:$C$639,$C134-1,$D$5:$D$639,$D134)=0,K134*SUMIFS(K$5:K$639,$A$5:$A$639,$A134,$C$5:$C$639,$C134-1,$D$5:$D$639,$D134)<0),"n.s.",ABS(K134)/ABS(SUMIFS(K$5:K$639,$A$5:$A$639,$A134,$C$5:$C$639,$C134-1,$D$5:$D$639,$D134))-1))) | T134: =IF(OR($A134="",L134="",$C134=""),"",IF(COUNTIFS($A$5:$A$639,$A134,$C$5:$C$639,$C134-1,$D$5:$D$639,$D134,L$5:L$639,"<>")=0,"",IF(OR(SUMIFS(L$5:L$639,$A$5:$A$639,$A134,$C$5:$C$639,$C134-1,$D$5:$D$639,$D134)=0,L134*SUMIFS(L$5:L$639,$A$5:$A$639,$A134,$C$5:$C$639,$C134-1,$D$5:$D$639,$D134)<0),"n.s.",ABS(L134)/ABS(SUMIFS(L$5:L$639,$A$5:$A$639,$A134,$C$5:$C$639,$C134-1,$D$5:$D$639,$D134))-1))) | U134: =IF(OR($A134="",M134="",$C134=""),"",IF(COUNTIFS($A$5:$A$639,$A134,$C$5:$C$639,$C134-1,$D$5:$D$639,$D134,M$5:M$639,"<>")=0,"",IF(OR(SUMIFS(M$5:M$639,$A$5:$A$639,$A134,$C$5:$C$639,$C134-1,$D$5:$D$639,$D134)=0,M134*SUMIFS(M$5:M$639,$A$5:$A$639,$A134,$C$5:$C$639,$C134-1,$D$5:$D$639,$D134)<0),"n.s.",ABS(M134)/ABS(SUMIFS(M$5:M$639,$A$5:$A$639,$A134,$C$5:$C$639,$C134-1,$D$5:$D$639,$D134))-1)))
A135: STBC | B135: =IF(A135="","",IFERROR(VLOOKUP(A135,Titres!$A$2:$B$400,2,FALSE),"Ticker inconnu")) | C135: 2022 | D135: S1 | N135: =IF(A135="","",COUNT(H135:M135)/6) | O135: =IF(COUNT(H135:M135)=0,"",IF(LEN(IF(COUNT(I135,J135)=2,IF(J135>I135+1,"EBE > VA ",""),"")&IF(COUNT(H135,M135)=2,IF(ABS(M135)>ABS(H135),"RN > CA ",""),"")&IF(COUNT(H135,K135)=2,IF(ABS(K135)>ABS(H135),"RE > CA ",""),""))=0,"OK",IF(COUNT(I135,J135)=2,IF(J135>I135+1,"EBE > VA ",""),"")&IF(COUNT(H135,M135)=2,IF(ABS(M135)>ABS(H135),"RN > CA ",""),"")&IF(COUNT(H135,K135)=2,IF(ABS(K135)>ABS(H135),"RE > CA ",""),""))) | P135: =IF(OR($A135="",H135="",$C135=""),"",IF(COUNTIFS($A$5:$A$639,$A135,$C$5:$C$639,$C135-1,$D$5:$D$639,$D135,H$5:H$639,"<>")=0,"",IF(OR(SUMIFS(H$5:H$639,$A$5:$A$639,$A135,$C$5:$C$639,$C135-1,$D$5:$D$639,$D135)=0,H135*SUMIFS(H$5:H$639,$A$5:$A$639,$A135,$C$5:$C$639,$C135-1,$D$5:$D$639,$D135)<0),"n.s.",ABS(H135)/ABS(SUMIFS(H$5:H$639,$A$5:$A$639,$A135,$C$5:$C$639,$C135-1,$D$5:$D$639,$D135))-1))) | Q135: =IF(OR($A135="",I135="",$C135=""),"",IF(COUNTIFS($A$5:$A$639,$A135,$C$5:$C$639,$C135-1,$D$5:$D$639,$D135,I$5:I$639,"<>")=0,"",IF(OR(SUMIFS(I$5:I$639,$A$5:$A$639,$A135,$C$5:$C$639,$C135-1,$D$5:$D$639,$D135)=0,I135*SUMIFS(I$5:I$639,$A$5:$A$639,$A135,$C$5:$C$639,$C135-1,$D$5:$D$639,$D135)<0),"n.s.",ABS(I135)/ABS(SUMIFS(I$5:I$639,$A$5:$A$639,$A135,$C$5:$C$639,$C135-1,$D$5:$D$639,$D135))-1))) | R135: =IF(OR($A135="",J135="",$C135=""),"",IF(COUNTIFS($A$5:$A$639,$A135,$C$5:$C$639,$C135-1,$D$5:$D$639,$D135,J$5:J$639,"<>")=0,"",IF(OR(SUMIFS(J$5:J$639,$A$5:$A$639,$A135,$C$5:$C$639,$C135-1,$D$5:$D$639,$D135)=0,J135*SUMIFS(J$5:J$639,$A$5:$A$639,$A135,$C$5:$C$639,$C135-1,$D$5:$D$639,$D135)<0),"n.s.",ABS(J135)/ABS(SUMIFS(J$5:J$639,$A$5:$A$639,$A135,$C$5:$C$639,$C135-1,$D$5:$D$639,$D135))-1))) | S135: =IF(OR($A135="",K135="",$C135=""),"",IF(COUNTIFS($A$5:$A$639,$A135,$C$5:$C$639,$C135-1,$D$5:$D$639,$D135,K$5:K$639,"<>")=0,"",IF(OR(SUMIFS(K$5:K$639,$A$5:$A$639,$A135,$C$5:$C$639,$C135-1,$D$5:$D$639,$D135)=0,K135*SUMIFS(K$5:K$639,$A$5:$A$639,$A135,$C$5:$C$639,$C135-1,$D$5:$D$639,$D135)<0),"n.s.",ABS(K135)/ABS(SUMIFS(K$5:K$639,$A$5:$A$639,$A135,$C$5:$C$639,$C135-1,$D$5:$D$639,$D135))-1))) | T135: =IF(OR($A135="",L135="",$C135=""),"",IF(COUNTIFS($A$5:$A$639,$A135,$C$5:$C$639,$C135-1,$D$5:$D$639,$D135,L$5:L$639,"<>")=0,"",IF(OR(SUMIFS(L$5:L$639,$A$5:$A$639,$A135,$C$5:$C$639,$C135-1,$D$5:$D$639,$D135)=0,L135*SUMIFS(L$5:L$639,$A$5:$A$639,$A135,$C$5:$C$639,$C135-1,$D$5:$D$639,$D135)<0),"n.s.",ABS(L135)/ABS(SUMIFS(L$5:L$639,$A$5:$A$639,$A135,$C$5:$C$639,$C135-1,$D$5:$D$639,$D135))-1))) | U135: =IF(OR($A135="",M135="",$C135=""),"",IF(COUNTIFS($A$5:$A$639,$A135,$C$5:$C$639,$C135-1,$D$5:$D$639,$D135,M$5:M$639,"<>")=0,"",IF(OR(SUMIFS(M$5:M$639,$A$5:$A$639,$A135,$C$5:$C$639,$C135-1,$D$5:$D$639,$D135)=0,M135*SUMIFS(M$5:M$639,$A$5:$A$639,$A135,$C$5:$C$639,$C135-1,$D$5:$D$639,$D135)<0),"n.s.",ABS(M135)/ABS(SUMIFS(M$5:M$639,$A$5:$A$639,$A135,$C$5:$C$639,$C135-1,$D$5:$D$639,$D135))-1)))
A136: STBC | B136: =IF(A136="","",IFERROR(VLOOKUP(A136,Titres!$A$2:$B$400,2,FALSE),"Ticker inconnu")) | C136: 2022 | D136: T3 | N136: =IF(A136="","",COUNT(H136:M136)/6) | O136: =IF(COUNT(H136:M136)=0,"",IF(LEN(IF(COUNT(I136,J136)=2,IF(J136>I136+1,"EBE > VA ",""),"")&IF(COUNT(H136,M136)=2,IF(ABS(M136)>ABS(H136),"RN > CA ",""),"")&IF(COUNT(H136,K136)=2,IF(ABS(K136)>ABS(H136),"RE > CA ",""),""))=0,"OK",IF(COUNT(I136,J136)=2,IF(J136>I136+1,"EBE > VA ",""),"")&IF(COUNT(H136,M136)=2,IF(ABS(M136)>ABS(H136),"RN > CA ",""),"")&IF(COUNT(H136,K136)=2,IF(ABS(K136)>ABS(H136),"RE > CA ",""),""))) | P136: =IF(OR($A136="",H136="",$C136=""),"",IF(COUNTIFS($A$5:$A$639,$A136,$C$5:$C$639,$C136-1,$D$5:$D$639,$D136,H$5:H$639,"<>")=0,"",IF(OR(SUMIFS(H$5:H$639,$A$5:$A$639,$A136,$C$5:$C$639,$C136-1,$D$5:$D$639,$D136)=0,H136*SUMIFS(H$5:H$639,$A$5:$A$639,$A136,$C$5:$C$639,$C136-1,$D$5:$D$639,$D136)<0),"n.s.",ABS(H136)/ABS(SUMIFS(H$5:H$639,$A$5:$A$639,$A136,$C$5:$C$639,$C136-1,$D$5:$D$639,$D136))-1))) | Q136: =IF(OR($A136="",I136="",$C136=""),"",IF(COUNTIFS($A$5:$A$639,$A136,$C$5:$C$639,$C136-1,$D$5:$D$639,$D136,I$5:I$639,"<>")=0,"",IF(OR(SUMIFS(I$5:I$639,$A$5:$A$639,$A136,$C$5:$C$639,$C136-1,$D$5:$D$639,$D136)=0,I136*SUMIFS(I$5:I$639,$A$5:$A$639,$A136,$C$5:$C$639,$C136-1,$D$5:$D$639,$D136)<0),"n.s.",ABS(I136)/ABS(SUMIFS(I$5:I$639,$A$5:$A$639,$A136,$C$5:$C$639,$C136-1,$D$5:$D$639,$D136))-1))) | R136: =IF(OR($A136="",J136="",$C136=""),"",IF(COUNTIFS($A$5:$A$639,$A136,$C$5:$C$639,$C136-1,$D$5:$D$639,$D136,J$5:J$639,"<>")=0,"",IF(OR(SUMIFS(J$5:J$639,$A$5:$A$639,$A136,$C$5:$C$639,$C136-1,$D$5:$D$639,$D136)=0,J136*SUMIFS(J$5:J$639,$A$5:$A$639,$A136,$C$5:$C$639,$C136-1,$D$5:$D$639,$D136)<0),"n.s.",ABS(J136)/ABS(SUMIFS(J$5:J$639,$A$5:$A$639,$A136,$C$5:$C$639,$C136-1,$D$5:$D$639,$D136))-1))) | S136: =IF(OR($A136="",K136="",$C136=""),"",IF(COUNTIFS($A$5:$A$639,$A136,$C$5:$C$639,$C136-1,$D$5:$D$639,$D136,K$5:K$639,"<>")=0,"",IF(OR(SUMIFS(K$5:K$639,$A$5:$A$639,$A136,$C$5:$C$639,$C136-1,$D$5:$D$639,$D136)=0,K136*SUMIFS(K$5:K$639,$A$5:$A$639,$A136,$C$5:$C$639,$C136-1,$D$5:$D$639,$D136)<0),"n.s.",ABS(K136)/ABS(SUMIFS(K$5:K$639,$A$5:$A$639,$A136,$C$5:$C$639,$C136-1,$D$5:$D$639,$D136))-1))) | T136: =IF(OR($A136="",L136="",$C136=""),"",IF(COUNTIFS($A$5:$A$639,$A136,$C$5:$C$639,$C136-1,$D$5:$D$639,$D136,L$5:L$639,"<>")=0,"",IF(OR(SUMIFS(L$5:L$639,$A$5:$A$639,$A136,$C$5:$C$639,$C136-1,$D$5:$D$639,$D136)=0,L136*SUMIFS(L$5:L$639,$A$5:$A$639,$A136,$C$5:$C$639,$C136-1,$D$5:$D$639,$D136)<0),"n.s.",ABS(L136)/ABS(SUMIFS(L$5:L$639,$A$5:$A$639,$A136,$C$5:$C$639,$C136-1,$D$5:$D$639,$D136))-1))) | U136: =IF(OR($A136="",M136="",$C136=""),"",IF(COUNTIFS($A$5:$A$639,$A136,$C$5:$C$639,$C136-1,$D$5:$D$639,$D136,M$5:M$639,"<>")=0,"",IF(OR(SUMIFS(M$5:M$639,$A$5:$A$639,$A136,$C$5:$C$639,$C136-1,$D$5:$D$639,$D136)=0,M136*SUMIFS(M$5:M$639,$A$5:$A$639,$A136,$C$5:$C$639,$C136-1,$D$5:$D$639,$D136)<0),"n.s.",ABS(M136)/ABS(SUMIFS(M$5:M$639,$A$5:$A$639,$A136,$C$5:$C$639,$C136-1,$D$5:$D$639,$D136))-1)))
A137: STBC | B137: =IF(A137="","",IFERROR(VLOOKUP(A137,Titres!$A$2:$B$400,2,FALSE),"Ticker inconnu")) | C137: 2023 | D137: T1 | N137: =IF(A137="","",COUNT(H137:M137)/6) | O137: =IF(COUNT(H137:M137)=0,"",IF(LEN(IF(COUNT(I137,J137)=2,IF(J137>I137+1,"EBE > VA ",""),"")&IF(COUNT(H137,M137)=2,IF(ABS(M137)>ABS(H137),"RN > CA ",""),"")&IF(COUNT(H137,K137)=2,IF(ABS(K137)>ABS(H137),"RE > CA ",""),""))=0,"OK",IF(COUNT(I137,J137)=2,IF(J137>I137+1,"EBE > VA ",""),"")&IF(COUNT(H137,M137)=2,IF(ABS(M137)>ABS(H137),"RN > CA ",""),"")&IF(COUNT(H137,K137)=2,IF(ABS(K137)>ABS(H137),"RE > CA ",""),""))) | P137: =IF(OR($A137="",H137="",$C137=""),"",IF(COUNTIFS($A$5:$A$639,$A137,$C$5:$C$639,$C137-1,$D$5:$D$639,$D137,H$5:H$639,"<>")=0,"",IF(OR(SUMIFS(H$5:H$639,$A$5:$A$639,$A137,$C$5:$C$639,$C137-1,$D$5:$D$639,$D137)=0,H137*SUMIFS(H$5:H$639,$A$5:$A$639,$A137,$C$5:$C$639,$C137-1,$D$5:$D$639,$D137)<0),"n.s.",ABS(H137)/ABS(SUMIFS(H$5:H$639,$A$5:$A$639,$A137,$C$5:$C$639,$C137-1,$D$5:$D$639,$D137))-1))) | Q137: =IF(OR($A137="",I137="",$C137=""),"",IF(COUNTIFS($A$5:$A$639,$A137,$C$5:$C$639,$C137-1,$D$5:$D$639,$D137,I$5:I$639,"<>")=0,"",IF(OR(SUMIFS(I$5:I$639,$A$5:$A$639,$A137,$C$5:$C$639,$C137-1,$D$5:$D$639,$D137)=0,I137*SUMIFS(I$5:I$639,$A$5:$A$639,$A137,$C$5:$C$639,$C137-1,$D$5:$D$639,$D137)<0),"n.s.",ABS(I137)/ABS(SUMIFS(I$5:I$639,$A$5:$A$639,$A137,$C$5:$C$639,$C137-1,$D$5:$D$639,$D137))-1))) | R137: =IF(OR($A137="",J137="",$C137=""),"",IF(COUNTIFS($A$5:$A$639,$A137,$C$5:$C$639,$C137-1,$D$5:$D$639,$D137,J$5:J$639,"<>")=0,"",IF(OR(SUMIFS(J$5:J$639,$A$5:$A$639,$A137,$C$5:$C$639,$C137-1,$D$5:$D$639,$D137)=0,J137*SUMIFS(J$5:J$639,$A$5:$A$639,$A137,$C$5:$C$639,$C137-1,$D$5:$D$639,$D137)<0),"n.s.",ABS(J137)/ABS(SUMIFS(J$5:J$639,$A$5:$A$639,$A137,$C$5:$C$639,$C137-1,$D$5:$D$639,$D137))-1))) | S137: =IF(OR($A137="",K137="",$C137=""),"",IF(COUNTIFS($A$5:$A$639,$A137,$C$5:$C$639,$C137-1,$D$5:$D$639,$D137,K$5:K$639,"<>")=0,"",IF(OR(SUMIFS(K$5:K$639,$A$5:$A$639,$A137,$C$5:$C$639,$C137-1,$D$5:$D$639,$D137)=0,K137*SUMIFS(K$5:K$639,$A$5:$A$639,$A137,$C$5:$C$639,$C137-1,$D$5:$D$639,$D137)<0),"n.s.",ABS(K137)/ABS(SUMIFS(K$5:K$639,$A$5:$A$639,$A137,$C$5:$C$639,$C137-1,$D$5:$D$639,$D137))-1))) | T137: =IF(OR($A137="",L137="",$C137=""),"",IF(COUNTIFS($A$5:$A$639,$A137,$C$5:$C$639,$C137-1,$D$5:$D$639,$D137,L$5:L$639,"<>")=0,"",IF(OR(SUMIFS(L$5:L$639,$A$5:$A$639,$A137,$C$5:$C$639,$C137-1,$D$5:$D$639,$D137)=0,L137*SUMIFS(L$5:L$639,$A$5:$A$639,$A137,$C$5:$C$639,$C137-1,$D$5:$D$639,$D137)<0),"n.s.",ABS(L137)/ABS(SUMIFS(L$5:L$639,$A$5:$A$639,$A137,$C$5:$C$639,$C137-1,$D$5:$D$639,$D137))-1))) | U137: =IF(OR($A137="",M137="",$C137=""),"",IF(COUNTIFS($A$5:$A$639,$A137,$C$5:$C$639,$C137-1,$D$5:$D$639,$D137,M$5:M$639,"<>")=0,"",IF(OR(SUMIFS(M$5:M$639,$A$5:$A$639,$A137,$C$5:$C$639,$C137-1,$D$5:$D$639,$D137)=0,M137*SUMIFS(M$5:M$639,$A$5:$A$639,$A137,$C$5:$C$639,$C137-1,$D$5:$D$639,$D137)<0),"n.s.",ABS(M137)/ABS(SUMIFS(M$5:M$639,$A$5:$A$639,$A137,$C$5:$C$639,$C137-1,$D$5:$D$639,$D137))-1)))
A138: STBC | B138: =IF(A138="","",IFERROR(VLOOKUP(A138,Titres!$A$2:$B$400,2,FALSE),"Ticker inconnu")) | C138: 2023 | D138: S1 | N138: =IF(A138="","",COUNT(H138:M138)/6) | O138: =IF(COUNT(H138:M138)=0,"",IF(LEN(IF(COUNT(I138,J138)=2,IF(J138>I138+1,"EBE > VA ",""),"")&IF(COUNT(H138,M138)=2,IF(ABS(M138)>ABS(H138),"RN > CA ",""),"")&IF(COUNT(H138,K138)=2,IF(ABS(K138)>ABS(H138),"RE > CA ",""),""))=0,"OK",IF(COUNT(I138,J138)=2,IF(J138>I138+1,"EBE > VA ",""),"")&IF(COUNT(H138,M138)=2,IF(ABS(M138)>ABS(H138),"RN > CA ",""),"")&IF(COUNT(H138,K138)=2,IF(ABS(K138)>ABS(H138),"RE > CA ",""),""))) | P138: =IF(OR($A138="",H138="",$C138=""),"",IF(COUNTIFS($A$5:$A$639,$A138,$C$5:$C$639,$C138-1,$D$5:$D$639,$D138,H$5:H$639,"<>")=0,"",IF(OR(SUMIFS(H$5:H$639,$A$5:$A$639,$A138,$C$5:$C$639,$C138-1,$D$5:$D$639,$D138)=0,H138*SUMIFS(H$5:H$639,$A$5:$A$639,$A138,$C$5:$C$639,$C138-1,$D$5:$D$639,$D138)<0),"n.s.",ABS(H138)/ABS(SUMIFS(H$5:H$639,$A$5:$A$639,$A138,$C$5:$C$639,$C138-1,$D$5:$D$639,$D138))-1))) | Q138: =IF(OR($A138="",I138="",$C138=""),"",IF(COUNTIFS($A$5:$A$639,$A138,$C$5:$C$639,$C138-1,$D$5:$D$639,$D138,I$5:I$639,"<>")=0,"",IF(OR(SUMIFS(I$5:I$639,$A$5:$A$639,$A138,$C$5:$C$639,$C138-1,$D$5:$D$639,$D138)=0,I138*SUMIFS(I$5:I$639,$A$5:$A$639,$A138,$C$5:$C$639,$C138-1,$D$5:$D$639,$D138)<0),"n.s.",ABS(I138)/ABS(SUMIFS(I$5:I$639,$A$5:$A$639,$A138,$C$5:$C$639,$C138-1,$D$5:$D$639,$D138))-1))) | R138: =IF(OR($A138="",J138="",$C138=""),"",IF(COUNTIFS($A$5:$A$639,$A138,$C$5:$C$639,$C138-1,$D$5:$D$639,$D138,J$5:J$639,"<>")=0,"",IF(OR(SUMIFS(J$5:J$639,$A$5:$A$639,$A138,$C$5:$C$639,$C138-1,$D$5:$D$639,$D138)=0,J138*SUMIFS(J$5:J$639,$A$5:$A$639,$A138,$C$5:$C$639,$C138-1,$D$5:$D$639,$D138)<0),"n.s.",ABS(J138)/ABS(SUMIFS(J$5:J$639,$A$5:$A$639,$A138,$C$5:$C$639,$C138-1,$D$5:$D$639,$D138))-1))) | S138: =IF(OR($A138="",K138="",$C138=""),"",IF(COUNTIFS($A$5:$A$639,$A138,$C$5:$C$639,$C138-1,$D$5:$D$639,$D138,K$5:K$639,"<>")=0,"",IF(OR(SUMIFS(K$5:K$639,$A$5:$A$639,$A138,$C$5:$C$639,$C138-1,$D$5:$D$639,$D138)=0,K138*SUMIFS(K$5:K$639,$A$5:$A$639,$A138,$C$5:$C$639,$C138-1,$D$5:$D$639,$D138)<0),"n.s.",ABS(K138)/ABS(SUMIFS(K$5:K$639,$A$5:$A$639,$A138,$C$5:$C$639,$C138-1,$D$5:$D$639,$D138))-1))) | T138: =IF(OR($A138="",L138="",$C138=""),"",IF(COUNTIFS($A$5:$A$639,$A138,$C$5:$C$639,$C138-1,$D$5:$D$639,$D138,L$5:L$639,"<>")=0,"",IF(OR(SUMIFS(L$5:L$639,$A$5:$A$639,$A138,$C$5:$C$639,$C138-1,$D$5:$D$639,$D138)=0,L138*SUMIFS(L$5:L$639,$A$5:$A$639,$A138,$C$5:$C$639,$C138-1,$D$5:$D$639,$D138)<0),"n.s.",ABS(L138)/ABS(SUMIFS(L$5:L$639,$A$5:$A$639,$A138,$C$5:$C$639,$C138-1,$D$5:$D$639,$D138))-1))) | U138: =IF(OR($A138="",M138="",$C138=""),"",IF(COUNTIFS($A$5:$A$639,$A138,$C$5:$C$639,$C138-1,$D$5:$D$639,$D138,M$5:M$639,"<>")=0,"",IF(OR(SUMIFS(M$5:M$639,$A$5:$A$639,$A138,$C$5:$C$639,$C138-1,$D$5:$D$639,$D138)=0,M138*SUMIFS(M$5:M$639,$A$5:$A$639,$A138,$C$5:$C$639,$C138-1,$D$5:$D$639,$D138)<0),"n.s.",ABS(M138)/ABS(SUMIFS(M$5:M$639,$A$5:$A$639,$A138,$C$5:$C$639,$C138-1,$D$5:$D$639,$D138))-1)))
A139: STBC | B139: =IF(A139="","",IFERROR(VLOOKUP(A139,Titres!$A$2:$B$400,2,FALSE),"Ticker inconnu")) | C139: 2023 | D139: T3 | N139: =IF(A139="","",COUNT(H139:M139)/6) | O139: =IF(COUNT(H139:M139)=0,"",IF(LEN(IF(COUNT(I139,J139)=2,IF(J139>I139+1,"EBE > VA ",""),"")&IF(COUNT(H139,M139)=2,IF(ABS(M139)>ABS(H139),"RN > CA ",""),"")&IF(COUNT(H139,K139)=2,IF(ABS(K139)>ABS(H139),"RE > CA ",""),""))=0,"OK",IF(COUNT(I139,J139)=2,IF(J139>I139+1,"EBE > VA ",""),"")&IF(COUNT(H139,M139)=2,IF(ABS(M139)>ABS(H139),"RN > CA ",""),"")&IF(COUNT(H139,K139)=2,IF(ABS(K139)>ABS(H139),"RE > CA ",""),""))) | P139: =IF(OR($A139="",H139="",$C139=""),"",IF(COUNTIFS($A$5:$A$639,$A139,$C$5:$C$639,$C139-1,$D$5:$D$639,$D139,H$5:H$639,"<>")=0,"",IF(OR(SUMIFS(H$5:H$639,$A$5:$A$639,$A139,$C$5:$C$639,$C139-1,$D$5:$D$639,$D139)=0,H139*SUMIFS(H$5:H$639,$A$5:$A$639,$A139,$C$5:$C$639,$C139-1,$D$5:$D$639,$D139)<0),"n.s.",ABS(H139)/ABS(SUMIFS(H$5:H$639,$A$5:$A$639,$A139,$C$5:$C$639,$C139-1,$D$5:$D$639,$D139))-1))) | Q139: =IF(OR($A139="",I139="",$C139=""),"",IF(COUNTIFS($A$5:$A$639,$A139,$C$5:$C$639,$C139-1,$D$5:$D$639,$D139,I$5:I$639,"<>")=0,"",IF(OR(SUMIFS(I$5:I$639,$A$5:$A$639,$A139,$C$5:$C$639,$C139-1,$D$5:$D$639,$D139)=0,I139*SUMIFS(I$5:I$639,$A$5:$A$639,$A139,$C$5:$C$639,$C139-1,$D$5:$D$639,$D139)<0),"n.s.",ABS(I139)/ABS(SUMIFS(I$5:I$639,$A$5:$A$639,$A139,$C$5:$C$639,$C139-1,$D$5:$D$639,$D139))-1))) | R139: =IF(OR($A139="",J139="",$C139=""),"",IF(COUNTIFS($A$5:$A$639,$A139,$C$5:$C$639,$C139-1,$D$5:$D$639,$D139,J$5:J$639,"<>")=0,"",IF(OR(SUMIFS(J$5:J$639,$A$5:$A$639,$A139,$C$5:$C$639,$C139-1,$D$5:$D$639,$D139)=0,J139*SUMIFS(J$5:J$639,$A$5:$A$639,$A139,$C$5:$C$639,$C139-1,$D$5:$D$639,$D139)<0),"n.s.",ABS(J139)/ABS(SUMIFS(J$5:J$639,$A$5:$A$639,$A139,$C$5:$C$639,$C139-1,$D$5:$D$639,$D139))-1))) | S139: =IF(OR($A139="",K139="",$C139=""),"",IF(COUNTIFS($A$5:$A$639,$A139,$C$5:$C$639,$C139-1,$D$5:$D$639,$D139,K$5:K$639,"<>")=0,"",IF(OR(SUMIFS(K$5:K$639,$A$5:$A$639,$A139,$C$5:$C$639,$C139-1,$D$5:$D$639,$D139)=0,K139*SUMIFS(K$5:K$639,$A$5:$A$639,$A139,$C$5:$C$639,$C139-1,$D$5:$D$639,$D139)<0),"n.s.",ABS(K139)/ABS(SUMIFS(K$5:K$639,$A$5:$A$639,$A139,$C$5:$C$639,$C139-1,$D$5:$D$639,$D139))-1))) | T139: =IF(OR($A139="",L139="",$C139=""),"",IF(COUNTIFS($A$5:$A$639,$A139,$C$5:$C$639,$C139-1,$D$5:$D$639,$D139,L$5:L$639,"<>")=0,"",IF(OR(SUMIFS(L$5:L$639,$A$5:$A$639,$A139,$C$5:$C$639,$C139-1,$D$5:$D$639,$D139)=0,L139*SUMIFS(L$5:L$639,$A$5:$A$639,$A139,$C$5:$C$639,$C139-1,$D$5:$D$639,$D139)<0),"n.s.",ABS(L139)/ABS(SUMIFS(L$5:L$639,$A$5:$A$639,$A139,$C$5:$C$639,$C139-1,$D$5:$D$639,$D139))-1))) | U139: =IF(OR($A139="",M139="",$C139=""),"",IF(COUNTIFS($A$5:$A$639,$A139,$C$5:$C$639,$C139-1,$D$5:$D$639,$D139,M$5:M$639,"<>")=0,"",IF(OR(SUMIFS(M$5:M$639,$A$5:$A$639,$A139,$C$5:$C$639,$C139-1,$D$5:$D$639,$D139)=0,M139*SUMIFS(M$5:M$639,$A$5:$A$639,$A139,$C$5:$C$639,$C139-1,$D$5:$D$639,$D139)<0),"n.s.",ABS(M139)/ABS(SUMIFS(M$5:M$639,$A$5:$A$639,$A139,$C$5:$C$639,$C139-1,$D$5:$D$639,$D139))-1)))
A140: STBC | B140: =IF(A140="","",IFERROR(VLOOKUP(A140,Titres!$A$2:$B$400,2,FALSE),"Ticker inconnu")) | C140: 2024 | D140: T1 | N140: =IF(A140="","",COUNT(H140:M140)/6) | O140: =IF(COUNT(H140:M140)=0,"",IF(LEN(IF(COUNT(I140,J140)=2,IF(J140>I140+1,"EBE > VA ",""),"")&IF(COUNT(H140,M140)=2,IF(ABS(M140)>ABS(H140),"RN > CA ",""),"")&IF(COUNT(H140,K140)=2,IF(ABS(K140)>ABS(H140),"RE > CA ",""),""))=0,"OK",IF(COUNT(I140,J140)=2,IF(J140>I140+1,"EBE > VA ",""),"")&IF(COUNT(H140,M140)=2,IF(ABS(M140)>ABS(H140),"RN > CA ",""),"")&IF(COUNT(H140,K140)=2,IF(ABS(K140)>ABS(H140),"RE > CA ",""),""))) | P140: =IF(OR($A140="",H140="",$C140=""),"",IF(COUNTIFS($A$5:$A$639,$A140,$C$5:$C$639,$C140-1,$D$5:$D$639,$D140,H$5:H$639,"<>")=0,"",IF(OR(SUMIFS(H$5:H$639,$A$5:$A$639,$A140,$C$5:$C$639,$C140-1,$D$5:$D$639,$D140)=0,H140*SUMIFS(H$5:H$639,$A$5:$A$639,$A140,$C$5:$C$639,$C140-1,$D$5:$D$639,$D140)<0),"n.s.",ABS(H140)/ABS(SUMIFS(H$5:H$639,$A$5:$A$639,$A140,$C$5:$C$639,$C140-1,$D$5:$D$639,$D140))-1))) | Q140: =IF(OR($A140="",I140="",$C140=""),"",IF(COUNTIFS($A$5:$A$639,$A140,$C$5:$C$639,$C140-1,$D$5:$D$639,$D140,I$5:I$639,"<>")=0,"",IF(OR(SUMIFS(I$5:I$639,$A$5:$A$639,$A140,$C$5:$C$639,$C140-1,$D$5:$D$639,$D140)=0,I140*SUMIFS(I$5:I$639,$A$5:$A$639,$A140,$C$5:$C$639,$C140-1,$D$5:$D$639,$D140)<0),"n.s.",ABS(I140)/ABS(SUMIFS(I$5:I$639,$A$5:$A$639,$A140,$C$5:$C$639,$C140-1,$D$5:$D$639,$D140))-1))) | R140: =IF(OR($A140="",J140="",$C140=""),"",IF(COUNTIFS($A$5:$A$639,$A140,$C$5:$C$639,$C140-1,$D$5:$D$639,$D140,J$5:J$639,"<>")=0,"",IF(OR(SUMIFS(J$5:J$639,$A$5:$A$639,$A140,$C$5:$C$639,$C140-1,$D$5:$D$639,$D140)=0,J140*SUMIFS(J$5:J$639,$A$5:$A$639,$A140,$C$5:$C$639,$C140-1,$D$5:$D$639,$D140)<0),"n.s.",ABS(J140)/ABS(SUMIFS(J$5:J$639,$A$5:$A$639,$A140,$C$5:$C$639,$C140-1,$D$5:$D$639,$D140))-1))) | S140: =IF(OR($A140="",K140="",$C140=""),"",IF(COUNTIFS($A$5:$A$639,$A140,$C$5:$C$639,$C140-1,$D$5:$D$639,$D140,K$5:K$639,"<>")=0,"",IF(OR(SUMIFS(K$5:K$639,$A$5:$A$639,$A140,$C$5:$C$639,$C140-1,$D$5:$D$639,$D140)=0,K140*SUMIFS(K$5:K$639,$A$5:$A$639,$A140,$C$5:$C$639,$C140-1,$D$5:$D$639,$D140)<0),"n.s.",ABS(K140)/ABS(SUMIFS(K$5:K$639,$A$5:$A$639,$A140,$C$5:$C$639,$C140-1,$D$5:$D$639,$D140))-1))) | T140: =IF(OR($A140="",L140="",$C140=""),"",IF(COUNTIFS($A$5:$A$639,$A140,$C$5:$C$639,$C140-1,$D$5:$D$639,$D140,L$5:L$639,"<>")=0,"",IF(OR(SUMIFS(L$5:L$639,$A$5:$A$639,$A140,$C$5:$C$639,$C140-1,$D$5:$D$639,$D140)=0,L140*SUMIFS(L$5:L$639,$A$5:$A$639,$A140,$C$5:$C$639,$C140-1,$D$5:$D$639,$D140)<0),"n.s.",ABS(L140)/ABS(SUMIFS(L$5:L$639,$A$5:$A$639,$A140,$C$5:$C$639,$C140-1,$D$5:$D$639,$D140))-1))) | U140: =IF(OR($A140="",M140="",$C140=""),"",IF(COUNTIFS($A$5:$A$639,$A140,$C$5:$C$639,$C140-1,$D$5:$D$639,$D140,M$5:M$639,"<>")=0,"",IF(OR(SUMIFS(M$5:M$639,$A$5:$A$639,$A140,$C$5:$C$639,$C140-1,$D$5:$D$639,$D140)=0,M140*SUMIFS(M$5:M$639,$A$5:$A$639,$A140,$C$5:$C$639,$C140-1,$D$5:$D$639,$D140)<0),"n.s.",ABS(M140)/ABS(SUMIFS(M$5:M$639,$A$5:$A$639,$A140,$C$5:$C$639,$C140-1,$D$5:$D$639,$D140))-1)))
... A196: BNBC | B196: =IF(A196="","",IFERROR(VLOOKUP(A196,Titres!$A$2:$B$400,2,FALSE),"Ticker inconnu")) | C196: 2024 | D196: T3 | N196: =IF(A196="","",COUNT(H196:M196)/6) | O196: =IF(COUNT(H196:M196)=0,"",IF(LEN(IF(COUNT(I196,J196)=2,IF(J196>I196+1,"EBE > VA ",""),"")&IF(COUNT(H196,M196)=2,IF(ABS(M196)>ABS(H196),"RN > CA ",""),"")&IF(COUNT(H196,K196)=2,IF(ABS(K196)>ABS(H196),"RE > CA ",""),""))=0,"OK",IF(COUNT(I196,J196)=2,IF(J196>I196+1,"EBE > VA ",""),"")&IF(COUNT(H196,M196)=2,IF(ABS(M196)>ABS(H196),"RN > CA ",""),"")&IF(COUNT(H196,K196)=2,IF(ABS(K196)>ABS(H196),"RE > CA ",""),""))) | P196: =IF(OR($A196="",H196="",$C196=""),"",IF(COUNTIFS($A$5:$A$639,$A196,$C$5:$C$639,$C196-1,$D$5:$D$639,$D196,H$5:H$639,"<>")=0,"",IF(OR(SUMIFS(H$5:H$639,$A$5:$A$639,$A196,$C$5:$C$639,$C196-1,$D$5:$D$639,$D196)=0,H196*SUMIFS(H$5:H$639,$A$5:$A$639,$A196,$C$5:$C$639,$C196-1,$D$5:$D$639,$D196)<0),"n.s.",ABS(H196)/ABS(SUMIFS(H$5:H$639,$A$5:$A$639,$A196,$C$5:$C$639,$C196-1,$D$5:$D$639,$D196))-1))) | Q196: =IF(OR($A196="",I196="",$C196=""),"",IF(COUNTIFS($A$5:$A$639,$A196,$C$5:$C$639,$C196-1,$D$5:$D$639,$D196,I$5:I$639,"<>")=0,"",IF(OR(SUMIFS(I$5:I$639,$A$5:$A$639,$A196,$C$5:$C$639,$C196-1,$D$5:$D$639,$D196)=0,I196*SUMIFS(I$5:I$639,$A$5:$A$639,$A196,$C$5:$C$639,$C196-1,$D$5:$D$639,$D196)<0),"n.s.",ABS(I196)/ABS(SUMIFS(I$5:I$639,$A$5:$A$639,$A196,$C$5:$C$639,$C196-1,$D$5:$D$639,$D196))-1))) | R196: =IF(OR($A196="",J196="",$C196=""),"",IF(COUNTIFS($A$5:$A$639,$A196,$C$5:$C$639,$C196-1,$D$5:$D$639,$D196,J$5:J$639,"<>")=0,"",IF(OR(SUMIFS(J$5:J$639,$A$5:$A$639,$A196,$C$5:$C$639,$C196-1,$D$5:$D$639,$D196)=0,J196*SUMIFS(J$5:J$639,$A$5:$A$639,$A196,$C$5:$C$639,$C196-1,$D$5:$D$639,$D196)<0),"n.s.",ABS(J196)/ABS(SUMIFS(J$5:J$639,$A$5:$A$639,$A196,$C$5:$C$639,$C196-1,$D$5:$D$639,$D196))-1))) | S196: =IF(OR($A196="",K196="",$C196=""),"",IF(COUNTIFS($A$5:$A$639,$A196,$C$5:$C$639,$C196-1,$D$5:$D$639,$D196,K$5:K$639,"<>")=0,"",IF(OR(SUMIFS(K$5:K$639,$A$5:$A$639,$A196,$C$5:$C$639,$C196-1,$D$5:$D$639,$D196)=0,K196*SUMIFS(K$5:K$639,$A$5:$A$639,$A196,$C$5:$C$639,$C196-1,$D$5:$D$639,$D196)<0),"n.s.",ABS(K196)/ABS(SUMIFS(K$5:K$639,$A$5:$A$639,$A196,$C$5:$C$639,$C196-1,$D$5:$D$639,$D196))-1))) | T196: =IF(OR($A196="",L196="",$C196=""),"",IF(COUNTIFS($A$5:$A$639,$A196,$C$5:$C$639,$C196-1,$D$5:$D$639,$D196,L$5:L$639,"<>")=0,"",IF(OR(SUMIFS(L$5:L$639,$A$5:$A$639,$A196,$C$5:$C$639,$C196-1,$D$5:$D$639,$D196)=0,L196*SUMIFS(L$5:L$639,$A$5:$A$639,$A196,$C$5:$C$639,$C196-1,$D$5:$D$639,$D196)<0),"n.s.",ABS(L196)/ABS(SUMIFS(L$5:L$639,$A$5:$A$639,$A196,$C$5:$C$639,$C196-1,$D$5:$D$639,$D196))-1))) | U196: =IF(OR($A196="",M196="",$C196=""),"",IF(COUNTIFS($A$5:$A$639,$A196,$C$5:$C$639,$C196-1,$D$5:$D$639,$D196,M$5:M$639,"<>")=0,"",IF(OR(SUMIFS(M$5:M$639,$A$5:$A$639,$A196,$C$5:$C$639,$C196-1,$D$5:$D$639,$D196)=0,M196*SUMIFS(M$5:M$639,$A$5:$A$639,$A196,$C$5:$C$639,$C196-1,$D$5:$D$639,$D196)<0),"n.s.",ABS(M196)/ABS(SUMIFS(M$5:M$639,$A$5:$A$639,$A196,$C$5:$C$639,$C196-1,$D$5:$D$639,$D196))-1)))
A197: BNBC | B197: =IF(A197="","",IFERROR(VLOOKUP(A197,Titres!$A$2:$B$400,2,FALSE),"Ticker inconnu")) | C197: 2025 | D197: T1 | E197: Publié | F197: 46142 | G197: https://www.richbourse.com/common/actualite/afficher-fichier/30-04-2026-bernabe-ci-rapport-dactivites-1er-trimestre-2026 (comparatif N-1) | H197: 11207.24 | L197: -21.53 | M197: -16.147 | N197: =IF(A197="","",COUNT(H197:M197)/6) | O197: =IF(COUNT(H197:M197)=0,"",IF(LEN(IF(COUNT(I197,J197)=2,IF(J197>I197+1,"EBE > VA ",""),"")&IF(COUNT(H197,M197)=2,IF(ABS(M197)>ABS(H197),"RN > CA ",""),"")&IF(COUNT(H197,K197)=2,IF(ABS(K197)>ABS(H197),"RE > CA ",""),""))=0,"OK",IF(COUNT(I197,J197)=2,IF(J197>I197+1,"EBE > VA ",""),"")&IF(COUNT(H197,M197)=2,IF(ABS(M197)>ABS(H197),"RN > CA ",""),"")&IF(COUNT(H197,K197)=2,IF(ABS(K197)>ABS(H197),"RE > CA ",""),""))) | P197: =IF(OR($A197="",H197="",$C197=""),"",IF(COUNTIFS($A$5:$A$639,$A197,$C$5:$C$639,$C197-1,$D$5:$D$639,$D197,H$5:H$639,"<>")=0,"",IF(OR(SUMIFS(H$5:H$639,$A$5:$A$639,$A197,$C$5:$C$639,$C197-1,$D$5:$D$639,$D197)=0,H197*SUMIFS(H$5:H$639,$A$5:$A$639,$A197,$C$5:$C$639,$C197-1,$D$5:$D$639,$D197)<0),"n.s.",ABS(H197)/ABS(SUMIFS(H$5:H$639,$A$5:$A$639,$A197,$C$5:$C$639,$C197-1,$D$5:$D$639,$D197))-1))) | Q197: =IF(OR($A197="",I197="",$C197=""),"",IF(COUNTIFS($A$5:$A$639,$A197,$C$5:$C$639,$C197-1,$D$5:$D$639,$D197,I$5:I$639,"<>")=0,"",IF(OR(SUMIFS(I$5:I$639,$A$5:$A$639,$A197,$C$5:$C$639,$C197-1,$D$5:$D$639,$D197)=0,I197*SUMIFS(I$5:I$639,$A$5:$A$639,$A197,$C$5:$C$639,$C197-1,$D$5:$D$639,$D197)<0),"n.s.",ABS(I197)/ABS(SUMIFS(I$5:I$639,$A$5:$A$639,$A197,$C$5:$C$639,$C197-1,$D$5:$D$639,$D197))-1))) | R197: =IF(OR($A197="",J197="",$C197=""),"",IF(COUNTIFS($A$5:$A$639,$A197,$C$5:$C$639,$C197-1,$D$5:$D$639,$D197,J$5:J$639,"<>")=0,"",IF(OR(SUMIFS(J$5:J$639,$A$5:$A$639,$A197,$C$5:$C$639,$C197-1,$D$5:$D$639,$D197)=0,J197*SUMIFS(J$5:J$639,$A$5:$A$639,$A197,$C$5:$C$639,$C197-1,$D$5:$D$639,$D197)<0),"n.s.",ABS(J197)/ABS(SUMIFS(J$5:J$639,$A$5:$A$639,$A197,$C$5:$C$639,$C197-1,$D$5:$D$639,$D197))-1))) | S197: =IF(OR($A197="",K197="",$C197=""),"",IF(COUNTIFS($A$5:$A$639,$A197,$C$5:$C$639,$C197-1,$D$5:$D$639,$D197,K$5:K$639,"<>")=0,"",IF(OR(SUMIFS(K$5:K$639,$A$5:$A$639,$A197,$C$5:$C$639,$C197-1,$D$5:$D$639,$D197)=0,K197*SUMIFS(K$5:K$639,$A$5:$A$639,$A197,$C$5:$C$639,$C197-1,$D$5:$D$639,$D197)<0),"n.s.",ABS(K197)/ABS(SUMIFS(K$5:K$639,$A$5:$A$639,$A197,$C$5:$C$639,$C197-1,$D$5:$D$639,$D197))-1))) | T197: =IF(OR($A197="",L197="",$C197=""),"",IF(COUNTIFS($A$5:$A$639,$A197,$C$5:$C$639,$C197-1,$D$5:$D$639,$D197,L$5:L$639,"<>")=0,"",IF(OR(SUMIFS(L$5:L$639,$A$5:$A$639,$A197,$C$5:$C$639,$C197-1,$D$5:$D$639,$D197)=0,L197*SUMIFS(L$5:L$639,$A$5:$A$639,$A197,$C$5:$C$639,$C197-1,$D$5:$D$639,$D197)<0),"n.s.",ABS(L197)/ABS(SUMIFS(L$5:L$639,$A$5:$A$639,$A197,$C$5:$C$639,$C197-1,$D$5:$D$639,$D197))-1))) | U197: =IF(OR($A197="",M197="",$C197=""),"",IF(COUNTIFS($A$5:$A$639,$A197,$C$5:$C$639,$C197-1,$D$5:$D$639,$D197,M$5:M$639,"<>")=0,"",IF(OR(SUMIFS(M$5:M$639,$A$5:$A$639,$A197,$C$5:$C$639,$C197-1,$D$5:$D$639,$D197)=0,M197*SUMIFS(M$5:M$639,$A$5:$A$639,$A197,$C$5:$C$639,$C197-1,$D$5:$D$639,$D197)<0),"n.s.",ABS(M197)/ABS(SUMIFS(M$5:M$639,$A$5:$A$639,$A197,$C$5:$C$639,$C197-1,$D$5:$D$639,$D197))-1)))
A198: BNBC | B198: =IF(A198="","",IFERROR(VLOOKUP(A198,Titres!$A$2:$B$400,2,FALSE),"Ticker inconnu")) | C198: 2025 | D198: S1 | N198: =IF(A198="","",COUNT(H198:M198)/6) | O198: =IF(COUNT(H198:M198)=0,"",IF(LEN(IF(COUNT(I198,J198)=2,IF(J198>I198+1,"EBE > VA ",""),"")&IF(COUNT(H198,M198)=2,IF(ABS(M198)>ABS(H198),"RN > CA ",""),"")&IF(COUNT(H198,K198)=2,IF(ABS(K198)>ABS(H198),"RE > CA ",""),""))=0,"OK",IF(COUNT(I198,J198)=2,IF(J198>I198+1,"EBE > VA ",""),"")&IF(COUNT(H198,M198)=2,IF(ABS(M198)>ABS(H198),"RN > CA ",""),"")&IF(COUNT(H198,K198)=2,IF(ABS(K198)>ABS(H198),"RE > CA ",""),""))) | P198: =IF(OR($A198="",H198="",$C198=""),"",IF(COUNTIFS($A$5:$A$639,$A198,$C$5:$C$639,$C198-1,$D$5:$D$639,$D198,H$5:H$639,"<>")=0,"",IF(OR(SUMIFS(H$5:H$639,$A$5:$A$639,$A198,$C$5:$C$639,$C198-1,$D$5:$D$639,$D198)=0,H198*SUMIFS(H$5:H$639,$A$5:$A$639,$A198,$C$5:$C$639,$C198-1,$D$5:$D$639,$D198)<0),"n.s.",ABS(H198)/ABS(SUMIFS(H$5:H$639,$A$5:$A$639,$A198,$C$5:$C$639,$C198-1,$D$5:$D$639,$D198))-1))) | Q198: =IF(OR($A198="",I198="",$C198=""),"",IF(COUNTIFS($A$5:$A$639,$A198,$C$5:$C$639,$C198-1,$D$5:$D$639,$D198,I$5:I$639,"<>")=0,"",IF(OR(SUMIFS(I$5:I$639,$A$5:$A$639,$A198,$C$5:$C$639,$C198-1,$D$5:$D$639,$D198)=0,I198*SUMIFS(I$5:I$639,$A$5:$A$639,$A198,$C$5:$C$639,$C198-1,$D$5:$D$639,$D198)<0),"n.s.",ABS(I198)/ABS(SUMIFS(I$5:I$639,$A$5:$A$639,$A198,$C$5:$C$639,$C198-1,$D$5:$D$639,$D198))-1))) | R198: =IF(OR($A198="",J198="",$C198=""),"",IF(COUNTIFS($A$5:$A$639,$A198,$C$5:$C$639,$C198-1,$D$5:$D$639,$D198,J$5:J$639,"<>")=0,"",IF(OR(SUMIFS(J$5:J$639,$A$5:$A$639,$A198,$C$5:$C$639,$C198-1,$D$5:$D$639,$D198)=0,J198*SUMIFS(J$5:J$639,$A$5:$A$639,$A198,$C$5:$C$639,$C198-1,$D$5:$D$639,$D198)<0),"n.s.",ABS(J198)/ABS(SUMIFS(J$5:J$639,$A$5:$A$639,$A198,$C$5:$C$639,$C198-1,$D$5:$D$639,$D198))-1))) | S198: =IF(OR($A198="",K198="",$C198=""),"",IF(COUNTIFS($A$5:$A$639,$A198,$C$5:$C$639,$C198-1,$D$5:$D$639,$D198,K$5:K$639,"<>")=0,"",IF(OR(SUMIFS(K$5:K$639,$A$5:$A$639,$A198,$C$5:$C$639,$C198-1,$D$5:$D$639,$D198)=0,K198*SUMIFS(K$5:K$639,$A$5:$A$639,$A198,$C$5:$C$639,$C198-1,$D$5:$D$639,$D198)<0),"n.s.",ABS(K198)/ABS(SUMIFS(K$5:K$639,$A$5:$A$639,$A198,$C$5:$C$639,$C198-1,$D$5:$D$639,$D198))-1))) | T198: =IF(OR($A198="",L198="",$C198=""),"",IF(COUNTIFS($A$5:$A$639,$A198,$C$5:$C$639,$C198-1,$D$5:$D$639,$D198,L$5:L$639,"<>")=0,"",IF(OR(SUMIFS(L$5:L$639,$A$5:$A$639,$A198,$C$5:$C$639,$C198-1,$D$5:$D$639,$D198)=0,L198*SUMIFS(L$5:L$639,$A$5:$A$639,$A198,$C$5:$C$639,$C198-1,$D$5:$D$639,$D198)<0),"n.s.",ABS(L198)/ABS(SUMIFS(L$5:L$639,$A$5:$A$639,$A198,$C$5:$C$639,$C198-1,$D$5:$D$639,$D198))-1))) | U198: =IF(OR($A198="",M198="",$C198=""),"",IF(COUNTIFS($A$5:$A$639,$A198,$C$5:$C$639,$C198-1,$D$5:$D$639,$D198,M$5:M$639,"<>")=0,"",IF(OR(SUMIFS(M$5:M$639,$A$5:$A$639,$A198,$C$5:$C$639,$C198-1,$D$5:$D$639,$D198)=0,M198*SUMIFS(M$5:M$639,$A$5:$A$639,$A198,$C$5:$C$639,$C198-1,$D$5:$D$639,$D198)<0),"n.s.",ABS(M198)/ABS(SUMIFS(M$5:M$639,$A$5:$A$639,$A198,$C$5:$C$639,$C198-1,$D$5:$D$639,$D198))-1)))
A199: BNBC | B199: =IF(A199="","",IFERROR(VLOOKUP(A199,Titres!$A$2:$B$400,2,FALSE),"Ticker inconnu")) | C199: 2025 | D199: T3 | N199: =IF(A199="","",COUNT(H199:M199)/6) | O199: =IF(COUNT(H199:M199)=0,"",IF(LEN(IF(COUNT(I199,J199)=2,IF(J199>I199+1,"EBE > VA ",""),"")&IF(COUNT(H199,M199)=2,IF(ABS(M199)>ABS(H199),"RN > CA ",""),"")&IF(COUNT(H199,K199)=2,IF(ABS(K199)>ABS(H199),"RE > CA ",""),""))=0,"OK",IF(COUNT(I199,J199)=2,IF(J199>I199+1,"EBE > VA ",""),"")&IF(COUNT(H199,M199)=2,IF(ABS(M199)>ABS(H199),"RN > CA ",""),"")&IF(COUNT(H199,K199)=2,IF(ABS(K199)>ABS(H199),"RE > CA ",""),""))) | P199: =IF(OR($A199="",H199="",$C199=""),"",IF(COUNTIFS($A$5:$A$639,$A199,$C$5:$C$639,$C199-1,$D$5:$D$639,$D199,H$5:H$639,"<>")=0,"",IF(OR(SUMIFS(H$5:H$639,$A$5:$A$639,$A199,$C$5:$C$639,$C199-1,$D$5:$D$639,$D199)=0,H199*SUMIFS(H$5:H$639,$A$5:$A$639,$A199,$C$5:$C$639,$C199-1,$D$5:$D$639,$D199)<0),"n.s.",ABS(H199)/ABS(SUMIFS(H$5:H$639,$A$5:$A$639,$A199,$C$5:$C$639,$C199-1,$D$5:$D$639,$D199))-1))) | Q199: =IF(OR($A199="",I199="",$C199=""),"",IF(COUNTIFS($A$5:$A$639,$A199,$C$5:$C$639,$C199-1,$D$5:$D$639,$D199,I$5:I$639,"<>")=0,"",IF(OR(SUMIFS(I$5:I$639,$A$5:$A$639,$A199,$C$5:$C$639,$C199-1,$D$5:$D$639,$D199)=0,I199*SUMIFS(I$5:I$639,$A$5:$A$639,$A199,$C$5:$C$639,$C199-1,$D$5:$D$639,$D199)<0),"n.s.",ABS(I199)/ABS(SUMIFS(I$5:I$639,$A$5:$A$639,$A199,$C$5:$C$639,$C199-1,$D$5:$D$639,$D199))-1))) | R199: =IF(OR($A199="",J199="",$C199=""),"",IF(COUNTIFS($A$5:$A$639,$A199,$C$5:$C$639,$C199-1,$D$5:$D$639,$D199,J$5:J$639,"<>")=0,"",IF(OR(SUMIFS(J$5:J$639,$A$5:$A$639,$A199,$C$5:$C$639,$C199-1,$D$5:$D$639,$D199)=0,J199*SUMIFS(J$5:J$639,$A$5:$A$639,$A199,$C$5:$C$639,$C199-1,$D$5:$D$639,$D199)<0),"n.s.",ABS(J199)/ABS(SUMIFS(J$5:J$639,$A$5:$A$639,$A199,$C$5:$C$639,$C199-1,$D$5:$D$639,$D199))-1))) | S199: =IF(OR($A199="",K199="",$C199=""),"",IF(COUNTIFS($A$5:$A$639,$A199,$C$5:$C$639,$C199-1,$D$5:$D$639,$D199,K$5:K$639,"<>")=0,"",IF(OR(SUMIFS(K$5:K$639,$A$5:$A$639,$A199,$C$5:$C$639,$C199-1,$D$5:$D$639,$D199)=0,K199*SUMIFS(K$5:K$639,$A$5:$A$639,$A199,$C$5:$C$639,$C199-1,$D$5:$D$639,$D199)<0),"n.s.",ABS(K199)/ABS(SUMIFS(K$5:K$639,$A$5:$A$639,$A199,$C$5:$C$639,$C199-1,$D$5:$D$639,$D199))-1))) | T199: =IF(OR($A199="",L199="",$C199=""),"",IF(COUNTIFS($A$5:$A$639,$A199,$C$5:$C$639,$C199-1,$D$5:$D$639,$D199,L$5:L$639,"<>")=0,"",IF(OR(SUMIFS(L$5:L$639,$A$5:$A$639,$A199,$C$5:$C$639,$C199-1,$D$5:$D$639,$D199)=0,L199*SUMIFS(L$5:L$639,$A$5:$A$639,$A199,$C$5:$C$639,$C199-1,$D$5:$D$639,$D199)<0),"n.s.",ABS(L199)/ABS(SUMIFS(L$5:L$639,$A$5:$A$639,$A199,$C$5:$C$639,$C199-1,$D$5:$D$639,$D199))-1))) | U199: =IF(OR($A199="",M199="",$C199=""),"",IF(COUNTIFS($A$5:$A$639,$A199,$C$5:$C$639,$C199-1,$D$5:$D$639,$D199,M$5:M$639,"<>")=0,"",IF(OR(SUMIFS(M$5:M$639,$A$5:$A$639,$A199,$C$5:$C$639,$C199-1,$D$5:$D$639,$D199)=0,M199*SUMIFS(M$5:M$639,$A$5:$A$639,$A199,$C$5:$C$639,$C199-1,$D$5:$D$639,$D199)<0),"n.s.",ABS(M199)/ABS(SUMIFS(M$5:M$639,$A$5:$A$639,$A199,$C$5:$C$639,$C199-1,$D$5:$D$639,$D199))-1)))
